{
  "width": 48,
  "height": 26,
  "pixels": [
    {"x":0,"y":0,"r":0,"g":0,"b":0,"char":" ","brightness":0.00},
    {"x":1,"y":0,"r":0,"g":0,"b":0,"char":" ","brightness":0.00},
    {"x":2,"y":0,"r":0,"g":0,"b":0,"char":" ","brightness":0.00},
    {"x":3,"y":0,"r":0,"g":0,"b":0,"char":" ","brightness":0.00},
    {"x":4,"y":0,"r":0,"g":0,"b":0,"char":" ","brightness":0.00},
    {"x":5,"y":0,"r":0,"g":0,"b":0,"char":" ","brightness":0.00},
    {"x":6,"y":0,"r":0,"g":0,"b":0,"char":" ","brightness":0.00},
    {"x":7,"y":0,"r":0,"g":0,"b":0,"char":" ","brightness":0.00},
    {"x":8,"y":0,"r":0,"g":0,"b":0,"char":" ","brightness":0.00},
    {"x":9,"y":0,"r":0,"g":0,"b":0,"char":" ","brightness":0.00},
    {"x":10,"y":0,"r":0,"g":0,"b":0,"char":" ","brightness":0.00},
    {"x":11,"y":0,"r":0,"g":0,"b":0,"char":" ","brightness":0.00},
    {"x":12,"y":0,"r":0,"g":0,"b":0,"char":" ","brightness":0.00},
    {"x":13,"y":0,"r":0,"g":0,"b":0,"char":" ","brightness":0.00},
    {"x":14,"y":0,"r":0,"g":0,"b":0,"char":" ","brightness":0.00},
    {"x":15,"y":0,"r":0,"g":0,"b":0,"char":" ","brightness":0.00},
    {"x":16,"y":0,"r":0,"g":0,"b":0,"char":" ","brightness":0.00},
    {"x":17,"y":0,"r":0,"g":0,"b":0,"char":" ","brightness":0.00},
    {"x":18,"y":0,"r":0,"g":0,"b":0,"char":" ","brightness":0.00},
    {"x":19,"y":0,"r":0,"g":0,"b":0,"char":" ","brightness":0.00},
    {"x":20,"y":0,"r":0,"g":0,"b":0,"char":" ","brightness":0.00},
    {"x":21,"y":0,"r":0,"g":0,"b":0,"char":" ","brightness":0.00},
    {"x":22,"y":0,"r":0,"g":0,"b":0,"char":" ","brightness":0.00},
    {"x":23,"y":0,"r":0,"g":0,"b":0,"char":" ","brightness":0.00},
    {"x":24,"y":0,"r":0,"g":0,"b":0,"char":" ","brightness":0.00},
    {"x":25,"y":0,"r":0,"g":0,"b":0,"char":" ","brightness":0.00},
    {"x":26,"y":0,"r":0,"g":0,"b":0,"char":" ","brightness":0.00},
    {"x":27,"y":0,"r":0,"g":0,"b":0,"char":" ","brightness":0.00},
    {"x":28,"y":0,"r":0,"g":0,"b":0,"char":" ","brightness":0.00},
    {"x":29,"y":0,"r":0,"g":0,"b":0,"char":" ","brightness":0.00},
    {"x":30,"y":0,"r":0,"g":0,"b":0,"char":" ","brightness":0.00},
    {"x":31,"y":0,"r":0,"g":0,"b":0,"char":" ","brightness":0.00},
    {"x":32,"y":0,"r":0,"g":0,"b":0,"char":" ","brightness":0.00},
    {"x":33,"y":0,"r":0,"g":0,"b":0,"char":" ","brightness":0.00},
    {"x":34,"y":0,"r":0,"g":0,"b":0,"char":" ","brightness":0.00},
    {"x":35,"y":0,"r":0,"g":0,"b":0,"char":" ","brightness":0.00},
    {"x":36,"y":0,"r":0,"g":0,"b":0,"char":" ","brightness":0.00},
    {"x":37,"y":0,"r":0,"g":0,"b":0,"char":" ","brightness":0.00},
    {"x":38,"y":0,"r":0,"g":0,"b":0,"char":" ","brightness":0.00},
    {"x":39,"y":0,"r":0,"g":0,"b":0,"char":" ","brightness":0.00},
    {"x":40,"y":0,"r":0,"g":0,"b":0,"char":" ","brightness":0.00},
    {"x":41,"y":0,"r":0,"g":0,"b":0,"char":" ","brightness":0.00},
    {"x":42,"y":0,"r":0,"g":0,"b":0,"char":" ","brightness":0.00},
    {"x":43,"y":0,"r":0,"g":0,"b":0,"char":" ","brightness":0.00},
    {"x":44,"y":0,"r":0,"g":0,"b":0,"char":" ","brightness":0.00},
    {"x":45,"y":0,"r":0,"g":0,"b":0,"char":" ","brightness":0.00},
    {"x":46,"y":0,"r":0,"g":0,"b":0,"char":" ","brightness":0.00},
    {"x":47,"y":0,"r":0,"g":0,"b":0,"char":" ","brightness":0.00},
    {"x":0,"y":1,"r":0,"g":0,"b":0,"char":" ","brightness":0.00},
    {"x":1,"y":1,"r":0,"g":0,"b":0,"char":" ","brightness":0.00},
    {"x":2,"y":1,"r":0,"g":0,"b":0,"char":" ","brightness":0.00},
    {"x":3,"y":1,"r":0,"g":0,"b":0,"char":" ","brightness":0.00},
    {"x":4,"y":1,"r":0,"g":0,"b":0,"char":" ","brightness":0.00},
    {"x":5,"y":1,"r":0,"g":0,"b":0,"char":" ","brightness":0.00},
    {"x":6,"y":1,"r":0,"g":0,"b":0,"char":" ","brightness":0.00},
    {"x":7,"y":1,"r":0,"g":0,"b":0,"char":" ","brightness":0.00},
    {"x":8,"y":1,"r":0,"g":0,"b":0,"char":" ","brightness":0.00},
    {"x":9,"y":1,"r":0,"g":0,"b":0,"char":" ","brightness":0.00},
    {"x":10,"y":1,"r":0,"g":0,"b":0,"char":" ","brightness":0.00},
    {"x":11,"y":1,"r":0,"g":0,"b":0,"char":" ","brightness":0.00},
    {"x":12,"y":1,"r":0,"g":0,"b":0,"char":" ","brightness":0.00},
    {"x":13,"y":1,"r":0,"g":0,"b":0,"char":" ","brightness":0.00},
    {"x":14,"y":1,"r":0,"g":0,"b":0,"char":" ","brightness":0.00},
    {"x":15,"y":1,"r":0,"g":0,"b":0,"char":" ","brightness":0.00},
    {"x":16,"y":1,"r":0,"g":0,"b":0,"char":" ","brightness":0.00},
    {"x":17,"y":1,"r":0,"g":0,"b":0,"char":" ","brightness":0.00},
    {"x":18,"y":1,"r":0,"g":0,"b":0,"char":" ","brightness":0.00},
    {"x":19,"y":1,"r":0,"g":0,"b":0,"char":" ","brightness":0.00},
    {"x":20,"y":1,"r":0,"g":0,"b":0,"char":" ","brightness":0.00},
    {"x":21,"y":1,"r":0,"g":0,"b":0,"char":" ","brightness":0.00},
    {"x":22,"y":1,"r":0,"g":0,"b":0,"char":" ","brightness":0.00},
    {"x":23,"y":1,"r":0,"g":0,"b":0,"char":" ","brightness":0.00},
    {"x":24,"y":1,"r":0,"g":0,"b":0,"char":" ","brightness":0.00},
    {"x":25,"y":1,"r":0,"g":0,"b":0,"char":" ","brightness":0.00},
    {"x":26,"y":1,"r":0,"g":0,"b":0,"char":" ","brightness":0.00},
    {"x":27,"y":1,"r":0,"g":0,"b":0,"char":" ","brightness":0.00},
    {"x":28,"y":1,"r":0,"g":0,"b":0,"char":" ","brightness":0.00},
    {"x":29,"y":1,"r":0,"g":0,"b":0,"char":" ","brightness":0.00},
    {"x":30,"y":1,"r":0,"g":0,"b":0,"char":" ","brightness":0.00},
    {"x":31,"y":1,"r":0,"g":0,"b":0,"char":" ","brightness":0.00},
    {"x":32,"y":1,"r":0,"g":0,"b":0,"char":" ","brightness":0.00},
    {"x":33,"y":1,"r":0,"g":0,"b":0,"char":" ","brightness":0.00},
    {"x":34,"y":1,"r":0,"g":0,"b":0,"char":" ","brightness":0.00},
    {"x":35,"y":1,"r":0,"g":0,"b":0,"char":" ","brightness":0.00},
    {"x":36,"y":1,"r":0,"g":0,"b":0,"char":" ","brightness":0.00},
    {"x":37,"y":1,"r":0,"g":0,"b":0,"char":" ","brightness":0.00},
    {"x":38,"y":1,"r":0,"g":0,"b":0,"char":" ","brightness":0.00},
    {"x":39,"y":1,"r":0,"g":0,"b":0,"char":" ","brightness":0.00},
    {"x":40,"y":1,"r":0,"g":0,"b":0,"char":" ","brightness":0.00},
    {"x":41,"y":1,"r":0,"g":0,"b":0,"char":" ","brightness":0.00},
    {"x":42,"y":1,"r":0,"g":0,"b":0,"char":" ","brightness":0.00},
    {"x":43,"y":1,"r":0,"g":0,"b":0,"char":" ","brightness":0.00},
    {"x":44,"y":1,"r":0,"g":0,"b":0,"char":" ","brightness":0.00},
    {"x":45,"y":1,"r":0,"g":0,"b":0,"char":" ","brightness":0.00},
    {"x":46,"y":1,"r":0,"g":0,"b":0,"char":" ","brightness":0.00},
    {"x":47,"y":1,"r":0,"g":0,"b":0,"char":" ","brightness":0.00},
    {"x":0,"y":2,"r":0,"g":0,"b":0,"char":" ","brightness":0.00},
    {"x":1,"y":2,"r":0,"g":0,"b":0,"char":" ","brightness":0.00},
    {"x":2,"y":2,"r":0,"g":0,"b":0,"char":" ","brightness":0.00},
    {"x":3,"y":2,"r":0,"g":0,"b":0,"char":" ","brightness":0.00},
    {"x":4,"y":2,"r":0,"g":0,"b":0,"char":" ","brightness":0.00},
    {"x":5,"y":2,"r":0,"g":0,"b":0,"char":" ","brightness":0.00},
    {"x":6,"y":2,"r":0,"g":0,"b":0,"char":" ","brightness":0.00},
    {"x":7,"y":2,"r":0,"g":0,"b":0,"char":" ","brightness":0.00},
    {"x":8,"y":2,"r":0,"g":0,"b":0,"char":" ","brightness":0.00},
    {"x":9,"y":2,"r":0,"g":0,"b":0,"char":" ","brightness":0.00},
    {"x":10,"y":2,"r":0,"g":0,"b":0,"char":" ","brightness":0.00},
    {"x":11,"y":2,"r":0,"g":0,"b":0,"char":" ","brightness":0.00},
    {"x":12,"y":2,"r":0,"g":0,"b":0,"char":" ","brightness":0.00},
    {"x":13,"y":2,"r":0,"g":0,"b":0,"char":" ","brightness":0.00},
    {"x":14,"y":2,"r":0,"g":0,"b":0,"char":" ","brightness":0.00},
    {"x":15,"y":2,"r":0,"g":0,"b":0,"char":" ","brightness":0.00},
    {"x":16,"y":2,"r":0,"g":0,"b":0,"char":" ","brightness":0.00},
    {"x":17,"y":2,"r":0,"g":0,"b":0,"char":" ","brightness":0.00},
    {"x":18,"y":2,"r":0,"g":0,"b":0,"char":" ","brightness":0.00},
    {"x":19,"y":2,"r":0,"g":0,"b":0,"char":" ","brightness":0.00},
    {"x":20,"y":2,"r":0,"g":0,"b":0,"char":" ","brightness":0.00},
    {"x":21,"y":2,"r":0,"g":0,"b":0,"char":" ","brightness":0.00},
    {"x":22,"y":2,"r":0,"g":0,"b":0,"char":" ","brightness":0.00},
    {"x":23,"y":2,"r":0,"g":0,"b":0,"char":" ","brightness":0.00},
    {"x":24,"y":2,"r":0,"g":0,"b":0,"char":" ","brightness":0.00},
    {"x":25,"y":2,"r":0,"g":0,"b":0,"char":" ","brightness":0.00},
    {"x":26,"y":2,"r":0,"g":0,"b":0,"char":" ","brightness":0.00},
    {"x":27,"y":2,"r":0,"g":0,"b":0,"char":" ","brightness":0.00},
    {"x":28,"y":2,"r":0,"g":0,"b":0,"char":" ","brightness":0.00},
    {"x":29,"y":2,"r":0,"g":0,"b":0,"char":" ","brightness":0.00},
    {"x":30,"y":2,"r":0,"g":0,"b":0,"char":" ","brightness":0.00},
    {"x":31,"y":2,"r":0,"g":0,"b":0,"char":" ","brightness":0.00},
    {"x":32,"y":2,"r":0,"g":0,"b":0,"char":" ","brightness":0.00},
    {"x":33,"y":2,"r":0,"g":0,"b":0,"char":" ","brightness":0.00},
    {"x":34,"y":2,"r":0,"g":0,"b":0,"char":" ","brightness":0.00},
    {"x":35,"y":2,"r":0,"g":0,"b":0,"char":" ","brightness":0.00},
    {"x":36,"y":2,"r":0,"g":0,"b":0,"char":" ","brightness":0.00},
    {"x":37,"y":2,"r":0,"g":0,"b":0,"char":" ","brightness":0.00},
    {"x":38,"y":2,"r":0,"g":0,"b":0,"char":" ","brightness":0.00},
    {"x":39,"y":2,"r":0,"g":0,"b":0,"char":" ","brightness":0.00},
    {"x":40,"y":2,"r":0,"g":0,"b":0,"char":" ","brightness":0.00},
    {"x":41,"y":2,"r":0,"g":0,"b":0,"char":" ","brightness":0.00},
    {"x":42,"y":2,"r":0,"g":0,"b":0,"char":" ","brightness":0.00},
    {"x":43,"y":2,"r":0,"g":0,"b":0,"char":" ","brightness":0.00},
    {"x":44,"y":2,"r":0,"g":0,"b":0,"char":" ","brightness":0.00},
    {"x":45,"y":2,"r":0,"g":0,"b":0,"char":" ","brightness":0.00},
    {"x":46,"y":2,"r":0,"g":0,"b":0,"char":" ","brightness":0.00},
    {"x":47,"y":2,"r":0,"g":0,"b":0,"char":" ","brightness":0.00},
    {"x":0,"y":3,"r":0,"g":0,"b":0,"char":" ","brightness":0.00},
    {"x":1,"y":3,"r":0,"g":0,"b":0,"char":" ","brightness":0.00},
    {"x":2,"y":3,"r":0,"g":0,"b":0,"char":" ","brightness":0.00},
    {"x":3,"y":3,"r":0,"g":0,"b":0,"char":" ","brightness":0.00},
    {"x":4,"y":3,"r":0,"g":0,"b":0,"char":" ","brightness":0.00},
    {"x":5,"y":3,"r":0,"g":0,"b":0,"char":" ","brightness":0.00},
    {"x":6,"y":3,"r":0,"g":0,"b":0,"char":" ","brightness":0.00},
    {"x":7,"y":3,"r":0,"g":0,"b":0,"char":" ","brightness":0.00},
    {"x":8,"y":3,"r":0,"g":0,"b":0,"char":" ","brightness":0.00},
    {"x":9,"y":3,"r":0,"g":0,"b":0,"char":" ","brightness":0.00},
    {"x":10,"y":3,"r":0,"g":0,"b":0,"char":" ","brightness":0.00},
    {"x":11,"y":3,"r":0,"g":0,"b":0,"char":" ","brightness":0.00},
    {"x":12,"y":3,"r":0,"g":0,"b":0,"char":" ","brightness":0.00},
    {"x":13,"y":3,"r":0,"g":0,"b":0,"char":" ","brightness":0.00},
    {"x":14,"y":3,"r":0,"g":0,"b":0,"char":" ","brightness":0.00},
    {"x":15,"y":3,"r":0,"g":0,"b":0,"char":" ","brightness":0.00},
    {"x":16,"y":3,"r":0,"g":0,"b":0,"char":" ","brightness":0.00},
    {"x":17,"y":3,"r":0,"g":0,"b":0,"char":" ","brightness":0.00},
    {"x":18,"y":3,"r":0,"g":0,"b":0,"char":" ","brightness":0.00},
    {"x":19,"y":3,"r":0,"g":0,"b":0,"char":" ","brightness":0.00},
    {"x":20,"y":3,"r":0,"g":0,"b":0,"char":" ","brightness":0.00},
    {"x":21,"y":3,"r":0,"g":0,"b":0,"char":" ","brightness":0.00},
    {"x":22,"y":3,"r":0,"g":0,"b":0,"char":" ","brightness":0.00},
    {"x":23,"y":3,"r":0,"g":0,"b":0,"char":" ","brightness":0.00},
    {"x":24,"y":3,"r":0,"g":0,"b":0,"char":" ","brightness":0.00},
    {"x":25,"y":3,"r":0,"g":0,"b":0,"char":" ","brightness":0.00},
    {"x":26,"y":3,"r":0,"g":0,"b":0,"char":" ","brightness":0.00},
    {"x":27,"y":3,"r":0,"g":0,"b":0,"char":" ","brightness":0.00},
    {"x":28,"y":3,"r":0,"g":0,"b":0,"char":" ","brightness":0.00},
    {"x":29,"y":3,"r":0,"g":0,"b":0,"char":" ","brightness":0.00},
    {"x":30,"y":3,"r":0,"g":0,"b":0,"char":" ","brightness":0.00},
    {"x":31,"y":3,"r":0,"g":0,"b":0,"char":" ","brightness":0.00},
    {"x":32,"y":3,"r":0,"g":0,"b":0,"char":" ","brightness":0.00},
    {"x":33,"y":3,"r":0,"g":0,"b":0,"char":" ","brightness":0.00},
    {"x":34,"y":3,"r":0,"g":0,"b":0,"char":" ","brightness":0.00},
    {"x":35,"y":3,"r":0,"g":0,"b":0,"char":" ","brightness":0.00},
    {"x":36,"y":3,"r":0,"g":0,"b":0,"char":" ","brightness":0.00},
    {"x":37,"y":3,"r":0,"g":0,"b":0,"char":" ","brightness":0.00},
    {"x":38,"y":3,"r":0,"g":0,"b":0,"char":" ","brightness":0.00},
    {"x":39,"y":3,"r":0,"g":0,"b":0,"char":" ","brightness":0.00},
    {"x":40,"y":3,"r":0,"g":0,"b":0,"char":" ","brightness":0.00},
    {"x":41,"y":3,"r":0,"g":0,"b":0,"char":" ","brightness":0.00},
    {"x":42,"y":3,"r":0,"g":0,"b":0,"char":" ","brightness":0.00},
    {"x":43,"y":3,"r":0,"g":0,"b":0,"char":" ","brightness":0.00},
    {"x":44,"y":3,"r":0,"g":0,"b":0,"char":" ","brightness":0.00},
    {"x":45,"y":3,"r":0,"g":0,"b":0,"char":" ","brightness":0.00},
    {"x":46,"y":3,"r":0,"g":0,"b":0,"char":" ","brightness":0.00},
    {"x":47,"y":3,"r":0,"g":0,"b":0,"char":" ","brightness":0.00},
    {"x":0,"y":4,"r":0,"g":0,"b":0,"char":" ","brightness":0.00},
    {"x":1,"y":4,"r":0,"g":0,"b":0,"char":" ","brightness":0.00},
    {"x":2,"y":4,"r":0,"g":0,"b":0,"char":" ","brightness":0.00},
    {"x":3,"y":4,"r":0,"g":0,"b":0,"char":" ","brightness":0.00},
    {"x":4,"y":4,"r":0,"g":0,"b":0,"char":" ","brightness":0.00},
    {"x":5,"y":4,"r":0,"g":0,"b":0,"char":" ","brightness":0.00},
    {"x":6,"y":4,"r":0,"g":0,"b":0,"char":" ","brightness":0.00},
    {"x":7,"y":4,"r":0,"g":0,"b":0,"char":" ","brightness":0.00},
    {"x":8,"y":4,"r":0,"g":0,"b":0,"char":" ","brightness":0.00},
    {"x":9,"y":4,"r":0,"g":0,"b":0,"char":" ","brightness":0.00},
    {"x":10,"y":4,"r":0,"g":0,"b":0,"char":" ","brightness":0.00},
    {"x":11,"y":4,"r":0,"g":0,"b":0,"char":" ","brightness":0.00},
    {"x":12,"y":4,"r":0,"g":0,"b":0,"char":" ","brightness":0.00},
    {"x":13,"y":4,"r":0,"g":0,"b":0,"char":" ","brightness":0.00},
    {"x":14,"y":4,"r":0,"g":0,"b":0,"char":" ","brightness":0.00},
    {"x":15,"y":4,"r":0,"g":0,"b":0,"char":" ","brightness":0.00},
    {"x":16,"y":4,"r":0,"g":0,"b":0,"char":" ","brightness":0.00},
    {"x":17,"y":4,"r":0,"g":0,"b":0,"char":" ","brightness":0.00},
    {"x":18,"y":4,"r":99,"g":84,"b":181,"char":" ","brightness":99.54},
    {"x":19,"y":4,"r":138,"g":1,"b":130,"char":" ","brightness":56.67},
    {"x":20,"y":4,"r":122,"g":75,"b":193,"char":" ","brightness":102.50},
    {"x":21,"y":4,"r":154,"g":80,"b":167,"char":" ","brightness":112.04},
    {"x":22,"y":4,"r":247,"g":128,"b":137,"char":" ","brightness":164.61},
    {"x":23,"y":4,"r":226,"g":118,"b":143,"char":" ","brightness":153.14},
    {"x":24,"y":4,"r":0,"g":0,"b":0,"char":" ","brightness":0.00},
    {"x":25,"y":4,"r":0,"g":0,"b":0,"char":" ","brightness":0.00},
    {"x":26,"y":4,"r":0,"g":0,"b":0,"char":" ","brightness":0.00},
    {"x":27,"y":4,"r":0,"g":0,"b":0,"char":" ","brightness":0.00},
    {"x":28,"y":4,"r":0,"g":0,"b":0,"char":" ","brightness":0.00},
    {"x":29,"y":4,"r":0,"g":0,"b":0,"char":" ","brightness":0.00},
    {"x":30,"y":4,"r":0,"g":0,"b":0,"char":" ","brightness":0.00},
    {"x":31,"y":4,"r":0,"g":0,"b":0,"char":" ","brightness":0.00},
    {"x":32,"y":4,"r":0,"g":0,"b":0,"char":" ","brightness":0.00},
    {"x":33,"y":4,"r":0,"g":0,"b":0,"char":" ","brightness":0.00},
    {"x":34,"y":4,"r":0,"g":0,"b":0,"char":" ","brightness":0.00},
    {"x":35,"y":4,"r":0,"g":0,"b":0,"char":" ","brightness":0.00},
    {"x":36,"y":4,"r":0,"g":0,"b":0,"char":" ","brightness":0.00},
    {"x":37,"y":4,"r":0,"g":0,"b":0,"char":" ","brightness":0.00},
    {"x":38,"y":4,"r":0,"g":0,"b":0,"char":" ","brightness":0.00},
    {"x":39,"y":4,"r":0,"g":0,"b":0,"char":" ","brightness":0.00},
    {"x":40,"y":4,"r":0,"g":0,"b":0,"char":" ","brightness":0.00},
    {"x":41,"y":4,"r":0,"g":0,"b":0,"char":" ","brightness":0.00},
    {"x":42,"y":4,"r":0,"g":0,"b":0,"char":" ","brightness":0.00},
    {"x":43,"y":4,"r":0,"g":0,"b":0,"char":" ","brightness":0.00},
    {"x":44,"y":4,"r":0,"g":0,"b":0,"char":" ","brightness":0.00},
    {"x":45,"y":4,"r":0,"g":0,"b":0,"char":" ","brightness":0.00},
    {"x":46,"y":4,"r":0,"g":0,"b":0,"char":" ","brightness":0.00},
    {"x":47,"y":4,"r":0,"g":0,"b":0,"char":" ","brightness":0.00},
    {"x":0,"y":5,"r":0,"g":0,"b":0,"char":" ","brightness":0.00},
    {"x":1,"y":5,"r":0,"g":0,"b":0,"char":" ","brightness":0.00},
    {"x":2,"y":5,"r":0,"g":0,"b":0,"char":" ","brightness":0.00},
    {"x":3,"y":5,"r":0,"g":0,"b":0,"char":" ","brightness":0.00},
    {"x":4,"y":5,"r":0,"g":0,"b":0,"char":" ","brightness":0.00},
    {"x":5,"y":5,"r":0,"g":0,"b":0,"char":" ","brightness":0.00},
    {"x":6,"y":5,"r":0,"g":0,"b":0,"char":" ","brightness":0.00},
    {"x":7,"y":5,"r":0,"g":0,"b":0,"char":" ","brightness":0.00},
    {"x":8,"y":5,"r":0,"g":0,"b":0,"char":" ","brightness":0.00},
    {"x":9,"y":5,"r":0,"g":0,"b":0,"char":" ","brightness":0.00},
    {"x":10,"y":5,"r":0,"g":0,"b":0,"char":" ","brightness":0.00},
    {"x":11,"y":5,"r":0,"g":0,"b":0,"char":" ","brightness":0.00},
    {"x":12,"y":5,"r":0,"g":0,"b":0,"char":" ","brightness":0.00},
    {"x":13,"y":5,"r":0,"g":0,"b":0,"char":" ","brightness":0.00},
    {"x":14,"y":5,"r":0,"g":0,"b":0,"char":" ","brightness":0.00},
    {"x":15,"y":5,"r":0,"g":0,"b":0,"char":" ","brightness":0.00},
    {"x":16,"y":5,"r":0,"g":0,"b":0,"char":" ","brightness":0.00},
    {"x":17,"y":5,"r":97,"g":93,"b":187,"char":" ","brightness":104.91},
    {"x":18,"y":5,"r":96,"g":97,"b":190,"char":" ","brightness":107.30},
    {"x":19,"y":5,"r":133,"g":83,"b":213,"char":" ","brightness":112.77},
    {"x":20,"y":5,"r":117,"g":74,"b":184,"char":"*","brightness":99.40},
    {"x":21,"y":5,"r":152,"g":79,"b":161,"char":"#","brightness":110.17},
    {"x":22,"y":5,"r":255,"g":216,"b":68,"char":" ","brightness":210.79},
    {"x":23,"y":5,"r":228,"g":118,"b":135,"char":" ","brightness":152.83},
    {"x":24,"y":5,"r":153,"g":80,"b":60,"char":" ","brightness":99.55},
    {"x":25,"y":5,"r":168,"g":86,"b":87,"char":" ","brightness":110.63},
    {"x":26,"y":5,"r":0,"g":0,"b":0,"char":" ","brightness":0.00},
    {"x":27,"y":5,"r":0,"g":0,"b":0,"char":" ","brightness":0.00},
    {"x":28,"y":5,"r":0,"g":0,"b":0,"char":" ","brightness":0.00},
    {"x":29,"y":5,"r":0,"g":0,"b":0,"char":" ","brightness":0.00},
    {"x":30,"y":5,"r":0,"g":0,"b":0,"char":" ","brightness":0.00},
    {"x":31,"y":5,"r":0,"g":0,"b":0,"char":" ","brightness":0.00},
    {"x":32,"y":5,"r":0,"g":0,"b":0,"char":" ","brightness":0.00},
    {"x":33,"y":5,"r":0,"g":0,"b":0,"char":" ","brightness":0.00},
    {"x":34,"y":5,"r":0,"g":0,"b":0,"char":" ","brightness":0.00},
    {"x":35,"y":5,"r":0,"g":0,"b":0,"char":" ","brightness":0.00},
    {"x":36,"y":5,"r":0,"g":0,"b":0,"char":" ","brightness":0.00},
    {"x":37,"y":5,"r":0,"g":0,"b":0,"char":" ","brightness":0.00},
    {"x":38,"y":5,"r":0,"g":0,"b":0,"char":" ","brightness":0.00},
    {"x":39,"y":5,"r":0,"g":0,"b":0,"char":" ","brightness":0.00},
    {"x":40,"y":5,"r":0,"g":0,"b":0,"char":" ","brightness":0.00},
    {"x":41,"y":5,"r":0,"g":0,"b":0,"char":" ","brightness":0.00},
    {"x":42,"y":5,"r":0,"g":0,"b":0,"char":" ","brightness":0.00},
    {"x":43,"y":5,"r":0,"g":0,"b":0,"char":" ","brightness":0.00},
    {"x":44,"y":5,"r":0,"g":0,"b":0,"char":" ","brightness":0.00},
    {"x":45,"y":5,"r":0,"g":0,"b":0,"char":" ","brightness":0.00},
    {"x":46,"y":5,"r":0,"g":0,"b":0,"char":" ","brightness":0.00},
    {"x":47,"y":5,"r":0,"g":0,"b":0,"char":" ","brightness":0.00},
    {"x":0,"y":6,"r":0,"g":0,"b":0,"char":" ","brightness":0.00},
    {"x":1,"y":6,"r":0,"g":0,"b":0,"char":" ","brightness":0.00},
    {"x":2,"y":6,"r":0,"g":0,"b":0,"char":" ","brightness":0.00},
    {"x":3,"y":6,"r":0,"g":0,"b":0,"char":" ","brightness":0.00},
    {"x":4,"y":6,"r":0,"g":0,"b":0,"char":" ","brightness":0.00},
    {"x":5,"y":6,"r":0,"g":0,"b":0,"char":" ","brightness":0.00},
    {"x":6,"y":6,"r":0,"g":0,"b":0,"char":" ","brightness":0.00},
    {"x":7,"y":6,"r":0,"g":0,"b":0,"char":" ","brightness":0.00},
    {"x":8,"y":6,"r":0,"g":0,"b":0,"char":" ","brightness":0.00},
    {"x":9,"y":6,"r":0,"g":0,"b":0,"char":" ","brightness":0.00},
    {"x":10,"y":6,"r":0,"g":0,"b":0,"char":" ","brightness":0.00},
    {"x":11,"y":6,"r":0,"g":0,"b":0,"char":" ","brightness":0.00},
    {"x":12,"y":6,"r":0,"g":0,"b":0,"char":" ","brightness":0.00},
    {"x":13,"y":6,"r":0,"g":0,"b":0,"char":" ","brightness":0.00},
    {"x":14,"y":6,"r":0,"g":0,"b":0,"char":" ","brightness":0.00},
    {"x":15,"y":6,"r":87,"g":85,"b":169,"char":" ","brightness":95.17},
    {"x":16,"y":6,"r":230,"g":216,"b":255,"char":" ","brightness":224.63},
    {"x":17,"y":6,"r":116,"g":112,"b":226,"char":" ","brightness":126.19},
    {"x":18,"y":6,"r":86,"g":128,"b":206,"char":" ","brightness":124.33},
    {"x":19,"y":6,"r":117,"g":89,"b":205,"char":"#","brightness":110.60},
    {"x":20,"y":6,"r":124,"g":69,"b":194,"char":"*","brightness":99.70},
    {"x":21,"y":6,"r":138,"g":69,"b":185,"char":"*","brightness":102.86},
    {"x":22,"y":6,"r":186,"g":93,"b":163,"char":"#","brightness":128.79},
    {"x":23,"y":6,"r":242,"g":125,"b":127,"char":"%","brightness":160.21},
    {"x":24,"y":6,"r":255,"g":160,"b":236,"char":" ","brightness":197.07},
    {"x":25,"y":6,"r":237,"g":122,"b":118,"char":" ","brightness":155.93},
    {"x":26,"y":6,"r":255,"g":148,"b":147,"char":" ","brightness":179.88},
    {"x":27,"y":6,"r":158,"g":81,"b":82,"char":" ","brightness":104.14},
    {"x":28,"y":6,"r":0,"g":0,"b":0,"char":" ","brightness":0.00},
    {"x":29,"y":6,"r":0,"g":0,"b":0,"char":" ","brightness":0.00},
    {"x":30,"y":6,"r":0,"g":0,"b":0,"char":" ","brightness":0.00},
    {"x":31,"y":6,"r":0,"g":0,"b":0,"char":" ","brightness":0.00},
    {"x":32,"y":6,"r":0,"g":0,"b":0,"char":" ","brightness":0.00},
    {"x":33,"y":6,"r":0,"g":0,"b":0,"char":" ","brightness":0.00},
    {"x":34,"y":6,"r":0,"g":0,"b":0,"char":" ","brightness":0.00},
    {"x":35,"y":6,"r":0,"g":0,"b":0,"char":" ","brightness":0.00},
    {"x":36,"y":6,"r":0,"g":0,"b":0,"char":" ","brightness":0.00},
    {"x":37,"y":6,"r":0,"g":0,"b":0,"char":" ","brightness":0.00},
    {"x":38,"y":6,"r":0,"g":0,"b":0,"char":" ","brightness":0.00},
    {"x":39,"y":6,"r":0,"g":0,"b":0,"char":" ","brightness":0.00},
    {"x":40,"y":6,"r":0,"g":0,"b":0,"char":" ","brightness":0.00},
    {"x":41,"y":6,"r":0,"g":0,"b":0,"char":" ","brightness":0.00},
    {"x":42,"y":6,"r":0,"g":0,"b":0,"char":" ","brightness":0.00},
    {"x":43,"y":6,"r":0,"g":0,"b":0,"char":" ","brightness":0.00},
    {"x":44,"y":6,"r":0,"g":0,"b":0,"char":" ","brightness":0.00},
    {"x":45,"y":6,"r":0,"g":0,"b":0,"char":" ","brightness":0.00},
    {"x":46,"y":6,"r":0,"g":0,"b":0,"char":" ","brightness":0.00},
    {"x":47,"y":6,"r":0,"g":0,"b":0,"char":" ","brightness":0.00},
    {"x":0,"y":7,"r":0,"g":0,"b":0,"char":" ","brightness":0.00},
    {"x":1,"y":7,"r":0,"g":0,"b":0,"char":" ","brightness":0.00},
    {"x":2,"y":7,"r":0,"g":0,"b":0,"char":" ","brightness":0.00},
    {"x":3,"y":7,"r":0,"g":0,"b":0,"char":" ","brightness":0.00},
    {"x":4,"y":7,"r":0,"g":0,"b":0,"char":" ","brightness":0.00},
    {"x":5,"y":7,"r":0,"g":0,"b":0,"char":" ","brightness":0.00},
    {"x":6,"y":7,"r":0,"g":0,"b":0,"char":" ","brightness":0.00},
    {"x":7,"y":7,"r":0,"g":0,"b":0,"char":" ","brightness":0.00},
    {"x":8,"y":7,"r":0,"g":0,"b":0,"char":" ","brightness":0.00},
    {"x":9,"y":7,"r":0,"g":0,"b":0,"char":" ","brightness":0.00},
    {"x":10,"y":7,"r":0,"g":0,"b":0,"char":" ","brightness":0.00},
    {"x":11,"y":7,"r":0,"g":0,"b":0,"char":" ","brightness":0.00},
    {"x":12,"y":7,"r":0,"g":0,"b":0,"char":" ","brightness":0.00},
    {"x":13,"y":7,"r":0,"g":0,"b":0,"char":" ","brightness":0.00},
    {"x":14,"y":7,"r":118,"g":117,"b":232,"char":" ","brightness":130.41},
    {"x":15,"y":7,"r":115,"g":116,"b":226,"char":" ","brightness":128.24},
    {"x":16,"y":7,"r":132,"g":126,"b":255,"char":" ","brightness":142.50},
    {"x":17,"y":7,"r":116,"g":119,"b":232,"char":"#","brightness":130.98},
    {"x":18,"y":7,"r":123,"g":97,"b":218,"char":"#","brightness":118.57},
    {"x":19,"y":7,"r":125,"g":73,"b":198,"char":"*","brightness":102.80},
    {"x":20,"y":7,"r":127,"g":63,"b":191,"char":"*","brightness":96.73},
    {"x":21,"y":7,"r":126,"g":63,"b":191,"char":"*","brightness":96.43},
    {"x":22,"y":7,"r":137,"g":68,"b":187,"char":"*","brightness":102.20},
    {"x":23,"y":7,"r":185,"g":93,"b":158,"char":"#","brightness":127.92},
    {"x":24,"y":7,"r":236,"g":119,"b":127,"char":"%","brightness":154.89},
    {"x":25,"y":7,"r":255,"g":132,"b":119,"char":"%","brightness":167.29},
    {"x":26,"y":7,"r":255,"g":129,"b":127,"char":" ","brightness":166.45},
    {"x":27,"y":7,"r":195,"g":101,"b":102,"char":" ","brightness":129.22},
    {"x":28,"y":7,"r":201,"g":104,"b":105,"char":" ","brightness":133.12},
    {"x":29,"y":7,"r":0,"g":0,"b":0,"char":" ","brightness":0.00},
    {"x":30,"y":7,"r":0,"g":0,"b":0,"char":" ","brightness":0.00},
    {"x":31,"y":7,"r":0,"g":0,"b":0,"char":" ","brightness":0.00},
    {"x":32,"y":7,"r":0,"g":0,"b":0,"char":" ","brightness":0.00},
    {"x":33,"y":7,"r":0,"g":0,"b":0,"char":" ","brightness":0.00},
    {"x":34,"y":7,"r":0,"g":0,"b":0,"char":" ","brightness":0.00},
    {"x":35,"y":7,"r":0,"g":0,"b":0,"char":" ","brightness":0.00},
    {"x":36,"y":7,"r":0,"g":0,"b":0,"char":" ","brightness":0.00},
    {"x":37,"y":7,"r":0,"g":0,"b":0,"char":" ","brightness":0.00},
    {"x":38,"y":7,"r":0,"g":0,"b":0,"char":" ","brightness":0.00},
    {"x":39,"y":7,"r":0,"g":0,"b":0,"char":" ","brightness":0.00},
    {"x":40,"y":7,"r":0,"g":0,"b":0,"char":" ","brightness":0.00},
    {"x":41,"y":7,"r":0,"g":0,"b":0,"char":" ","brightness":0.00},
    {"x":42,"y":7,"r":0,"g":0,"b":0,"char":" ","brightness":0.00},
    {"x":43,"y":7,"r":0,"g":0,"b":0,"char":" ","brightness":0.00},
    {"x":44,"y":7,"r":0,"g":0,"b":0,"char":" ","brightness":0.00},
    {"x":45,"y":7,"r":0,"g":0,"b":0,"char":" ","brightness":0.00},
    {"x":46,"y":7,"r":0,"g":0,"b":0,"char":" ","brightness":0.00},
    {"x":47,"y":7,"r":0,"g":0,"b":0,"char":" ","brightness":0.00},
    {"x":0,"y":8,"r":0,"g":0,"b":0,"char":" ","brightness":0.00},
    {"x":1,"y":8,"r":0,"g":0,"b":0,"char":" ","brightness":0.00},
    {"x":2,"y":8,"r":0,"g":0,"b":0,"char":" ","brightness":0.00},
    {"x":3,"y":8,"r":0,"g":0,"b":0,"char":" ","brightness":0.00},
    {"x":4,"y":8,"r":0,"g":0,"b":0,"char":" ","brightness":0.00},
    {"x":5,"y":8,"r":0,"g":0,"b":0,"char":" ","brightness":0.00},
    {"x":6,"y":8,"r":0,"g":0,"b":0,"char":" ","brightness":0.00},
    {"x":7,"y":8,"r":0,"g":0,"b":0,"char":" ","brightness":0.00},
    {"x":8,"y":8,"r":0,"g":0,"b":0,"char":" ","brightness":0.00},
    {"x":9,"y":8,"r":0,"g":0,"b":0,"char":" ","brightness":0.00},
    {"x":10,"y":8,"r":0,"g":0,"b":0,"char":" ","brightness":0.00},
    {"x":11,"y":8,"r":0,"g":0,"b":0,"char":" ","brightness":0.00},
    {"x":12,"y":8,"r":123,"g":120,"b":218,"char":" ","brightness":132.07},
    {"x":13,"y":8,"r":127,"g":126,"b":252,"char":" ","brightness":140.66},
    {"x":14,"y":8,"r":124,"g":123,"b":244,"char":" ","brightness":137.09},
    {"x":15,"y":8,"r":70,"g":105,"b":151,"char":" ","brightness":99.78},
    {"x":16,"y":8,"r":123,"g":122,"b":241,"char":"#","brightness":135.86},
    {"x":17,"y":8,"r":125,"g":100,"b":224,"char":"#","brightness":121.61},
    {"x":18,"y":8,"r":127,"g":71,"b":199,"char":"*","brightness":102.34},
    {"x":19,"y":8,"r":127,"g":63,"b":191,"char":"*","brightness":96.73},
    {"x":20,"y":8,"r":127,"g":63,"b":191,"char":"*","brightness":96.73},
    {"x":21,"y":8,"r":127,"g":63,"b":191,"char":"*","brightness":96.73},
    {"x":22,"y":8,"r":126,"g":63,"b":191,"char":"*","brightness":96.43},
    {"x":23,"y":8,"r":131,"g":65,"b":189,"char":"*","brightness":98.87},
    {"x":24,"y":8,"r":181,"g":90,"b":164,"char":"#","brightness":125.64},
    {"x":25,"y":8,"r":238,"g":120,"b":132,"char":"%","brightness":156.65},
    {"x":26,"y":8,"r":250,"g":127,"b":122,"char":"%","brightness":163.21},
    {"x":27,"y":8,"r":142,"g":77,"b":81,"char":" ","brightness":96.89},
    {"x":28,"y":8,"r":232,"g":118,"b":118,"char":" ","brightness":152.09},
    {"x":29,"y":8,"r":251,"g":120,"b":100,"char":" ","brightness":156.89},
    {"x":30,"y":8,"r":244,"g":126,"b":131,"char":" ","brightness":161.85},
    {"x":31,"y":8,"r":0,"g":0,"b":0,"char":" ","brightness":0.00},
    {"x":32,"y":8,"r":0,"g":0,"b":0,"char":" ","brightness":0.00},
    {"x":33,"y":8,"r":0,"g":0,"b":0,"char":" ","brightness":0.00},
    {"x":34,"y":8,"r":0,"g":0,"b":0,"char":" ","brightness":0.00},
    {"x":35,"y":8,"r":0,"g":0,"b":0,"char":" ","brightness":0.00},
    {"x":36,"y":8,"r":0,"g":0,"b":0,"char":" ","brightness":0.00},
    {"x":37,"y":8,"r":0,"g":0,"b":0,"char":" ","brightness":0.00},
    {"x":38,"y":8,"r":0,"g":0,"b":0,"char":" ","brightness":0.00},
    {"x":39,"y":8,"r":0,"g":0,"b":0,"char":" ","brightness":0.00},
    {"x":40,"y":8,"r":0,"g":0,"b":0,"char":" ","brightness":0.00},
    {"x":41,"y":8,"r":0,"g":0,"b":0,"char":" ","brightness":0.00},
    {"x":42,"y":8,"r":0,"g":0,"b":0,"char":" ","brightness":0.00},
    {"x":43,"y":8,"r":0,"g":0,"b":0,"char":" ","brightness":0.00},
    {"x":44,"y":8,"r":0,"g":0,"b":0,"char":" ","brightness":0.00},
    {"x":45,"y":8,"r":0,"g":0,"b":0,"char":" ","brightness":0.00},
    {"x":46,"y":8,"r":0,"g":0,"b":0,"char":" ","brightness":0.00},
    {"x":47,"y":8,"r":0,"g":0,"b":0,"char":" ","brightness":0.00},
    {"x":0,"y":9,"r":0,"g":0,"b":0,"char":" ","brightness":0.00},
    {"x":1,"y":9,"r":0,"g":0,"b":0,"char":" ","brightness":0.00},
    {"x":2,"y":9,"r":0,"g":0,"b":0,"char":" ","brightness":0.00},
    {"x":3,"y":9,"r":0,"g":0,"b":0,"char":" ","brightness":0.00},
    {"x":4,"y":9,"r":0,"g":0,"b":0,"char":" ","brightness":0.00},
    {"x":5,"y":9,"r":0,"g":0,"b":0,"char":" ","brightness":0.00},
    {"x":6,"y":9,"r":0,"g":0,"b":0,"char":" ","brightness":0.00},
    {"x":7,"y":9,"r":0,"g":0,"b":0,"char":" ","brightness":0.00},
    {"x":8,"y":9,"r":0,"g":0,"b":0,"char":" ","brightness":0.00},
    {"x":9,"y":9,"r":0,"g":0,"b":0,"char":" ","brightness":0.00},
    {"x":10,"y":9,"r":0,"g":0,"b":0,"char":" ","brightness":0.00},
    {"x":11,"y":9,"r":73,"g":67,"b":139,"char":" ","brightness":77.00},
    {"x":12,"y":9,"r":255,"g":255,"b":255,"char":" ","brightness":255.00},
    {"x":13,"y":9,"r":121,"g":119,"b":238,"char":" ","brightness":133.16},
    {"x":14,"y":9,"r":125,"g":125,"b":244,"char":" ","brightness":138.57},
    {"x":15,"y":9,"r":127,"g":125,"b":249,"char":"#","brightness":139.73},
    {"x":16,"y":9,"r":127,"g":101,"b":228,"char":"#","brightness":123.25},
    {"x":17,"y":9,"r":127,"g":69,"b":197,"char":"*","brightness":100.93},
    {"x":18,"y":9,"r":127,"g":62,"b":190,"char":"*","brightness":96.03},
    {"x":19,"y":9,"r":127,"g":63,"b":191,"char":"*","brightness":96.73},
    {"x":20,"y":9,"r":127,"g":63,"b":191,"char":"*","brightness":96.73},
    {"x":21,"y":9,"r":127,"g":63,"b":191,"char":"*","brightness":96.73},
    {"x":22,"y":9,"r":127,"g":63,"b":191,"char":"*","brightness":96.73},
    {"x":23,"y":9,"r":127,"g":63,"b":191,"char":"*","brightness":96.73},
    {"x":24,"y":9,"r":127,"g":63,"b":191,"char":"*","brightness":96.73},
    {"x":25,"y":9,"r":168,"g":84,"b":170,"char":"#","brightness":118.92},
    {"x":26,"y":9,"r":234,"g":117,"b":135,"char":"%","brightness":154.03},
    {"x":27,"y":9,"r":250,"g":125,"b":122,"char":"%","brightness":162.03},
    {"x":28,"y":9,"r":239,"g":121,"b":121,"char":"%","brightness":156.28},
    {"x":29,"y":9,"r":246,"g":121,"b":119,"char":" ","brightness":158.15},
    {"x":30,"y":9,"r":236,"g":124,"b":125,"char":" ","brightness":157.60},
    {"x":31,"y":9,"r":246,"g":127,"b":128,"char":" ","brightness":162.70},
    {"x":32,"y":9,"r":181,"g":95,"b":98,"char":" ","brightness":121.06},
    {"x":33,"y":9,"r":0,"g":0,"b":0,"char":" ","brightness":0.00},
    {"x":34,"y":9,"r":0,"g":0,"b":0,"char":" ","brightness":0.00},
    {"x":35,"y":9,"r":0,"g":0,"b":0,"char":" ","brightness":0.00},
    {"x":36,"y":9,"r":0,"g":0,"b":0,"char":" ","brightness":0.00},
    {"x":37,"y":9,"r":0,"g":0,"b":0,"char":" ","brightness":0.00},
    {"x":38,"y":9,"r":0,"g":0,"b":0,"char":" ","brightness":0.00},
    {"x":39,"y":9,"r":0,"g":0,"b":0,"char":" ","brightness":0.00},
    {"x":40,"y":9,"r":0,"g":0,"b":0,"char":" ","brightness":0.00},
    {"x":41,"y":9,"r":0,"g":0,"b":0,"char":" ","brightness":0.00},
    {"x":42,"y":9,"r":0,"g":0,"b":0,"char":" ","brightness":0.00},
    {"x":43,"y":9,"r":0,"g":0,"b":0,"char":" ","brightness":0.00},
    {"x":44,"y":9,"r":0,"g":0,"b":0,"char":" ","brightness":0.00},
    {"x":45,"y":9,"r":0,"g":0,"b":0,"char":" ","brightness":0.00},
    {"x":46,"y":9,"r":0,"g":0,"b":0,"char":" ","brightness":0.00},
    {"x":47,"y":9,"r":0,"g":0,"b":0,"char":" ","brightness":0.00},
    {"x":0,"y":10,"r":0,"g":0,"b":0,"char":" ","brightness":0.00},
    {"x":1,"y":10,"r":0,"g":0,"b":0,"char":" ","brightness":0.00},
    {"x":2,"y":10,"r":0,"g":0,"b":0,"char":" ","brightness":0.00},
    {"x":3,"y":10,"r":0,"g":0,"b":0,"char":" ","brightness":0.00},
    {"x":4,"y":10,"r":0,"g":0,"b":0,"char":" ","brightness":0.00},
    {"x":5,"y":10,"r":0,"g":0,"b":0,"char":" ","brightness":0.00},
    {"x":6,"y":10,"r":0,"g":0,"b":0,"char":" ","brightness":0.00},
    {"x":7,"y":10,"r":0,"g":0,"b":0,"char":" ","brightness":0.00},
    {"x":8,"y":10,"r":0,"g":0,"b":0,"char":" ","brightness":0.00},
    {"x":9,"y":10,"r":0,"g":0,"b":0,"char":" ","brightness":0.00},
    {"x":10,"y":10,"r":103,"g":100,"b":198,"char":" ","brightness":112.07},
    {"x":11,"y":10,"r":88,"g":80,"b":160,"char":" ","brightness":91.51},
    {"x":12,"y":10,"r":130,"g":130,"b":255,"char":" ","brightness":144.25},
    {"x":13,"y":10,"r":110,"g":108,"b":214,"char":"#","brightness":120.68},
    {"x":14,"y":10,"r":125,"g":124,"b":247,"char":"#","brightness":138.32},
    {"x":15,"y":10,"r":127,"g":103,"b":230,"char":"#","brightness":124.65},
    {"x":16,"y":10,"r":127,"g":68,"b":196,"char":"*","brightness":100.23},
    {"x":17,"y":10,"r":127,"g":62,"b":190,"char":"*","brightness":96.03},
    {"x":18,"y":10,"r":127,"g":63,"b":191,"char":"*","brightness":96.73},
    {"x":19,"y":10,"r":127,"g":63,"b":191,"char":"*","brightness":96.73},
    {"x":20,"y":10,"r":127,"g":63,"b":191,"char":"*","brightness":96.73},
    {"x":21,"y":10,"r":127,"g":63,"b":191,"char":"*","brightness":96.73},
    {"x":22,"y":10,"r":127,"g":63,"b":191,"char":"*","brightness":96.73},
    {"x":23,"y":10,"r":127,"g":63,"b":191,"char":"*","brightness":96.73},
    {"x":24,"y":10,"r":127,"g":63,"b":191,"char":"*","brightness":96.73},
    {"x":25,"y":10,"r":126,"g":62,"b":191,"char":"*","brightness":95.84},
    {"x":26,"y":10,"r":156,"g":78,"b":177,"char":"#","brightness":112.61},
    {"x":27,"y":10,"r":228,"g":114,"b":140,"char":"%","brightness":151.05},
    {"x":28,"y":10,"r":253,"g":127,"b":125,"char":"%","brightness":164.45},
    {"x":29,"y":10,"r":235,"g":121,"b":120,"char":"%","brightness":154.97},
    {"x":30,"y":10,"r":217,"g":116,"b":118,"char":" ","brightness":146.43},
    {"x":31,"y":10,"r":246,"g":125,"b":124,"char":" ","brightness":161.06},
    {"x":32,"y":10,"r":209,"g":112,"b":113,"char":" ","brightness":141.12},
    {"x":33,"y":10,"r":225,"g":117,"b":118,"char":" ","brightness":149.41},
    {"x":34,"y":10,"r":0,"g":0,"b":0,"char":" ","brightness":0.00},
    {"x":35,"y":10,"r":0,"g":0,"b":0,"char":" ","brightness":0.00},
    {"x":36,"y":10,"r":0,"g":0,"b":0,"char":" ","brightness":0.00},
    {"x":37,"y":10,"r":0,"g":0,"b":0,"char":" ","brightness":0.00},
    {"x":38,"y":10,"r":0,"g":0,"b":0,"char":" ","brightness":0.00},
    {"x":39,"y":10,"r":0,"g":0,"b":0,"char":" ","brightness":0.00},
    {"x":40,"y":10,"r":0,"g":0,"b":0,"char":" ","brightness":0.00},
    {"x":41,"y":10,"r":0,"g":0,"b":0,"char":" ","brightness":0.00},
    {"x":42,"y":10,"r":0,"g":0,"b":0,"char":" ","brightness":0.00},
    {"x":43,"y":10,"r":0,"g":0,"b":0,"char":" ","brightness":0.00},
    {"x":44,"y":10,"r":0,"g":0,"b":0,"char":" ","brightness":0.00},
    {"x":45,"y":10,"r":0,"g":0,"b":0,"char":" ","brightness":0.00},
    {"x":46,"y":10,"r":0,"g":0,"b":0,"char":" ","brightness":0.00},
    {"x":47,"y":10,"r":0,"g":0,"b":0,"char":" ","brightness":0.00},
    {"x":0,"y":11,"r":0,"g":0,"b":0,"char":" ","brightness":0.00},
    {"x":1,"y":11,"r":0,"g":0,"b":0,"char":" ","brightness":0.00},
    {"x":2,"y":11,"r":0,"g":0,"b":0,"char":" ","brightness":0.00},
    {"x":3,"y":11,"r":0,"g":0,"b":0,"char":" ","brightness":0.00},
    {"x":4,"y":11,"r":0,"g":0,"b":0,"char":" ","brightness":0.00},
    {"x":5,"y":11,"r":0,"g":0,"b":0,"char":" ","brightness":0.00},
    {"x":6,"y":11,"r":0,"g":0,"b":0,"char":" ","brightness":0.00},
    {"x":7,"y":11,"r":0,"g":0,"b":0,"char":" ","brightness":0.00},
    {"x":8,"y":11,"r":0,"g":0,"b":0,"char":" ","brightness":0.00},
    {"x":9,"y":11,"r":82,"g":77,"b":159,"char":" ","brightness":87.84},
    {"x":10,"y":11,"r":84,"g":80,"b":160,"char":" ","brightness":90.32},
    {"x":11,"y":11,"r":118,"g":117,"b":237,"char":" ","brightness":130.98},
    {"x":12,"y":11,"r":121,"g":119,"b":238,"char":"#","brightness":133.16},
    {"x":13,"y":11,"r":125,"g":124,"b":247,"char":"#","brightness":138.32},
    {"x":14,"y":11,"r":127,"g":106,"b":233,"char":"#","brightness":126.76},
    {"x":15,"y":11,"r":127,"g":68,"b":196,"char":"*","brightness":100.23},
    {"x":16,"y":11,"r":127,"g":62,"b":190,"char":"*","brightness":96.03},
    {"x":17,"y":11,"r":127,"g":63,"b":191,"char":"*","brightness":96.73},
    {"x":18,"y":11,"r":127,"g":63,"b":191,"char":"*","brightness":96.73},
    {"x":19,"y":11,"r":127,"g":63,"b":191,"char":"*","brightness":96.73},
    {"x":20,"y":11,"r":127,"g":63,"b":191,"char":"*","brightness":96.73},
    {"x":21,"y":11,"r":127,"g":63,"b":191,"char":"*","brightness":96.73},
    {"x":22,"y":11,"r":127,"g":63,"b":191,"char":"*","brightness":96.73},
    {"x":23,"y":11,"r":127,"g":63,"b":191,"char":"*","brightness":96.73},
    {"x":24,"y":11,"r":127,"g":63,"b":191,"char":"*","brightness":96.73},
    {"x":25,"y":11,"r":127,"g":63,"b":191,"char":"*","brightness":96.73},
    {"x":26,"y":11,"r":125,"g":62,"b":192,"char":"*","brightness":95.66},
    {"x":27,"y":11,"r":145,"g":72,"b":182,"char":"*","brightness":106.37},
    {"x":28,"y":11,"r":218,"g":109,"b":145,"char":"#","brightness":145.69},
    {"x":29,"y":11,"r":253,"g":127,"b":126,"char":"%","brightness":164.56},
    {"x":30,"y":11,"r":250,"g":127,"b":127,"char":"%","brightness":163.78},
    {"x":31,"y":11,"r":245,"g":125,"b":124,"char":"%","brightness":160.77},
    {"x":32,"y":11,"r":255,"g":139,"b":137,"char":" ","brightness":173.46},
    {"x":33,"y":11,"r":247,"g":127,"b":126,"char":" ","brightness":162.77},
    {"x":34,"y":11,"r":254,"g":128,"b":130,"char":" ","brightness":165.90},
    {"x":35,"y":11,"r":242,"g":122,"b":121,"char":" ","brightness":157.77},
    {"x":36,"y":11,"r":0,"g":0,"b":0,"char":" ","brightness":0.00},
    {"x":37,"y":11,"r":0,"g":0,"b":0,"char":" ","brightness":0.00},
    {"x":38,"y":11,"r":0,"g":0,"b":0,"char":" ","brightness":0.00},
    {"x":39,"y":11,"r":0,"g":0,"b":0,"char":" ","brightness":0.00},
    {"x":40,"y":11,"r":0,"g":0,"b":0,"char":" ","brightness":0.00},
    {"x":41,"y":11,"r":0,"g":0,"b":0,"char":" ","brightness":0.00},
    {"x":42,"y":11,"r":0,"g":0,"b":0,"char":" ","brightness":0.00},
    {"x":43,"y":11,"r":0,"g":0,"b":0,"char":" ","brightness":0.00},
    {"x":44,"y":11,"r":0,"g":0,"b":0,"char":" ","brightness":0.00},
    {"x":45,"y":11,"r":0,"g":0,"b":0,"char":" ","brightness":0.00},
    {"x":46,"y":11,"r":0,"g":0,"b":0,"char":" ","brightness":0.00},
    {"x":47,"y":11,"r":0,"g":0,"b":0,"char":" ","brightness":0.00},
    {"x":0,"y":12,"r":0,"g":0,"b":0,"char":" ","brightness":0.00},
    {"x":1,"y":12,"r":0,"g":0,"b":0,"char":" ","brightness":0.00},
    {"x":2,"y":12,"r":0,"g":0,"b":0,"char":" ","brightness":0.00},
    {"x":3,"y":12,"r":0,"g":0,"b":0,"char":" ","brightness":0.00},
    {"x":4,"y":12,"r":0,"g":0,"b":0,"char":" ","brightness":0.00},
    {"x":5,"y":12,"r":0,"g":0,"b":0,"char":" ","brightness":0.00},
    {"x":6,"y":12,"r":0,"g":0,"b":0,"char":" ","brightness":0.00},
    {"x":7,"y":12,"r":0,"g":0,"b":0,"char":" ","brightness":0.00},
    {"x":8,"y":12,"r":116,"g":110,"b":217,"char":" ","brightness":123.99},
    {"x":9,"y":12,"r":72,"g":65,"b":132,"char":" ","brightness":74.73},
    {"x":10,"y":12,"r":179,"g":180,"b":255,"char":" ","brightness":188.25},
    {"x":11,"y":12,"r":114,"g":113,"b":225,"char":"#","brightness":126.07},
    {"x":12,"y":12,"r":127,"g":127,"b":252,"char":"#","brightness":141.25},
    {"x":13,"y":12,"r":128,"g":113,"b":240,"char":"#","brightness":131.96},
    {"x":14,"y":12,"r":127,"g":70,"b":198,"char":"*","brightness":101.63},
    {"x":15,"y":12,"r":127,"g":62,"b":190,"char":"*","brightness":96.03},
    {"x":16,"y":12,"r":127,"g":63,"b":191,"char":"*","brightness":96.73},
    {"x":17,"y":12,"r":127,"g":63,"b":191,"char":"*","brightness":96.73},
    {"x":18,"y":12,"r":127,"g":63,"b":191,"char":"*","brightness":96.73},
    {"x":19,"y":12,"r":127,"g":63,"b":191,"char":"*","brightness":96.73},
    {"x":20,"y":12,"r":127,"g":63,"b":191,"char":"*","brightness":96.73},
    {"x":21,"y":12,"r":127,"g":63,"b":191,"char":"*","brightness":96.73},
    {"x":22,"y":12,"r":127,"g":63,"b":191,"char":"*","brightness":96.73},
    {"x":23,"y":12,"r":127,"g":63,"b":191,"char":"*","brightness":96.73},
    {"x":24,"y":12,"r":127,"g":63,"b":191,"char":"*","brightness":96.73},
    {"x":25,"y":12,"r":127,"g":63,"b":191,"char":"*","brightness":96.73},
    {"x":26,"y":12,"r":127,"g":63,"b":191,"char":"*","brightness":96.73},
    {"x":27,"y":12,"r":126,"g":62,"b":192,"char":"*","brightness":95.96},
    {"x":28,"y":12,"r":138,"g":69,"b":185,"char":"*","brightness":102.86},
    {"x":29,"y":12,"r":206,"g":103,"b":152,"char":"#","brightness":139.38},
    {"x":30,"y":12,"r":253,"g":127,"b":127,"char":"%","brightness":164.67},
    {"x":31,"y":12,"r":253,"g":127,"b":126,"char":"%","brightness":164.56},
    {"x":32,"y":12,"r":251,"g":127,"b":127,"char":"%","brightness":164.08},
    {"x":33,"y":12,"r":246,"g":128,"b":127,"char":" ","brightness":163.17},
    {"x":34,"y":12,"r":252,"g":126,"b":127,"char":" ","brightness":163.79},
    {"x":35,"y":12,"r":211,"g":109,"b":108,"char":" ","brightness":139.38},
    {"x":36,"y":12,"r":214,"g":110,"b":109,"char":" ","brightness":140.98},
    {"x":37,"y":12,"r":0,"g":0,"b":0,"char":" ","brightness":0.00},
    {"x":38,"y":12,"r":0,"g":0,"b":0,"char":" ","brightness":0.00},
    {"x":39,"y":12,"r":0,"g":0,"b":0,"char":" ","brightness":0.00},
    {"x":40,"y":12,"r":0,"g":0,"b":0,"char":" ","brightness":0.00},
    {"x":41,"y":12,"r":0,"g":0,"b":0,"char":" ","brightness":0.00},
    {"x":42,"y":12,"r":0,"g":0,"b":0,"char":" ","brightness":0.00},
    {"x":43,"y":12,"r":0,"g":0,"b":0,"char":" ","brightness":0.00},
    {"x":44,"y":12,"r":0,"g":0,"b":0,"char":" ","brightness":0.00},
    {"x":45,"y":12,"r":0,"g":0,"b":0,"char":" ","brightness":0.00},
    {"x":46,"y":12,"r":0,"g":0,"b":0,"char":" ","brightness":0.00},
    {"x":47,"y":12,"r":0,"g":0,"b":0,"char":" ","brightness":0.00},
    {"x":0,"y":13,"r":0,"g":0,"b":0,"char":" ","brightness":0.00},
    {"x":1,"y":13,"r":0,"g":0,"b":0,"char":" ","brightness":0.00},
    {"x":2,"y":13,"r":0,"g":0,"b":0,"char":" ","brightness":0.00},
    {"x":3,"y":13,"r":0,"g":0,"b":0,"char":" ","brightness":0.00},
    {"x":4,"y":13,"r":0,"g":0,"b":0,"char":" ","brightness":0.00},
    {"x":5,"y":13,"r":0,"g":0,"b":0,"char":" ","brightness":0.00},
    {"x":6,"y":13,"r":0,"g":0,"b":0,"char":" ","brightness":0.00},
    {"x":7,"y":13,"r":0,"g":0,"b":0,"char":" ","brightness":0.00},
    {"x":8,"y":13,"r":166,"g":170,"b":255,"char":" ","brightness":178.49},
    {"x":9,"y":13,"r":118,"g":117,"b":236,"char":" ","brightness":130.87},
    {"x":10,"y":13,"r":111,"g":109,"b":219,"char":"#","brightness":122.14},
    {"x":11,"y":13,"r":123,"g":122,"b":245,"char":"#","brightness":136.32},
    {"x":12,"y":13,"r":128,"g":123,"b":250,"char":"#","brightness":138.97},
    {"x":13,"y":13,"r":127,"g":79,"b":207,"char":"*","brightness":107.94},
    {"x":14,"y":13,"r":127,"g":62,"b":190,"char":"*","brightness":96.03},
    {"x":15,"y":13,"r":127,"g":63,"b":191,"char":"*","brightness":96.73},
    {"x":16,"y":13,"r":127,"g":63,"b":191,"char":"*","brightness":96.73},
    {"x":17,"y":13,"r":127,"g":63,"b":191,"char":"*","brightness":96.73},
    {"x":18,"y":13,"r":127,"g":63,"b":191,"char":"*","brightness":96.73},
    {"x":19,"y":13,"r":127,"g":63,"b":191,"char":"*","brightness":96.73},
    {"x":20,"y":13,"r":127,"g":63,"b":191,"char":"*","brightness":96.73},
    {"x":21,"y":13,"r":127,"g":63,"b":191,"char":"*","brightness":96.73},
    {"x":22,"y":13,"r":127,"g":63,"b":191,"char":"*","brightness":96.73},
    {"x":23,"y":13,"r":127,"g":63,"b":191,"char":"*","brightness":96.73},
    {"x":24,"y":13,"r":127,"g":63,"b":191,"char":"*","brightness":96.73},
    {"x":25,"y":13,"r":127,"g":63,"b":191,"char":"*","brightness":96.73},
    {"x":26,"y":13,"r":127,"g":63,"b":191,"char":"*","brightness":96.73},
    {"x":27,"y":13,"r":127,"g":63,"b":191,"char":"*","brightness":96.73},
    {"x":28,"y":13,"r":126,"g":62,"b":192,"char":"*","brightness":95.96},
    {"x":29,"y":13,"r":132,"g":66,"b":188,"char":"*","brightness":99.64},
    {"x":30,"y":13,"r":193,"g":96,"b":157,"char":"#","brightness":131.96},
    {"x":31,"y":13,"r":251,"g":125,"b":129,"char":"%","brightness":163.13},
    {"x":32,"y":13,"r":255,"g":128,"b":127,"char":"%","brightness":165.86},
    {"x":33,"y":13,"r":252,"g":127,"b":127,"char":"%","brightness":164.38},
    {"x":34,"y":13,"r":248,"g":126,"b":125,"char":"%","brightness":162.36},
    {"x":35,"y":13,"r":0,"g":3,"b":4,"char":" ","brightness":2.22},
    {"x":36,"y":13,"r":242,"g":123,"b":122,"char":" ","brightness":158.47},
    {"x":37,"y":13,"r":249,"g":122,"b":116,"char":" ","brightness":159.29},
    {"x":38,"y":13,"r":238,"g":126,"b":135,"char":" ","brightness":160.51},
    {"x":39,"y":13,"r":0,"g":0,"b":0,"char":" ","brightness":0.00},
    {"x":40,"y":13,"r":0,"g":0,"b":0,"char":" ","brightness":0.00},
    {"x":41,"y":13,"r":0,"g":0,"b":0,"char":" ","brightness":0.00},
    {"x":42,"y":13,"r":0,"g":0,"b":0,"char":" ","brightness":0.00},
    {"x":43,"y":13,"r":0,"g":0,"b":0,"char":" ","brightness":0.00},
    {"x":44,"y":13,"r":0,"g":0,"b":0,"char":" ","brightness":0.00},
    {"x":45,"y":13,"r":0,"g":0,"b":0,"char":" ","brightness":0.00},
    {"x":46,"y":13,"r":0,"g":0,"b":0,"char":" ","brightness":0.00},
    {"x":47,"y":13,"r":0,"g":0,"b":0,"char":" ","brightness":0.00},
    {"x":0,"y":14,"r":0,"g":0,"b":0,"char":" ","brightness":0.00},
    {"x":1,"y":14,"r":0,"g":0,"b":0,"char":" ","brightness":0.00},
    {"x":2,"y":14,"r":0,"g":0,"b":0,"char":" ","brightness":0.00},
    {"x":3,"y":14,"r":0,"g":0,"b":0,"char":" ","brightness":0.00},
    {"x":4,"y":14,"r":0,"g":0,"b":0,"char":" ","brightness":0.00},
    {"x":5,"y":14,"r":0,"g":0,"b":0,"char":" ","brightness":0.00},
    {"x":6,"y":14,"r":0,"g":0,"b":0,"char":" ","brightness":0.00},
    {"x":7,"y":14,"r":58,"g":53,"b":100,"char":" ","brightness":59.85},
    {"x":8,"y":14,"r":114,"g":113,"b":223,"char":" ","brightness":125.84},
    {"x":9,"y":14,"r":112,"g":110,"b":217,"char":"#","brightness":122.80},
    {"x":10,"y":14,"r":125,"g":124,"b":247,"char":"#","brightness":138.32},
    {"x":11,"y":14,"r":128,"g":128,"b":255,"char":"#","brightness":142.48},
    {"x":12,"y":14,"r":128,"g":103,"b":231,"char":"#","brightness":125.07},
    {"x":13,"y":14,"r":127,"g":64,"b":192,"char":"*","brightness":97.43},
    {"x":14,"y":14,"r":127,"g":63,"b":191,"char":"*","brightness":96.73},
    {"x":15,"y":14,"r":127,"g":63,"b":191,"char":"*","brightness":96.73},
    {"x":16,"y":14,"r":127,"g":63,"b":191,"char":"*","brightness":96.73},
    {"x":17,"y":14,"r":127,"g":63,"b":191,"char":"*","brightness":96.73},
    {"x":18,"y":14,"r":127,"g":63,"b":191,"char":"*","brightness":96.73},
    {"x":19,"y":14,"r":127,"g":63,"b":191,"char":"*","brightness":96.73},
    {"x":20,"y":14,"r":127,"g":63,"b":191,"char":"*","brightness":96.73},
    {"x":21,"y":14,"r":127,"g":63,"b":191,"char":"*","brightness":96.73},
    {"x":22,"y":14,"r":127,"g":63,"b":191,"char":"*","brightness":96.73},
    {"x":23,"y":14,"r":127,"g":63,"b":191,"char":"*","brightness":96.73},
    {"x":24,"y":14,"r":127,"g":63,"b":191,"char":"*","brightness":96.73},
    {"x":25,"y":14,"r":127,"g":63,"b":191,"char":"*","brightness":96.73},
    {"x":26,"y":14,"r":127,"g":63,"b":191,"char":"*","brightness":96.73},
    {"x":27,"y":14,"r":127,"g":63,"b":191,"char":"*","brightness":96.73},
    {"x":28,"y":14,"r":127,"g":63,"b":191,"char":"*","brightness":96.73},
    {"x":29,"y":14,"r":126,"g":63,"b":191,"char":"*","brightness":96.43},
    {"x":30,"y":14,"r":129,"g":64,"b":190,"char":"*","brightness":97.80},
    {"x":31,"y":14,"r":181,"g":91,"b":164,"char":"#","brightness":126.23},
    {"x":32,"y":14,"r":246,"g":123,"b":132,"char":"%","brightness":160.80},
    {"x":33,"y":14,"r":255,"g":128,"b":126,"char":"%","brightness":165.74},
    {"x":34,"y":14,"r":253,"g":126,"b":126,"char":"%","brightness":163.97},
    {"x":35,"y":14,"r":248,"g":125,"b":125,"char":"%","brightness":161.78},
    {"x":36,"y":14,"r":243,"g":124,"b":125,"char":"%","brightness":159.69},
    {"x":37,"y":14,"r":255,"g":129,"b":128,"char":" ","brightness":166.56},
    {"x":38,"y":14,"r":225,"g":117,"b":121,"char":" ","brightness":149.75},
    {"x":39,"y":14,"r":229,"g":118,"b":122,"char":" ","brightness":151.64},
    {"x":40,"y":14,"r":0,"g":0,"b":0,"char":" ","brightness":0.00},
    {"x":41,"y":14,"r":0,"g":0,"b":0,"char":" ","brightness":0.00},
    {"x":42,"y":14,"r":0,"g":0,"b":0,"char":" ","brightness":0.00},
    {"x":43,"y":14,"r":0,"g":0,"b":0,"char":" ","brightness":0.00},
    {"x":44,"y":14,"r":0,"g":0,"b":0,"char":" ","brightness":0.00},
    {"x":45,"y":14,"r":0,"g":0,"b":0,"char":" ","brightness":0.00},
    {"x":46,"y":14,"r":0,"g":0,"b":0,"char":" ","brightness":0.00},
    {"x":47,"y":14,"r":0,"g":0,"b":0,"char":" ","brightness":0.00},
    {"x":0,"y":15,"r":0,"g":0,"b":0,"char":" ","brightness":0.00},
    {"x":1,"y":15,"r":0,"g":0,"b":0,"char":" ","brightness":0.00},
    {"x":2,"y":15,"r":0,"g":0,"b":0,"char":" ","brightness":0.00},
    {"x":3,"y":15,"r":0,"g":0,"b":0,"char":" ","brightness":0.00},
    {"x":4,"y":15,"r":0,"g":0,"b":0,"char":" ","brightness":0.00},
    {"x":5,"y":15,"r":0,"g":0,"b":0,"char":" ","brightness":0.00},
    {"x":6,"y":15,"r":0,"g":0,"b":0,"char":" ","brightness":0.00},
    {"x":7,"y":15,"r":64,"g":59,"b":114,"char":" ","brightness":66.76},
    {"x":8,"y":15,"r":141,"g":141,"b":255,"char":" ","brightness":154.00},
    {"x":9,"y":15,"r":124,"g":123,"b":243,"char":"#","brightness":136.98},
    {"x":10,"y":15,"r":128,"g":127,"b":254,"char":"#","brightness":141.78},
    {"x":11,"y":15,"r":128,"g":127,"b":255,"char":"#","brightness":141.89},
    {"x":12,"y":15,"r":127,"g":86,"b":213,"char":"#","brightness":112.74},
    {"x":13,"y":15,"r":127,"g":62,"b":190,"char":"*","brightness":96.03},
    {"x":14,"y":15,"r":127,"g":63,"b":191,"char":"*","brightness":96.73},
    {"x":15,"y":15,"r":127,"g":63,"b":191,"char":"*","brightness":96.73},
    {"x":16,"y":15,"r":127,"g":63,"b":191,"char":"*","brightness":96.73},
    {"x":17,"y":15,"r":127,"g":63,"b":191,"char":"*","brightness":96.73},
    {"x":18,"y":15,"r":127,"g":63,"b":191,"char":"*","brightness":96.73},
    {"x":19,"y":15,"r":127,"g":63,"b":191,"char":"*","brightness":96.73},
    {"x":20,"y":15,"r":127,"g":63,"b":191,"char":"*","brightness":96.73},
    {"x":21,"y":15,"r":127,"g":63,"b":191,"char":"*","brightness":96.73},
    {"x":22,"y":15,"r":127,"g":63,"b":191,"char":"*","brightness":96.73},
    {"x":23,"y":15,"r":127,"g":63,"b":191,"char":"*","brightness":96.73},
    {"x":24,"y":15,"r":127,"g":63,"b":191,"char":"*","brightness":96.73},
    {"x":25,"y":15,"r":127,"g":63,"b":191,"char":"*","brightness":96.73},
    {"x":26,"y":15,"r":127,"g":63,"b":191,"char":"*","brightness":96.73},
    {"x":27,"y":15,"r":127,"g":63,"b":191,"char":"*","brightness":96.73},
    {"x":28,"y":15,"r":127,"g":63,"b":191,"char":"*","brightness":96.73},
    {"x":29,"y":15,"r":127,"g":63,"b":191,"char":"*","brightness":96.73},
    {"x":30,"y":15,"r":127,"g":63,"b":191,"char":"*","brightness":96.73},
    {"x":31,"y":15,"r":127,"g":63,"b":191,"char":"*","brightness":96.73},
    {"x":32,"y":15,"r":170,"g":85,"b":170,"char":"#","brightness":120.10},
    {"x":33,"y":15,"r":241,"g":120,"b":134,"char":"%","brightness":157.78},
    {"x":34,"y":15,"r":255,"g":128,"b":126,"char":"%","brightness":165.74},
    {"x":35,"y":15,"r":254,"g":127,"b":127,"char":"%","brightness":164.97},
    {"x":36,"y":15,"r":251,"g":126,"b":126,"char":"%","brightness":163.37},
    {"x":37,"y":15,"r":239,"g":122,"b":122,"char":"%","brightness":156.98},
    {"x":38,"y":15,"r":212,"g":113,"b":122,"char":" ","brightness":143.63},
    {"x":39,"y":15,"r":240,"g":123,"b":124,"char":" ","brightness":158.10},
    {"x":40,"y":15,"r":254,"g":97,"b":104,"char":" ","brightness":144.74},
    {"x":41,"y":15,"r":237,"g":123,"b":124,"char":" ","brightness":157.20},
    {"x":42,"y":15,"r":0,"g":0,"b":0,"char":" ","brightness":0.00},
    {"x":43,"y":15,"r":0,"g":0,"b":0,"char":" ","brightness":0.00},
    {"x":44,"y":15,"r":0,"g":0,"b":0,"char":" ","brightness":0.00},
    {"x":45,"y":15,"r":0,"g":0,"b":0,"char":" ","brightness":0.00},
    {"x":46,"y":15,"r":0,"g":0,"b":0,"char":" ","brightness":0.00},
    {"x":47,"y":15,"r":0,"g":0,"b":0,"char":" ","brightness":0.00},
    {"x":0,"y":16,"r":0,"g":0,"b":0,"char":" ","brightness":0.00},
    {"x":1,"y":16,"r":0,"g":0,"b":0,"char":" ","brightness":0.00},
    {"x":2,"y":16,"r":0,"g":0,"b":0,"char":" ","brightness":0.00},
    {"x":3,"y":16,"r":0,"g":0,"b":0,"char":" ","brightness":0.00},
    {"x":4,"y":16,"r":0,"g":0,"b":0,"char":" ","brightness":0.00},
    {"x":5,"y":16,"r":0,"g":0,"b":0,"char":" ","brightness":0.00},
    {"x":6,"y":16,"r":0,"g":0,"b":0,"char":" ","brightness":0.00},
    {"x":7,"y":16,"r":80,"g":78,"b":155,"char":" ","brightness":87.38},
    {"x":8,"y":16,"r":63,"g":61,"b":119,"char":" ","brightness":68.21},
    {"x":9,"y":16,"r":120,"g":119,"b":238,"char":"#","brightness":132.86},
    {"x":10,"y":16,"r":128,"g":127,"b":255,"char":"#","brightness":141.89},
    {"x":11,"y":16,"r":128,"g":127,"b":255,"char":"#","brightness":141.89},
    {"x":12,"y":16,"r":127,"g":90,"b":218,"char":"#","brightness":115.66},
    {"x":13,"y":16,"r":127,"g":62,"b":190,"char":"*","brightness":96.03},
    {"x":14,"y":16,"r":127,"g":63,"b":191,"char":"*","brightness":96.73},
    {"x":15,"y":16,"r":127,"g":63,"b":191,"char":"*","brightness":96.73},
    {"x":16,"y":16,"r":127,"g":63,"b":191,"char":"*","brightness":96.73},
    {"x":17,"y":16,"r":127,"g":63,"b":191,"char":"*","brightness":96.73},
    {"x":18,"y":16,"r":127,"g":63,"b":191,"char":"*","brightness":96.73},
    {"x":19,"y":16,"r":127,"g":63,"b":191,"char":"*","brightness":96.73},
    {"x":20,"y":16,"r":127,"g":63,"b":191,"char":"*","brightness":96.73},
    {"x":21,"y":16,"r":127,"g":63,"b":191,"char":"*","brightness":96.73},
    {"x":22,"y":16,"r":127,"g":63,"b":191,"char":"*","brightness":96.73},
    {"x":23,"y":16,"r":127,"g":63,"b":191,"char":"*","brightness":96.73},
    {"x":24,"y":16,"r":127,"g":63,"b":191,"char":"*","brightness":96.73},
    {"x":25,"y":16,"r":127,"g":63,"b":191,"char":"*","brightness":96.73},
    {"x":26,"y":16,"r":127,"g":63,"b":191,"char":"*","brightness":96.73},
    {"x":27,"y":16,"r":127,"g":63,"b":191,"char":"*","brightness":96.73},
    {"x":28,"y":16,"r":127,"g":63,"b":191,"char":"*","brightness":96.73},
    {"x":29,"y":16,"r":127,"g":63,"b":191,"char":"*","brightness":96.73},
    {"x":30,"y":16,"r":127,"g":63,"b":191,"char":"*","brightness":96.73},
    {"x":31,"y":16,"r":127,"g":63,"b":191,"char":"*","brightness":96.73},
    {"x":32,"y":16,"r":126,"g":63,"b":192,"char":"*","brightness":96.54},
    {"x":33,"y":16,"r":159,"g":79,"b":175,"char":"#","brightness":113.86},
    {"x":34,"y":16,"r":233,"g":116,"b":138,"char":"%","brightness":153.49},
    {"x":35,"y":16,"r":255,"g":128,"b":126,"char":"%","brightness":165.74},
    {"x":36,"y":16,"r":255,"g":127,"b":127,"char":"%","brightness":165.27},
    {"x":37,"y":16,"r":253,"g":127,"b":127,"char":"%","brightness":164.67},
    {"x":38,"y":16,"r":248,"g":125,"b":126,"char":"%","brightness":161.89},
    {"x":39,"y":16,"r":237,"g":123,"b":123,"char":"%","brightness":157.09},
    {"x":40,"y":16,"r":254,"g":126,"b":127,"char":" ","brightness":164.39},
    {"x":41,"y":16,"r":175,"g":91,"b":92,"char":" ","brightness":116.23},
    {"x":42,"y":16,"r":180,"g":93,"b":94,"char":" ","brightness":119.13},
    {"x":43,"y":16,"r":0,"g":0,"b":0,"char":" ","brightness":0.00},
    {"x":44,"y":16,"r":0,"g":0,"b":0,"char":" ","brightness":0.00},
    {"x":45,"y":16,"r":0,"g":0,"b":0,"char":" ","brightness":0.00},
    {"x":46,"y":16,"r":0,"g":0,"b":0,"char":" ","brightness":0.00},
    {"x":47,"y":16,"r":0,"g":0,"b":0,"char":" ","brightness":0.00},
    {"x":0,"y":17,"r":0,"g":0,"b":0,"char":" ","brightness":0.00},
    {"x":1,"y":17,"r":0,"g":0,"b":0,"char":" ","brightness":0.00},
    {"x":2,"y":17,"r":0,"g":0,"b":0,"char":" ","brightness":0.00},
    {"x":3,"y":17,"r":0,"g":0,"b":0,"char":" ","brightness":0.00},
    {"x":4,"y":17,"r":0,"g":0,"b":0,"char":" ","brightness":0.00},
    {"x":5,"y":17,"r":0,"g":0,"b":0,"char":" ","brightness":0.00},
    {"x":6,"y":17,"r":0,"g":0,"b":0,"char":" ","brightness":0.00},
    {"x":7,"y":17,"r":66,"g":63,"b":124,"char":" ","brightness":70.85},
    {"x":8,"y":17,"r":255,"g":255,"b":255,"char":" ","brightness":255.00},
    {"x":9,"y":17,"r":117,"g":115,"b":230,"char":"#","brightness":128.71},
    {"x":10,"y":17,"r":127,"g":126,"b":253,"char":"#","brightness":140.78},
    {"x":11,"y":17,"r":128,"g":128,"b":255,"char":"#","brightness":142.48},
    {"x":12,"y":17,"r":128,"g":118,"b":246,"char":"#","brightness":135.58},
    {"x":13,"y":17,"r":127,"g":84,"b":212,"char":"#","brightness":111.45},
    {"x":14,"y":17,"r":127,"g":67,"b":195,"char":"*","brightness":99.53},
    {"x":15,"y":17,"r":127,"g":63,"b":191,"char":"*","brightness":96.73},
    {"x":16,"y":17,"r":127,"g":62,"b":190,"char":"*","brightness":96.03},
    {"x":17,"y":17,"r":127,"g":62,"b":190,"char":"*","brightness":96.03},
    {"x":18,"y":17,"r":127,"g":62,"b":190,"char":"*","brightness":96.03},
    {"x":19,"y":17,"r":127,"g":62,"b":190,"char":"*","brightness":96.03},
    {"x":20,"y":17,"r":127,"g":62,"b":190,"char":"*","brightness":96.03},
    {"x":21,"y":17,"r":127,"g":62,"b":190,"char":"*","brightness":96.03},
    {"x":22,"y":17,"r":127,"g":62,"b":190,"char":"*","brightness":96.03},
    {"x":23,"y":17,"r":127,"g":62,"b":190,"char":"*","brightness":96.03},
    {"x":24,"y":17,"r":127,"g":62,"b":190,"char":"*","brightness":96.03},
    {"x":25,"y":17,"r":127,"g":62,"b":190,"char":"*","brightness":96.03},
    {"x":26,"y":17,"r":127,"g":62,"b":190,"char":"*","brightness":96.03},
    {"x":27,"y":17,"r":127,"g":62,"b":190,"char":"*","brightness":96.03},
    {"x":28,"y":17,"r":127,"g":62,"b":190,"char":"*","brightness":96.03},
    {"x":29,"y":17,"r":127,"g":62,"b":190,"char":"*","brightness":96.03},
    {"x":30,"y":17,"r":127,"g":62,"b":190,"char":"*","brightness":96.03},
    {"x":31,"y":17,"r":127,"g":62,"b":190,"char":"*","brightness":96.03},
    {"x":32,"y":17,"r":127,"g":62,"b":190,"char":"*","brightness":96.03},
    {"x":33,"y":17,"r":126,"g":61,"b":191,"char":"*","brightness":95.25},
    {"x":34,"y":17,"r":150,"g":74,"b":178,"char":"*","brightness":108.58},
    {"x":35,"y":17,"r":224,"g":111,"b":141,"char":"%","brightness":148.21},
    {"x":36,"y":17,"r":255,"g":127,"b":125,"char":"%","brightness":165.04},
    {"x":37,"y":17,"r":255,"g":127,"b":127,"char":"%","brightness":165.27},
    {"x":38,"y":17,"r":254,"g":127,"b":127,"char":"%","brightness":164.97},
    {"x":39,"y":17,"r":251,"g":126,"b":126,"char":"%","brightness":163.37},
    {"x":40,"y":17,"r":234,"g":119,"b":119,"char":"%","brightness":153.38},
    {"x":41,"y":17,"r":156,"g":82,"b":83,"char":" ","brightness":104.24},
    {"x":42,"y":17,"r":182,"g":94,"b":95,"char":" ","brightness":120.43},
    {"x":43,"y":17,"r":0,"g":0,"b":0,"char":" ","brightness":0.00},
    {"x":44,"y":17,"r":0,"g":0,"b":0,"char":" ","brightness":0.00},
    {"x":45,"y":17,"r":0,"g":0,"b":0,"char":" ","brightness":0.00},
    {"x":46,"y":17,"r":0,"g":0,"b":0,"char":" ","brightness":0.00},
    {"x":47,"y":17,"r":0,"g":0,"b":0,"char":" ","brightness":0.00},
    {"x":0,"y":18,"r":0,"g":0,"b":0,"char":" ","brightness":0.00},
    {"x":1,"y":18,"r":0,"g":0,"b":0,"char":" ","brightness":0.00},
    {"x":2,"y":18,"r":0,"g":0,"b":0,"char":" ","brightness":0.00},
    {"x":3,"y":18,"r":0,"g":0,"b":0,"char":" ","brightness":0.00},
    {"x":4,"y":18,"r":0,"g":0,"b":0,"char":" ","brightness":0.00},
    {"x":5,"y":18,"r":0,"g":0,"b":0,"char":" ","brightness":0.00},
    {"x":6,"y":18,"r":0,"g":0,"b":0,"char":" ","brightness":0.00},
    {"x":7,"y":18,"r":66,"g":62,"b":123,"char":" ","brightness":70.15},
    {"x":8,"y":18,"r":112,"g":110,"b":218,"char":" ","brightness":122.91},
    {"x":9,"y":18,"r":108,"g":106,"b":207,"char":" ","brightness":118.11},
    {"x":10,"y":18,"r":126,"g":124,"b":248,"char":"#","brightness":138.73},
    {"x":11,"y":18,"r":127,"g":126,"b":252,"char":"#","brightness":140.66},
    {"x":12,"y":18,"r":127,"g":127,"b":254,"char":"#","brightness":141.48},
    {"x":13,"y":18,"r":128,"g":125,"b":252,"char":"#","brightness":140.38},
    {"x":14,"y":18,"r":128,"g":113,"b":241,"char":"#","brightness":132.08},
    {"x":15,"y":18,"r":128,"g":101,"b":229,"char":"#","brightness":123.66},
    {"x":16,"y":18,"r":127,"g":93,"b":221,"char":"#","brightness":117.76},
    {"x":17,"y":18,"r":128,"g":88,"b":216,"char":"#","brightness":114.55},
    {"x":18,"y":18,"r":127,"g":84,"b":212,"char":"#","brightness":111.45},
    {"x":19,"y":18,"r":127,"g":83,"b":211,"char":"#","brightness":110.75},
    {"x":20,"y":18,"r":128,"g":83,"b":211,"char":"#","brightness":111.05},
    {"x":21,"y":18,"r":128,"g":83,"b":211,"char":"#","brightness":111.05},
    {"x":22,"y":18,"r":128,"g":83,"b":211,"char":"#","brightness":111.05},
    {"x":23,"y":18,"r":128,"g":83,"b":210,"char":"#","brightness":110.93},
    {"x":24,"y":18,"r":128,"g":83,"b":210,"char":"#","brightness":110.93},
    {"x":25,"y":18,"r":128,"g":83,"b":211,"char":"#","brightness":111.05},
    {"x":26,"y":18,"r":127,"g":83,"b":211,"char":"#","brightness":110.75},
    {"x":27,"y":18,"r":127,"g":83,"b":211,"char":"#","brightness":110.75},
    {"x":28,"y":18,"r":127,"g":83,"b":211,"char":"#","brightness":110.75},
    {"x":29,"y":18,"r":127,"g":83,"b":212,"char":"#","brightness":110.86},
    {"x":30,"y":18,"r":127,"g":85,"b":213,"char":"#","brightness":112.15},
    {"x":31,"y":18,"r":128,"g":86,"b":214,"char":"#","brightness":113.15},
    {"x":32,"y":18,"r":128,"g":88,"b":216,"char":"#","brightness":114.55},
    {"x":33,"y":18,"r":127,"g":89,"b":216,"char":"#","brightness":114.84},
    {"x":34,"y":18,"r":125,"g":88,"b":217,"char":"#","brightness":113.77},
    {"x":35,"y":18,"r":143,"g":98,"b":209,"char":"#","brightness":124.11},
    {"x":36,"y":18,"r":195,"g":120,"b":173,"char":"%","brightness":148.47},
    {"x":37,"y":18,"r":241,"g":125,"b":132,"char":"%","brightness":160.48},
    {"x":38,"y":18,"r":251,"g":127,"b":125,"char":"%","brightness":163.85},
    {"x":39,"y":18,"r":252,"g":126,"b":125,"char":"%","brightness":163.56},
    {"x":40,"y":18,"r":234,"g":118,"b":118,"char":"%","brightness":152.68},
    {"x":41,"y":18,"r":163,"g":86,"b":86,"char":"*","brightness":109.02},
    {"x":42,"y":18,"r":179,"g":94,"b":94,"char":" ","brightness":119.41},
    {"x":43,"y":18,"r":0,"g":0,"b":0,"char":" ","brightness":0.00},
    {"x":44,"y":18,"r":0,"g":0,"b":0,"char":" ","brightness":0.00},
    {"x":45,"y":18,"r":0,"g":0,"b":0,"char":" ","brightness":0.00},
    {"x":46,"y":18,"r":0,"g":0,"b":0,"char":" ","brightness":0.00},
    {"x":47,"y":18,"r":0,"g":0,"b":0,"char":" ","brightness":0.00},
    {"x":0,"y":19,"r":0,"g":0,"b":0,"char":" ","brightness":0.00},
    {"x":1,"y":19,"r":0,"g":0,"b":0,"char":" ","brightness":0.00},
    {"x":2,"y":19,"r":0,"g":0,"b":0,"char":" ","brightness":0.00},
    {"x":3,"y":19,"r":0,"g":0,"b":0,"char":" ","brightness":0.00},
    {"x":4,"y":19,"r":0,"g":0,"b":0,"char":" ","brightness":0.00},
    {"x":5,"y":19,"r":0,"g":0,"b":0,"char":" ","brightness":0.00},
    {"x":6,"y":19,"r":0,"g":0,"b":0,"char":" ","brightness":0.00},
    {"x":7,"y":19,"r":0,"g":0,"b":0,"char":" ","brightness":0.00},
    {"x":8,"y":19,"r":118,"g":116,"b":230,"char":" ","brightness":129.59},
    {"x":9,"y":19,"r":111,"g":109,"b":214,"char":" ","brightness":121.57},
    {"x":10,"y":19,"r":132,"g":132,"b":255,"char":" ","brightness":146.02},
    {"x":11,"y":19,"r":118,"g":116,"b":230,"char":"#","brightness":129.59},
    {"x":12,"y":19,"r":123,"g":122,"b":242,"char":"#","brightness":135.98},
    {"x":13,"y":19,"r":127,"g":126,"b":252,"char":"#","brightness":140.66},
    {"x":14,"y":19,"r":124,"g":124,"b":246,"char":"#","brightness":137.91},
    {"x":15,"y":19,"r":126,"g":126,"b":250,"char":"#","brightness":140.14},
    {"x":16,"y":19,"r":127,"g":127,"b":254,"char":"#","brightness":141.48},
    {"x":17,"y":19,"r":126,"g":125,"b":250,"char":"#","brightness":139.55},
    {"x":18,"y":19,"r":126,"g":124,"b":249,"char":"#","brightness":138.85},
    {"x":19,"y":19,"r":127,"g":125,"b":252,"char":"#","brightness":140.08},
    {"x":20,"y":19,"r":127,"g":125,"b":252,"char":"#","brightness":140.08},
    {"x":21,"y":19,"r":127,"g":125,"b":252,"char":"#","brightness":140.08},
    {"x":22,"y":19,"r":128,"g":126,"b":253,"char":"#","brightness":141.08},
    {"x":23,"y":19,"r":128,"g":126,"b":253,"char":"#","brightness":141.08},
    {"x":24,"y":19,"r":128,"g":126,"b":253,"char":"#","brightness":141.08},
    {"x":25,"y":19,"r":128,"g":126,"b":254,"char":"#","brightness":141.19},
    {"x":26,"y":19,"r":128,"g":126,"b":254,"char":"#","brightness":141.19},
    {"x":27,"y":19,"r":128,"g":126,"b":254,"char":"#","brightness":141.19},
    {"x":28,"y":19,"r":128,"g":126,"b":254,"char":"#","brightness":141.19},
    {"x":29,"y":19,"r":128,"g":126,"b":254,"char":"#","brightness":141.19},
    {"x":30,"y":19,"r":128,"g":126,"b":254,"char":"#","brightness":141.19},
    {"x":31,"y":19,"r":128,"g":127,"b":255,"char":"#","brightness":141.89},
    {"x":32,"y":19,"r":128,"g":127,"b":255,"char":"#","brightness":141.89},
    {"x":33,"y":19,"r":128,"g":127,"b":255,"char":"#","brightness":141.89},
    {"x":34,"y":19,"r":128,"g":127,"b":255,"char":"#","brightness":141.89},
    {"x":35,"y":19,"r":127,"g":127,"b":255,"char":"#","brightness":141.59},
    {"x":36,"y":19,"r":126,"g":126,"b":253,"char":"#","brightness":140.48},
    {"x":37,"y":19,"r":124,"g":125,"b":247,"char":"#","brightness":138.61},
    {"x":38,"y":19,"r":94,"g":121,"b":255,"char":"#","brightness":128.20},
    {"x":39,"y":19,"r":233,"g":128,"b":151,"char":" ","brightness":162.02},
    {"x":40,"y":19,"r":242,"g":122,"b":122,"char":" ","brightness":157.88},
    {"x":41,"y":19,"r":164,"g":85,"b":86,"char":" ","brightness":108.73},
    {"x":42,"y":19,"r":178,"g":92,"b":93,"char":" ","brightness":117.83},
    {"x":43,"y":19,"r":0,"g":0,"b":0,"char":" ","brightness":0.00},
    {"x":44,"y":19,"r":0,"g":0,"b":0,"char":" ","brightness":0.00},
    {"x":45,"y":19,"r":0,"g":0,"b":0,"char":" ","brightness":0.00},
    {"x":46,"y":19,"r":0,"g":0,"b":0,"char":" ","brightness":0.00},
    {"x":47,"y":19,"r":0,"g":0,"b":0,"char":" ","brightness":0.00},
    {"x":0,"y":20,"r":0,"g":0,"b":0,"char":" ","brightness":0.00},
    {"x":1,"y":20,"r":0,"g":0,"b":0,"char":" ","brightness":0.00},
    {"x":2,"y":20,"r":0,"g":0,"b":0,"char":" ","brightness":0.00},
    {"x":3,"y":20,"r":0,"g":0,"b":0,"char":" ","brightness":0.00},
    {"x":4,"y":20,"r":0,"g":0,"b":0,"char":" ","brightness":0.00},
    {"x":5,"y":20,"r":0,"g":0,"b":0,"char":" ","brightness":0.00},
    {"x":6,"y":20,"r":0,"g":0,"b":0,"char":" ","brightness":0.00},
    {"x":7,"y":20,"r":0,"g":0,"b":0,"char":" ","brightness":0.00},
    {"x":8,"y":20,"r":0,"g":0,"b":0,"char":" ","brightness":0.00},
    {"x":9,"y":20,"r":104,"g":103,"b":198,"char":" ","brightness":114.13},
    {"x":10,"y":20,"r":98,"g":95,"b":180,"char":" ","brightness":105.59},
    {"x":11,"y":20,"r":118,"g":117,"b":232,"char":" ","brightness":130.41},
    {"x":12,"y":20,"r":123,"g":122,"b":243,"char":" ","brightness":136.09},
    {"x":13,"y":20,"r":129,"g":127,"b":255,"char":" ","brightness":142.19},
    {"x":14,"y":20,"r":136,"g":135,"b":255,"char":" ","brightness":148.98},
    {"x":15,"y":20,"r":161,"g":166,"b":255,"char":" ","brightness":174.65},
    {"x":16,"y":20,"r":117,"g":115,"b":226,"char":" ","brightness":128.25},
    {"x":17,"y":20,"r":111,"g":111,"b":215,"char":" ","brightness":122.86},
    {"x":18,"y":20,"r":116,"g":116,"b":223,"char":"#","brightness":128.20},
    {"x":19,"y":20,"r":121,"g":121,"b":241,"char":"#","brightness":134.68},
    {"x":20,"y":20,"r":122,"g":121,"b":242,"char":"#","brightness":135.09},
    {"x":21,"y":20,"r":122,"g":121,"b":238,"char":"#","brightness":134.64},
    {"x":22,"y":20,"r":126,"g":125,"b":249,"char":"#","brightness":139.44},
    {"x":23,"y":20,"r":125,"g":124,"b":248,"char":"#","brightness":138.44},
    {"x":24,"y":20,"r":125,"g":124,"b":248,"char":"#","brightness":138.44},
    {"x":25,"y":20,"r":127,"g":126,"b":254,"char":"#","brightness":140.89},
    {"x":26,"y":20,"r":125,"g":124,"b":249,"char":"#","brightness":138.55},
    {"x":27,"y":20,"r":120,"g":120,"b":240,"char":"#","brightness":133.68},
    {"x":28,"y":20,"r":117,"g":116,"b":233,"char":"#","brightness":129.64},
    {"x":29,"y":20,"r":123,"g":122,"b":245,"char":"#","brightness":136.32},
    {"x":30,"y":20,"r":118,"g":117,"b":235,"char":"#","brightness":130.75},
    {"x":31,"y":20,"r":124,"g":123,"b":247,"char":"#","brightness":137.44},
    {"x":32,"y":20,"r":122,"g":121,"b":243,"char":"#","brightness":135.21},
    {"x":33,"y":20,"r":122,"g":121,"b":242,"char":"#","brightness":135.09},
    {"x":34,"y":20,"r":124,"g":123,"b":247,"char":"#","brightness":137.44},
    {"x":35,"y":20,"r":122,"g":121,"b":242,"char":"#","brightness":135.09},
    {"x":36,"y":20,"r":126,"g":125,"b":250,"char":"#","brightness":139.55},
    {"x":37,"y":20,"r":128,"g":127,"b":253,"char":"#","brightness":141.66},
    {"x":38,"y":20,"r":123,"g":121,"b":237,"char":"#","brightness":134.82},
    {"x":39,"y":20,"r":84,"g":76,"b":146,"char":" ","brightness":86.37},
    {"x":40,"y":20,"r":94,"g":88,"b":173,"char":" ","brightness":99.48},
    {"x":41,"y":20,"r":0,"g":0,"b":0,"char":" ","brightness":0.00},
    {"x":42,"y":20,"r":0,"g":0,"b":0,"char":" ","brightness":0.00},
    {"x":43,"y":20,"r":0,"g":0,"b":0,"char":" ","brightness":0.00},
    {"x":44,"y":20,"r":0,"g":0,"b":0,"char":" ","brightness":0.00},
    {"x":45,"y":20,"r":0,"g":0,"b":0,"char":" ","brightness":0.00},
    {"x":46,"y":20,"r":0,"g":0,"b":0,"char":" ","brightness":0.00},
    {"x":47,"y":20,"r":0,"g":0,"b":0,"char":" ","brightness":0.00},
    {"x":0,"y":21,"r":0,"g":0,"b":0,"char":" ","brightness":0.00},
    {"x":1,"y":21,"r":0,"g":0,"b":0,"char":" ","brightness":0.00},
    {"x":2,"y":21,"r":0,"g":0,"b":0,"char":" ","brightness":0.00},
    {"x":3,"y":21,"r":0,"g":0,"b":0,"char":" ","brightness":0.00},
    {"x":4,"y":21,"r":0,"g":0,"b":0,"char":" ","brightness":0.00},
    {"x":5,"y":21,"r":0,"g":0,"b":0,"char":" ","brightness":0.00},
    {"x":6,"y":21,"r":0,"g":0,"b":0,"char":" ","brightness":0.00},
    {"x":7,"y":21,"r":0,"g":0,"b":0,"char":" ","brightness":0.00},
    {"x":8,"y":21,"r":0,"g":0,"b":0,"char":" ","brightness":0.00},
    {"x":9,"y":21,"r":0,"g":0,"b":0,"char":" ","brightness":0.00},
    {"x":10,"y":21,"r":0,"g":0,"b":0,"char":" ","brightness":0.00},
    {"x":11,"y":21,"r":0,"g":0,"b":0,"char":" ","brightness":0.00},
    {"x":12,"y":21,"r":0,"g":0,"b":0,"char":" ","brightness":0.00},
    {"x":13,"y":21,"r":0,"g":0,"b":0,"char":" ","brightness":0.00},
    {"x":14,"y":21,"r":131,"g":126,"b":246,"char":" ","brightness":141.17},
    {"x":15,"y":21,"r":101,"g":93,"b":178,"char":" ","brightness":105.08},
    {"x":16,"y":21,"r":121,"g":120,"b":239,"char":" ","brightness":133.87},
    {"x":17,"y":21,"r":111,"g":110,"b":214,"char":" ","brightness":122.15},
    {"x":18,"y":21,"r":115,"g":114,"b":221,"char":" ","brightness":126.50},
    {"x":19,"y":21,"r":121,"g":120,"b":240,"char":" ","brightness":133.98},
    {"x":20,"y":21,"r":123,"g":121,"b":242,"char":" ","brightness":135.39},
    {"x":21,"y":21,"r":123,"g":122,"b":240,"char":" ","brightness":135.75},
    {"x":22,"y":21,"r":127,"g":126,"b":251,"char":" ","brightness":140.55},
    {"x":23,"y":21,"r":126,"g":125,"b":251,"char":" ","brightness":139.66},
    {"x":24,"y":21,"r":127,"g":127,"b":254,"char":" ","brightness":141.48},
    {"x":25,"y":21,"r":128,"g":127,"b":255,"char":" ","brightness":141.89},
    {"x":26,"y":21,"r":130,"g":129,"b":255,"char":" ","brightness":143.66},
    {"x":27,"y":21,"r":155,"g":154,"b":255,"char":" ","brightness":165.81},
    {"x":28,"y":21,"r":211,"g":209,"b":255,"char":" ","brightness":214.84},
    {"x":29,"y":21,"r":220,"g":218,"b":255,"char":" ","brightness":222.82},
    {"x":30,"y":21,"r":0,"g":0,"b":0,"char":" ","brightness":0.00},
    {"x":31,"y":21,"r":73,"g":73,"b":147,"char":" ","brightness":81.44},
    {"x":32,"y":21,"r":69,"g":68,"b":138,"char":" ","brightness":76.28},
    {"x":33,"y":21,"r":84,"g":84,"b":169,"char":" ","brightness":93.69},
    {"x":34,"y":21,"r":97,"g":96,"b":192,"char":" ","brightness":107.24},
    {"x":35,"y":21,"r":86,"g":85,"b":171,"char":"*","brightness":95.10},
    {"x":36,"y":21,"r":112,"g":111,"b":223,"char":"#","brightness":124.07},
    {"x":37,"y":21,"r":128,"g":127,"b":255,"char":"#","brightness":141.89},
    {"x":38,"y":21,"r":124,"g":122,"b":242,"char":"#","brightness":136.28},
    {"x":39,"y":21,"r":106,"g":100,"b":198,"char":" ","brightness":112.97},
    {"x":40,"y":21,"r":105,"g":99,"b":195,"char":" ","brightness":111.74},
    {"x":41,"y":21,"r":0,"g":0,"b":0,"char":" ","brightness":0.00},
    {"x":42,"y":21,"r":0,"g":0,"b":0,"char":" ","brightness":0.00},
    {"x":43,"y":21,"r":0,"g":0,"b":0,"char":" ","brightness":0.00},
    {"x":44,"y":21,"r":0,"g":0,"b":0,"char":" ","brightness":0.00},
    {"x":45,"y":21,"r":0,"g":0,"b":0,"char":" ","brightness":0.00},
    {"x":46,"y":21,"r":0,"g":0,"b":0,"char":" ","brightness":0.00},
    {"x":47,"y":21,"r":0,"g":0,"b":0,"char":" ","brightness":0.00},
    {"x":0,"y":22,"r":0,"g":0,"b":0,"char":" ","brightness":0.00},
    {"x":1,"y":22,"r":0,"g":0,"b":0,"char":" ","brightness":0.00},
    {"x":2,"y":22,"r":0,"g":0,"b":0,"char":" ","brightness":0.00},
    {"x":3,"y":22,"r":0,"g":0,"b":0,"char":" ","brightness":0.00},
    {"x":4,"y":22,"r":0,"g":0,"b":0,"char":" ","brightness":0.00},
    {"x":5,"y":22,"r":0,"g":0,"b":0,"char":" ","brightness":0.00},
    {"x":6,"y":22,"r":0,"g":0,"b":0,"char":" ","brightness":0.00},
    {"x":7,"y":22,"r":0,"g":0,"b":0,"char":" ","brightness":0.00},
    {"x":8,"y":22,"r":0,"g":0,"b":0,"char":" ","brightness":0.00},
    {"x":9,"y":22,"r":0,"g":0,"b":0,"char":" ","brightness":0.00},
    {"x":10,"y":22,"r":0,"g":0,"b":0,"char":" ","brightness":0.00},
    {"x":11,"y":22,"r":0,"g":0,"b":0,"char":" ","brightness":0.00},
    {"x":12,"y":22,"r":0,"g":0,"b":0,"char":" ","brightness":0.00},
    {"x":13,"y":22,"r":0,"g":0,"b":0,"char":" ","brightness":0.00},
    {"x":14,"y":22,"r":0,"g":0,"b":0,"char":" ","brightness":0.00},
    {"x":15,"y":22,"r":0,"g":0,"b":0,"char":" ","brightness":0.00},
    {"x":16,"y":22,"r":0,"g":0,"b":0,"char":" ","brightness":0.00},
    {"x":17,"y":22,"r":0,"g":0,"b":0,"char":" ","brightness":0.00},
    {"x":18,"y":22,"r":0,"g":0,"b":0,"char":" ","brightness":0.00},
    {"x":19,"y":22,"r":0,"g":0,"b":0,"char":" ","brightness":0.00},
    {"x":20,"y":22,"r":0,"g":0,"b":0,"char":" ","brightness":0.00},
    {"x":21,"y":22,"r":0,"g":0,"b":0,"char":" ","brightness":0.00},
    {"x":22,"y":22,"r":0,"g":0,"b":0,"char":" ","brightness":0.00},
    {"x":23,"y":22,"r":0,"g":0,"b":0,"char":" ","brightness":0.00},
    {"x":24,"y":22,"r":0,"g":0,"b":0,"char":" ","brightness":0.00},
    {"x":25,"y":22,"r":0,"g":0,"b":0,"char":" ","brightness":0.00},
    {"x":26,"y":22,"r":31,"g":30,"b":62,"char":" ","brightness":33.95},
    {"x":27,"y":22,"r":29,"g":28,"b":58,"char":" ","brightness":31.72},
    {"x":28,"y":22,"r":60,"g":59,"b":120,"char":" ","brightness":66.25},
    {"x":29,"y":22,"r":57,"g":57,"b":115,"char":" ","brightness":63.61},
    {"x":30,"y":22,"r":51,"g":51,"b":103,"char":" ","brightness":56.93},
    {"x":31,"y":22,"r":99,"g":99,"b":198,"char":" ","brightness":110.29},
    {"x":32,"y":22,"r":74,"g":73,"b":147,"char":" ","brightness":81.73},
    {"x":33,"y":22,"r":87,"g":86,"b":173,"char":" ","brightness":96.22},
    {"x":34,"y":22,"r":95,"g":94,"b":189,"char":" ","brightness":105.13},
    {"x":35,"y":22,"r":84,"g":82,"b":166,"char":" ","brightness":92.17},
    {"x":36,"y":22,"r":111,"g":110,"b":221,"char":" ","brightness":122.95},
    {"x":37,"y":22,"r":128,"g":127,"b":254,"char":" ","brightness":141.78},
    {"x":38,"y":22,"r":124,"g":123,"b":243,"char":" ","brightness":136.98},
    {"x":39,"y":22,"r":107,"g":102,"b":202,"char":" ","brightness":114.89},
    {"x":40,"y":22,"r":106,"g":101,"b":200,"char":" ","brightness":113.78},
    {"x":41,"y":22,"r":0,"g":0,"b":0,"char":" ","brightness":0.00},
    {"x":42,"y":22,"r":0,"g":0,"b":0,"char":" ","brightness":0.00},
    {"x":43,"y":22,"r":0,"g":0,"b":0,"char":" ","brightness":0.00},
    {"x":44,"y":22,"r":0,"g":0,"b":0,"char":" ","brightness":0.00},
    {"x":45,"y":22,"r":0,"g":0,"b":0,"char":" ","brightness":0.00},
    {"x":46,"y":22,"r":0,"g":0,"b":0,"char":" ","brightness":0.00},
    {"x":47,"y":22,"r":0,"g":0,"b":0,"char":" ","brightness":0.00},
    {"x":0,"y":23,"r":0,"g":0,"b":0,"char":" ","brightness":0.00},
    {"x":1,"y":23,"r":0,"g":0,"b":0,"char":" ","brightness":0.00},
    {"x":2,"y":23,"r":0,"g":0,"b":0,"char":" ","brightness":0.00},
    {"x":3,"y":23,"r":0,"g":0,"b":0,"char":" ","brightness":0.00},
    {"x":4,"y":23,"r":0,"g":0,"b":0,"char":" ","brightness":0.00},
    {"x":5,"y":23,"r":0,"g":0,"b":0,"char":" ","brightness":0.00},
    {"x":6,"y":23,"r":0,"g":0,"b":0,"char":" ","brightness":0.00},
    {"x":7,"y":23,"r":0,"g":0,"b":0,"char":" ","brightness":0.00},
    {"x":8,"y":23,"r":0,"g":0,"b":0,"char":" ","brightness":0.00},
    {"x":9,"y":23,"r":0,"g":0,"b":0,"char":" ","brightness":0.00},
    {"x":10,"y":23,"r":0,"g":0,"b":0,"char":" ","brightness":0.00},
    {"x":11,"y":23,"r":0,"g":0,"b":0,"char":" ","brightness":0.00},
    {"x":12,"y":23,"r":0,"g":0,"b":0,"char":" ","brightness":0.00},
    {"x":13,"y":23,"r":0,"g":0,"b":0,"char":" ","brightness":0.00},
    {"x":14,"y":23,"r":0,"g":0,"b":0,"char":" ","brightness":0.00},
    {"x":15,"y":23,"r":0,"g":0,"b":0,"char":" ","brightness":0.00},
    {"x":16,"y":23,"r":0,"g":0,"b":0,"char":" ","brightness":0.00},
    {"x":17,"y":23,"r":0,"g":0,"b":0,"char":" ","brightness":0.00},
    {"x":18,"y":23,"r":0,"g":0,"b":0,"char":" ","brightness":0.00},
    {"x":19,"y":23,"r":0,"g":0,"b":0,"char":" ","brightness":0.00},
    {"x":20,"y":23,"r":0,"g":0,"b":0,"char":" ","brightness":0.00},
    {"x":21,"y":23,"r":0,"g":0,"b":0,"char":" ","brightness":0.00},
    {"x":22,"y":23,"r":0,"g":0,"b":0,"char":" ","brightness":0.00},
    {"x":23,"y":23,"r":0,"g":0,"b":0,"char":" ","brightness":0.00},
    {"x":24,"y":23,"r":0,"g":0,"b":0,"char":" ","brightness":0.00},
    {"x":25,"y":23,"r":0,"g":0,"b":0,"char":" ","brightness":0.00},
    {"x":26,"y":23,"r":0,"g":0,"b":0,"char":" ","brightness":0.00},
    {"x":27,"y":23,"r":0,"g":0,"b":0,"char":" ","brightness":0.00},
    {"x":28,"y":23,"r":0,"g":0,"b":0,"char":" ","brightness":0.00},
    {"x":29,"y":23,"r":0,"g":0,"b":0,"char":" ","brightness":0.00},
    {"x":30,"y":23,"r":0,"g":0,"b":0,"char":" ","brightness":0.00},
    {"x":31,"y":23,"r":0,"g":0,"b":0,"char":" ","brightness":0.00},
    {"x":32,"y":23,"r":0,"g":0,"b":0,"char":" ","brightness":0.00},
    {"x":33,"y":23,"r":0,"g":0,"b":0,"char":" ","brightness":0.00},
    {"x":34,"y":23,"r":0,"g":0,"b":0,"char":" ","brightness":0.00},
    {"x":35,"y":23,"r":0,"g":0,"b":0,"char":" ","brightness":0.00},
    {"x":36,"y":23,"r":0,"g":0,"b":0,"char":" ","brightness":0.00},
    {"x":37,"y":23,"r":0,"g":0,"b":0,"char":" ","brightness":0.00},
    {"x":38,"y":23,"r":0,"g":0,"b":0,"char":" ","brightness":0.00},
    {"x":39,"y":23,"r":0,"g":0,"b":0,"char":" ","brightness":0.00},
    {"x":40,"y":23,"r":0,"g":0,"b":0,"char":" ","brightness":0.00},
    {"x":41,"y":23,"r":0,"g":0,"b":0,"char":" ","brightness":0.00},
    {"x":42,"y":23,"r":0,"g":0,"b":0,"char":" ","brightness":0.00},
    {"x":43,"y":23,"r":0,"g":0,"b":0,"char":" ","brightness":0.00},
    {"x":44,"y":23,"r":0,"g":0,"b":0,"char":" ","brightness":0.00},
    {"x":45,"y":23,"r":0,"g":0,"b":0,"char":" ","brightness":0.00},
    {"x":46,"y":23,"r":0,"g":0,"b":0,"char":" ","brightness":0.00},
    {"x":47,"y":23,"r":0,"g":0,"b":0,"char":" ","brightness":0.00},
    {"x":0,"y":24,"r":0,"g":0,"b":0,"char":" ","brightness":0.00},
    {"x":1,"y":24,"r":0,"g":0,"b":0,"char":" ","brightness":0.00},
    {"x":2,"y":24,"r":0,"g":0,"b":0,"char":" ","brightness":0.00},
    {"x":3,"y":24,"r":0,"g":0,"b":0,"char":" ","brightness":0.00},
    {"x":4,"y":24,"r":0,"g":0,"b":0,"char":" ","brightness":0.00},
    {"x":5,"y":24,"r":0,"g":0,"b":0,"char":" ","brightness":0.00},
    {"x":6,"y":24,"r":0,"g":0,"b":0,"char":" ","brightness":0.00},
    {"x":7,"y":24,"r":0,"g":0,"b":0,"char":" ","brightness":0.00},
    {"x":8,"y":24,"r":0,"g":0,"b":0,"char":" ","brightness":0.00},
    {"x":9,"y":24,"r":0,"g":0,"b":0,"char":" ","brightness":0.00},
    {"x":10,"y":24,"r":0,"g":0,"b":0,"char":" ","brightness":0.00},
    {"x":11,"y":24,"r":0,"g":0,"b":0,"char":" ","brightness":0.00},
    {"x":12,"y":24,"r":0,"g":0,"b":0,"char":" ","brightness":0.00},
    {"x":13,"y":24,"r":0,"g":0,"b":0,"char":" ","brightness":0.00},
    {"x":14,"y":24,"r":0,"g":0,"b":0,"char":" ","brightness":0.00},
    {"x":15,"y":24,"r":0,"g":0,"b":0,"char":" ","brightness":0.00},
    {"x":16,"y":24,"r":0,"g":0,"b":0,"char":" ","brightness":0.00},
    {"x":17,"y":24,"r":0,"g":0,"b":0,"char":" ","brightness":0.00},
    {"x":18,"y":24,"r":0,"g":0,"b":0,"char":" ","brightness":0.00},
    {"x":19,"y":24,"r":0,"g":0,"b":0,"char":" ","brightness":0.00},
    {"x":20,"y":24,"r":0,"g":0,"b":0,"char":" ","brightness":0.00},
    {"x":21,"y":24,"r":0,"g":0,"b":0,"char":" ","brightness":0.00},
    {"x":22,"y":24,"r":0,"g":0,"b":0,"char":" ","brightness":0.00},
    {"x":23,"y":24,"r":0,"g":0,"b":0,"char":" ","brightness":0.00},
    {"x":24,"y":24,"r":0,"g":0,"b":0,"char":" ","brightness":0.00},
    {"x":25,"y":24,"r":0,"g":0,"b":0,"char":" ","brightness":0.00},
    {"x":26,"y":24,"r":0,"g":0,"b":0,"char":" ","brightness":0.00},
    {"x":27,"y":24,"r":0,"g":0,"b":0,"char":" ","brightness":0.00},
    {"x":28,"y":24,"r":0,"g":0,"b":0,"char":" ","brightness":0.00},
    {"x":29,"y":24,"r":0,"g":0,"b":0,"char":" ","brightness":0.00},
    {"x":30,"y":24,"r":0,"g":0,"b":0,"char":" ","brightness":0.00},
    {"x":31,"y":24,"r":0,"g":0,"b":0,"char":" ","brightness":0.00},
    {"x":32,"y":24,"r":0,"g":0,"b":0,"char":" ","brightness":0.00},
    {"x":33,"y":24,"r":0,"g":0,"b":0,"char":" ","brightness":0.00},
    {"x":34,"y":24,"r":0,"g":0,"b":0,"char":" ","brightness":0.00},
    {"x":35,"y":24,"r":0,"g":0,"b":0,"char":" ","brightness":0.00},
    {"x":36,"y":24,"r":0,"g":0,"b":0,"char":" ","brightness":0.00},
    {"x":37,"y":24,"r":0,"g":0,"b":0,"char":" ","brightness":0.00},
    {"x":38,"y":24,"r":0,"g":0,"b":0,"char":" ","brightness":0.00},
    {"x":39,"y":24,"r":0,"g":0,"b":0,"char":" ","brightness":0.00},
    {"x":40,"y":24,"r":0,"g":0,"b":0,"char":" ","brightness":0.00},
    {"x":41,"y":24,"r":0,"g":0,"b":0,"char":" ","brightness":0.00},
    {"x":42,"y":24,"r":0,"g":0,"b":0,"char":" ","brightness":0.00},
    {"x":43,"y":24,"r":0,"g":0,"b":0,"char":" ","brightness":0.00},
    {"x":44,"y":24,"r":0,"g":0,"b":0,"char":" ","brightness":0.00},
    {"x":45,"y":24,"r":0,"g":0,"b":0,"char":" ","brightness":0.00},
    {"x":46,"y":24,"r":0,"g":0,"b":0,"char":" ","brightness":0.00},
    {"x":47,"y":24,"r":0,"g":0,"b":0,"char":" ","brightness":0.00},
    {"x":0,"y":25,"r":0,"g":0,"b":0,"char":" ","brightness":0.00},
    {"x":1,"y":25,"r":0,"g":0,"b":0,"char":" ","brightness":0.00},
    {"x":2,"y":25,"r":0,"g":0,"b":0,"char":" ","brightness":0.00},
    {"x":3,"y":25,"r":0,"g":0,"b":0,"char":" ","brightness":0.00},
    {"x":4,"y":25,"r":0,"g":0,"b":0,"char":" ","brightness":0.00},
    {"x":5,"y":25,"r":0,"g":0,"b":0,"char":" ","brightness":0.00},
    {"x":6,"y":25,"r":0,"g":0,"b":0,"char":" ","brightness":0.00},
    {"x":7,"y":25,"r":0,"g":0,"b":0,"char":" ","brightness":0.00},
    {"x":8,"y":25,"r":0,"g":0,"b":0,"char":" ","brightness":0.00},
    {"x":9,"y":25,"r":0,"g":0,"b":0,"char":" ","brightness":0.00},
    {"x":10,"y":25,"r":0,"g":0,"b":0,"char":" ","brightness":0.00},
    {"x":11,"y":25,"r":0,"g":0,"b":0,"char":" ","brightness":0.00},
    {"x":12,"y":25,"r":0,"g":0,"b":0,"char":" ","brightness":0.00},
    {"x":13,"y":25,"r":0,"g":0,"b":0,"char":" ","brightness":0.00},
    {"x":14,"y":25,"r":0,"g":0,"b":0,"char":" ","brightness":0.00},
    {"x":15,"y":25,"r":0,"g":0,"b":0,"char":" ","brightness":0.00},
    {"x":16,"y":25,"r":0,"g":0,"b":0,"char":" ","brightness":0.00},
    {"x":17,"y":25,"r":0,"g":0,"b":0,"char":" ","brightness":0.00},
    {"x":18,"y":25,"r":0,"g":0,"b":0,"char":" ","brightness":0.00},
    {"x":19,"y":25,"r":0,"g":0,"b":0,"char":" ","brightness":0.00},
    {"x":20,"y":25,"r":0,"g":0,"b":0,"char":" ","brightness":0.00},
    {"x":21,"y":25,"r":0,"g":0,"b":0,"char":" ","brightness":0.00},
    {"x":22,"y":25,"r":0,"g":0,"b":0,"char":" ","brightness":0.00},
    {"x":23,"y":25,"r":0,"g":0,"b":0,"char":" ","brightness":0.00},
    {"x":24,"y":25,"r":0,"g":0,"b":0,"char":" ","brightness":0.00},
    {"x":25,"y":25,"r":0,"g":0,"b":0,"char":" ","brightness":0.00},
    {"x":26,"y":25,"r":0,"g":0,"b":0,"char":" ","brightness":0.00},
    {"x":27,"y":25,"r":0,"g":0,"b":0,"char":" ","brightness":0.00},
    {"x":28,"y":25,"r":0,"g":0,"b":0,"char":" ","brightness":0.00},
    {"x":29,"y":25,"r":0,"g":0,"b":0,"char":" ","brightness":0.00},
    {"x":30,"y":25,"r":0,"g":0,"b":0,"char":" ","brightness":0.00},
    {"x":31,"y":25,"r":0,"g":0,"b":0,"char":" ","brightness":0.00},
    {"x":32,"y":25,"r":0,"g":0,"b":0,"char":" ","brightness":0.00},
    {"x":33,"y":25,"r":0,"g":0,"b":0,"char":" ","brightness":0.00},
    {"x":34,"y":25,"r":0,"g":0,"b":0,"char":" ","brightness":0.00},
    {"x":35,"y":25,"r":0,"g":0,"b":0,"char":" ","brightness":0.00},
    {"x":36,"y":25,"r":0,"g":0,"b":0,"char":" ","brightness":0.00},
    {"x":37,"y":25,"r":0,"g":0,"b":0,"char":" ","brightness":0.00},
    {"x":38,"y":25,"r":0,"g":0,"b":0,"char":" ","brightness":0.00},
    {"x":39,"y":25,"r":0,"g":0,"b":0,"char":" ","brightness":0.00},
    {"x":40,"y":25,"r":0,"g":0,"b":0,"char":" ","brightness":0.00},
    {"x":41,"y":25,"r":0,"g":0,"b":0,"char":" ","brightness":0.00},
    {"x":42,"y":25,"r":0,"g":0,"b":0,"char":" ","brightness":0.00},
    {"x":43,"y":25,"r":0,"g":0,"b":0,"char":" ","brightness":0.00},
    {"x":44,"y":25,"r":0,"g":0,"b":0,"char":" ","brightness":0.00},
    {"x":45,"y":25,"r":0,"g":0,"b":0,"char":" ","brightness":0.00},
    {"x":46,"y":25,"r":0,"g":0,"b":0,"char":" ","brightness":0.00},
    {"x":47,"y":25,"r":0,"g":0,"b":0,"char":" ","brightness":0.00}
  ]
}
