{
  "width": 42,
  "height": 23,
  "pixels": [
    {"x":0,"y":0,"r":0,"g":0,"b":0,"char":" ","brightness":0.00},
    {"x":1,"y":0,"r":0,"g":0,"b":0,"char":" ","brightness":0.00},
    {"x":2,"y":0,"r":0,"g":0,"b":0,"char":" ","brightness":0.00},
    {"x":3,"y":0,"r":0,"g":0,"b":0,"char":" ","brightness":0.00},
    {"x":4,"y":0,"r":0,"g":0,"b":0,"char":" ","brightness":0.00},
    {"x":5,"y":0,"r":0,"g":0,"b":0,"char":" ","brightness":0.00},
    {"x":6,"y":0,"r":40,"g":44,"b":50,"char":" ","brightness":43.49},
    {"x":7,"y":0,"r":44,"g":0,"b":0,"char":" ","brightness":13.16},
    {"x":8,"y":0,"r":33,"g":61,"b":95,"char":" ","brightness":56.50},
    {"x":9,"y":0,"r":33,"g":58,"b":109,"char":" ","brightness":56.34},
    {"x":10,"y":0,"r":0,"g":0,"b":0,"char":" ","brightness":0.00},
    {"x":11,"y":0,"r":30,"g":60,"b":88,"char":"*","brightness":54.22},
    {"x":12,"y":0,"r":27,"g":64,"b":100,"char":"*","brightness":57.04},
    {"x":13,"y":0,"r":29,"g":53,"b":91,"char":"*","brightness":50.16},
    {"x":14,"y":0,"r":32,"g":55,"b":96,"char":"*","brightness":52.80},
    {"x":15,"y":0,"r":33,"g":62,"b":108,"char":"*","brightness":58.57},
    {"x":16,"y":0,"r":35,"g":60,"b":108,"char":"*","brightness":58.00},
    {"x":17,"y":0,"r":37,"g":62,"b":111,"char":"*","brightness":60.11},
    {"x":18,"y":0,"r":35,"g":61,"b":110,"char":"*","brightness":58.81},
    {"x":19,"y":0,"r":36,"g":63,"b":115,"char":"*","brightness":60.85},
    {"x":20,"y":0,"r":36,"g":63,"b":115,"char":"*","brightness":60.85},
    {"x":21,"y":0,"r":36,"g":63,"b":115,"char":"*","brightness":60.85},
    {"x":22,"y":0,"r":36,"g":63,"b":115,"char":"*","brightness":60.85},
    {"x":23,"y":0,"r":35,"g":60,"b":110,"char":"*","brightness":58.23},
    {"x":24,"y":0,"r":37,"g":62,"b":112,"char":"*","brightness":60.22},
    {"x":25,"y":0,"r":35,"g":63,"b":111,"char":"*","brightness":60.10},
    {"x":26,"y":0,"r":33,"g":62,"b":108,"char":"*","brightness":58.57},
    {"x":27,"y":0,"r":32,"g":56,"b":98,"char":"*","brightness":53.61},
    {"x":28,"y":0,"r":29,"g":55,"b":95,"char":"*","brightness":51.79},
    {"x":29,"y":0,"r":27,"g":72,"b":108,"char":"*","brightness":62.65},
    {"x":30,"y":0,"r":29,"g":56,"b":83,"char":"*","brightness":51.00},
    {"x":31,"y":0,"r":0,"g":0,"b":0,"char":" ","brightness":0.00},
    {"x":32,"y":0,"r":32,"g":58,"b":107,"char":" ","brightness":55.81},
    {"x":33,"y":0,"r":33,"g":61,"b":95,"char":" ","brightness":56.50},
    {"x":34,"y":0,"r":44,"g":0,"b":0,"char":" ","brightness":13.16},
    {"x":35,"y":0,"r":40,"g":44,"b":50,"char":" ","brightness":43.49},
    {"x":36,"y":0,"r":0,"g":0,"b":0,"char":" ","brightness":0.00},
    {"x":37,"y":0,"r":0,"g":0,"b":0,"char":" ","brightness":0.00},
    {"x":38,"y":0,"r":0,"g":0,"b":0,"char":" ","brightness":0.00},
    {"x":39,"y":0,"r":0,"g":0,"b":0,"char":" ","brightness":0.00},
    {"x":40,"y":0,"r":0,"g":0,"b":0,"char":" ","brightness":0.00},
    {"x":41,"y":0,"r":0,"g":0,"b":0,"char":" ","brightness":0.00},
    {"x":0,"y":1,"r":0,"g":0,"b":0,"char":" ","brightness":0.00},
    {"x":1,"y":1,"r":0,"g":0,"b":0,"char":" ","brightness":0.00},
    {"x":2,"y":1,"r":0,"g":0,"b":0,"char":" ","brightness":0.00},
    {"x":3,"y":1,"r":0,"g":0,"b":0,"char":" ","brightness":0.00},
    {"x":4,"y":1,"r":48,"g":58,"b":64,"char":" ","brightness":55.69},
    {"x":5,"y":1,"r":51,"g":60,"b":38,"char":" ","brightness":54.80},
    {"x":6,"y":1,"r":25,"g":64,"b":91,"char":" ","brightness":55.42},
    {"x":7,"y":1,"r":28,"g":81,"b":165,"char":" ","brightness":74.73},
    {"x":8,"y":1,"r":33,"g":59,"b":91,"char":"*","brightness":54.87},
    {"x":9,"y":1,"r":29,"g":56,"b":103,"char":"*","brightness":53.28},
    {"x":10,"y":1,"r":34,"g":59,"b":104,"char":"*","brightness":56.65},
    {"x":11,"y":1,"r":35,"g":62,"b":110,"char":"*","brightness":59.40},
    {"x":12,"y":1,"r":35,"g":63,"b":113,"char":"*","brightness":60.33},
    {"x":13,"y":1,"r":35,"g":62,"b":113,"char":"*","brightness":59.74},
    {"x":14,"y":1,"r":36,"g":63,"b":114,"char":"*","brightness":60.74},
    {"x":15,"y":1,"r":36,"g":63,"b":115,"char":"*","brightness":60.85},
    {"x":16,"y":1,"r":36,"g":63,"b":115,"char":"*","brightness":60.85},
    {"x":17,"y":1,"r":36,"g":63,"b":115,"char":"*","brightness":60.85},
    {"x":18,"y":1,"r":36,"g":63,"b":115,"char":"*","brightness":60.85},
    {"x":19,"y":1,"r":36,"g":63,"b":115,"char":"*","brightness":60.85},
    {"x":20,"y":1,"r":36,"g":63,"b":115,"char":"*","brightness":60.85},
    {"x":21,"y":1,"r":36,"g":63,"b":115,"char":"*","brightness":60.85},
    {"x":22,"y":1,"r":36,"g":63,"b":115,"char":"*","brightness":60.85},
    {"x":23,"y":1,"r":35,"g":62,"b":115,"char":"*","brightness":59.97},
    {"x":24,"y":1,"r":34,"g":61,"b":114,"char":"*","brightness":58.97},
    {"x":25,"y":1,"r":33,"g":60,"b":113,"char":"*","brightness":57.97},
    {"x":26,"y":1,"r":33,"g":60,"b":113,"char":"*","brightness":57.97},
    {"x":27,"y":1,"r":32,"g":60,"b":112,"char":"*","brightness":57.56},
    {"x":28,"y":1,"r":32,"g":60,"b":111,"char":"*","brightness":57.44},
    {"x":29,"y":1,"r":33,"g":63,"b":113,"char":"*","brightness":59.73},
    {"x":30,"y":1,"r":34,"g":61,"b":108,"char":"*","brightness":58.28},
    {"x":31,"y":1,"r":34,"g":58,"b":102,"char":"*","brightness":55.84},
    {"x":32,"y":1,"r":29,"g":56,"b":103,"char":"*","brightness":53.28},
    {"x":33,"y":1,"r":33,"g":59,"b":91,"char":"*","brightness":54.87},
    {"x":34,"y":1,"r":28,"g":81,"b":165,"char":" ","brightness":74.73},
    {"x":35,"y":1,"r":25,"g":64,"b":91,"char":" ","brightness":55.42},
    {"x":36,"y":1,"r":51,"g":61,"b":38,"char":" ","brightness":55.39},
    {"x":37,"y":1,"r":48,"g":58,"b":64,"char":" ","brightness":55.69},
    {"x":38,"y":1,"r":0,"g":0,"b":0,"char":" ","brightness":0.00},
    {"x":39,"y":1,"r":0,"g":0,"b":0,"char":" ","brightness":0.00},
    {"x":40,"y":1,"r":0,"g":0,"b":0,"char":" ","brightness":0.00},
    {"x":41,"y":1,"r":0,"g":0,"b":0,"char":" ","brightness":0.00},
    {"x":0,"y":2,"r":0,"g":0,"b":0,"char":" ","brightness":0.00},
    {"x":1,"y":2,"r":0,"g":0,"b":0,"char":" ","brightness":0.00},
    {"x":2,"y":2,"r":13,"g":14,"b":17,"char":" ","brightness":14.04},
    {"x":3,"y":2,"r":36,"g":50,"b":115,"char":" ","brightness":53.22},
    {"x":4,"y":2,"r":25,"g":42,"b":75,"char":" ","brightness":40.68},
    {"x":5,"y":2,"r":12,"g":35,"b":143,"char":" ","brightness":40.44},
    {"x":6,"y":2,"r":22,"g":61,"b":86,"char":"*","brightness":52.19},
    {"x":7,"y":2,"r":33,"g":55,"b":98,"char":"*","brightness":53.32},
    {"x":8,"y":2,"r":37,"g":63,"b":110,"char":"*","brightness":60.58},
    {"x":9,"y":2,"r":35,"g":62,"b":114,"char":"*","brightness":59.85},
    {"x":10,"y":2,"r":36,"g":63,"b":115,"char":"*","brightness":60.85},
    {"x":11,"y":2,"r":36,"g":63,"b":115,"char":"*","brightness":60.85},
    {"x":12,"y":2,"r":36,"g":63,"b":115,"char":"*","brightness":60.85},
    {"x":13,"y":2,"r":36,"g":63,"b":115,"char":"*","brightness":60.85},
    {"x":14,"y":2,"r":36,"g":63,"b":115,"char":"*","brightness":60.85},
    {"x":15,"y":2,"r":36,"g":63,"b":115,"char":"*","brightness":60.85},
    {"x":16,"y":2,"r":36,"g":63,"b":115,"char":"*","brightness":60.85},
    {"x":17,"y":2,"r":36,"g":63,"b":115,"char":"*","brightness":60.85},
    {"x":18,"y":2,"r":36,"g":63,"b":115,"char":"*","brightness":60.85},
    {"x":19,"y":2,"r":36,"g":63,"b":115,"char":"*","brightness":60.85},
    {"x":20,"y":2,"r":35,"g":62,"b":114,"char":"*","brightness":59.85},
    {"x":21,"y":2,"r":33,"g":60,"b":113,"char":"*","brightness":57.97},
    {"x":22,"y":2,"r":36,"g":63,"b":115,"char":"*","brightness":60.85},
    {"x":23,"y":2,"r":49,"g":74,"b":124,"char":"*","brightness":72.22},
    {"x":24,"y":2,"r":69,"g":91,"b":136,"char":"*","brightness":89.55},
    {"x":25,"y":2,"r":87,"g":107,"b":148,"char":"*","brightness":105.69},
    {"x":26,"y":2,"r":96,"g":116,"b":154,"char":"*","brightness":114.35},
    {"x":27,"y":2,"r":97,"g":116,"b":154,"char":"*","brightness":114.65},
    {"x":28,"y":2,"r":89,"g":109,"b":150,"char":"*","brightness":107.69},
    {"x":29,"y":2,"r":70,"g":92,"b":137,"char":"*","brightness":90.55},
    {"x":30,"y":2,"r":44,"g":71,"b":123,"char":"*","brightness":68.86},
    {"x":31,"y":2,"r":35,"g":63,"b":115,"char":"*","brightness":60.56},
    {"x":32,"y":2,"r":35,"g":61,"b":113,"char":"*","brightness":59.15},
    {"x":33,"y":2,"r":37,"g":62,"b":110,"char":"*","brightness":60.00},
    {"x":34,"y":2,"r":33,"g":55,"b":98,"char":"*","brightness":53.32},
    {"x":35,"y":2,"r":22,"g":61,"b":86,"char":"*","brightness":52.19},
    {"x":36,"y":2,"r":0,"g":42,"b":150,"char":" ","brightness":41.75},
    {"x":37,"y":2,"r":26,"g":44,"b":77,"char":" ","brightness":42.38},
    {"x":38,"y":2,"r":35,"g":53,"b":118,"char":" ","brightness":55.03},
    {"x":39,"y":2,"r":13,"g":14,"b":17,"char":" ","brightness":14.04},
    {"x":40,"y":2,"r":0,"g":0,"b":0,"char":" ","brightness":0.00},
    {"x":41,"y":2,"r":0,"g":0,"b":0,"char":" ","brightness":0.00},
    {"x":0,"y":3,"r":0,"g":0,"b":0,"char":" ","brightness":0.00},
    {"x":1,"y":3,"r":14,"g":18,"b":56,"char":" ","brightness":21.14},
    {"x":2,"y":3,"r":0,"g":0,"b":17,"char":" ","brightness":1.94},
    {"x":3,"y":3,"r":25,"g":47,"b":104,"char":" ","brightness":46.92},
    {"x":4,"y":3,"r":16,"g":31,"b":58,"char":"*","brightness":29.59},
    {"x":5,"y":3,"r":31,"g":60,"b":97,"char":"*","brightness":55.55},
    {"x":6,"y":3,"r":35,"g":66,"b":111,"char":"*","brightness":61.86},
    {"x":7,"y":3,"r":35,"g":62,"b":114,"char":"*","brightness":59.85},
    {"x":8,"y":3,"r":36,"g":63,"b":115,"char":"*","brightness":60.85},
    {"x":9,"y":3,"r":36,"g":63,"b":115,"char":"*","brightness":60.85},
    {"x":10,"y":3,"r":36,"g":63,"b":115,"char":"*","brightness":60.85},
    {"x":11,"y":3,"r":36,"g":63,"b":115,"char":"*","brightness":60.85},
    {"x":12,"y":3,"r":36,"g":63,"b":115,"char":"*","brightness":60.85},
    {"x":13,"y":3,"r":36,"g":63,"b":115,"char":"*","brightness":60.85},
    {"x":14,"y":3,"r":36,"g":63,"b":115,"char":"*","brightness":60.85},
    {"x":15,"y":3,"r":36,"g":63,"b":115,"char":"*","brightness":60.85},
    {"x":16,"y":3,"r":36,"g":63,"b":115,"char":"*","brightness":60.85},
    {"x":17,"y":3,"r":36,"g":63,"b":115,"char":"*","brightness":60.85},
    {"x":18,"y":3,"r":36,"g":63,"b":115,"char":"*","brightness":60.85},
    {"x":19,"y":3,"r":33,"g":61,"b":113,"char":"*","brightness":58.56},
    {"x":20,"y":3,"r":50,"g":75,"b":124,"char":"*","brightness":73.11},
    {"x":21,"y":3,"r":104,"g":121,"b":158,"char":"*","brightness":120.14},
    {"x":22,"y":3,"r":165,"g":176,"b":198,"char":"$","brightness":175.22},
    {"x":23,"y":3,"r":209,"g":214,"b":226,"char":"$","brightness":213.87},
    {"x":24,"y":3,"r":234,"g":236,"b":241,"char":"$","brightness":235.97},
    {"x":25,"y":3,"r":245,"g":246,"b":249,"char":"$","brightness":246.04},
    {"x":26,"y":3,"r":250,"g":250,"b":251,"char":"$","brightness":250.11},
    {"x":27,"y":3,"r":250,"g":250,"b":252,"char":"$","brightness":250.23},
    {"x":28,"y":3,"r":246,"g":247,"b":250,"char":"$","brightness":247.04},
    {"x":29,"y":3,"r":235,"g":237,"b":243,"char":"$","brightness":237.09},
    {"x":30,"y":3,"r":188,"g":199,"b":219,"char":"$","brightness":197.99},
    {"x":31,"y":3,"r":77,"g":113,"b":168,"char":"*","brightness":108.51},
    {"x":32,"y":3,"r":43,"g":80,"b":140,"char":"*","brightness":75.78},
    {"x":33,"y":3,"r":39,"g":68,"b":123,"char":"*","brightness":65.60},
    {"x":34,"y":3,"r":35,"g":62,"b":113,"char":"*","brightness":59.74},
    {"x":35,"y":3,"r":36,"g":65,"b":111,"char":"*","brightness":61.57},
    {"x":36,"y":3,"r":35,"g":64,"b":101,"char":"*","brightness":59.55},
    {"x":37,"y":3,"r":15,"g":36,"b":64,"char":"*","brightness":32.91},
    {"x":38,"y":3,"r":25,"g":49,"b":106,"char":" ","brightness":48.32},
    {"x":39,"y":3,"r":0,"g":0,"b":16,"char":" ","brightness":1.82},
    {"x":40,"y":3,"r":14,"g":18,"b":56,"char":" ","brightness":21.14},
    {"x":41,"y":3,"r":0,"g":0,"b":0,"char":" ","brightness":0.00},
    {"x":0,"y":4,"r":13,"g":17,"b":80,"char":" ","brightness":22.99},
    {"x":1,"y":4,"r":17,"g":15,"b":56,"char":" ","brightness":20.27},
    {"x":2,"y":4,"r":56,"g":98,"b":134,"char":" ","brightness":89.55},
    {"x":3,"y":4,"r":24,"g":49,"b":94,"char":"*","brightness":46.66},
    {"x":4,"y":4,"r":33,"g":59,"b":105,"char":"*","brightness":56.47},
    {"x":5,"y":4,"r":35,"g":62,"b":113,"char":"*","brightness":59.74},
    {"x":6,"y":4,"r":36,"g":63,"b":115,"char":"*","brightness":60.85},
    {"x":7,"y":4,"r":36,"g":63,"b":115,"char":"*","brightness":60.85},
    {"x":8,"y":4,"r":36,"g":63,"b":115,"char":"*","brightness":60.85},
    {"x":9,"y":4,"r":36,"g":63,"b":115,"char":"*","brightness":60.85},
    {"x":10,"y":4,"r":36,"g":63,"b":115,"char":"*","brightness":60.85},
    {"x":11,"y":4,"r":36,"g":63,"b":115,"char":"*","brightness":60.85},
    {"x":12,"y":4,"r":36,"g":63,"b":115,"char":"*","brightness":60.85},
    {"x":13,"y":4,"r":36,"g":63,"b":115,"char":"*","brightness":60.85},
    {"x":14,"y":4,"r":36,"g":63,"b":115,"char":"*","brightness":60.85},
    {"x":15,"y":4,"r":36,"g":63,"b":115,"char":"*","brightness":60.85},
    {"x":16,"y":4,"r":36,"g":63,"b":115,"char":"*","brightness":60.85},
    {"x":17,"y":4,"r":35,"g":62,"b":115,"char":"*","brightness":59.97},
    {"x":18,"y":4,"r":38,"g":64,"b":116,"char":"*","brightness":62.15},
    {"x":19,"y":4,"r":102,"g":119,"b":157,"char":"*","brightness":118.25},
    {"x":20,"y":4,"r":201,"g":207,"b":221,"char":"$","brightness":206.80},
    {"x":21,"y":4,"r":249,"g":250,"b":251,"char":"$","brightness":249.81},
    {"x":22,"y":4,"r":255,"g":255,"b":255,"char":"$","brightness":255.00},
    {"x":23,"y":4,"r":255,"g":255,"b":255,"char":"$","brightness":255.00},
    {"x":24,"y":4,"r":255,"g":255,"b":255,"char":"$","brightness":255.00},
    {"x":25,"y":4,"r":255,"g":255,"b":255,"char":"$","brightness":255.00},
    {"x":26,"y":4,"r":254,"g":254,"b":254,"char":"$","brightness":254.00},
    {"x":27,"y":4,"r":253,"g":253,"b":253,"char":"$","brightness":253.00},
    {"x":28,"y":4,"r":255,"g":255,"b":255,"char":"$","brightness":255.00},
    {"x":29,"y":4,"r":255,"g":255,"b":255,"char":"$","brightness":255.00},
    {"x":30,"y":4,"r":234,"g":240,"b":248,"char":"$","brightness":239.12},
    {"x":31,"y":4,"r":102,"g":143,"b":199,"char":"$","brightness":137.12},
    {"x":32,"y":4,"r":55,"g":108,"b":180,"char":"*","brightness":100.36},
    {"x":33,"y":4,"r":54,"g":102,"b":171,"char":"*","brightness":95.51},
    {"x":34,"y":4,"r":46,"g":83,"b":144,"char":"*","brightness":78.89},
    {"x":35,"y":4,"r":37,"g":65,"b":118,"char":"*","brightness":62.67},
    {"x":36,"y":4,"r":35,"g":62,"b":113,"char":"*","brightness":59.74},
    {"x":37,"y":4,"r":33,"g":60,"b":106,"char":"*","brightness":57.17},
    {"x":38,"y":4,"r":24,"g":49,"b":94,"char":"*","brightness":46.66},
    {"x":39,"y":4,"r":56,"g":98,"b":135,"char":" ","brightness":89.66},
    {"x":40,"y":4,"r":16,"g":15,"b":56,"char":" ","brightness":19.97},
    {"x":41,"y":4,"r":13,"g":17,"b":80,"char":" ","brightness":22.99},
    {"x":0,"y":5,"r":6,"g":23,"b":59,"char":" ","brightness":22.02},
    {"x":1,"y":5,"r":30,"g":116,"b":140,"char":" ","brightness":93.02},
    {"x":2,"y":5,"r":33,"g":50,"b":90,"char":"*","brightness":49.48},
    {"x":3,"y":5,"r":33,"g":58,"b":110,"char":"*","brightness":56.45},
    {"x":4,"y":5,"r":36,"g":63,"b":115,"char":"*","brightness":60.85},
    {"x":5,"y":5,"r":36,"g":63,"b":115,"char":"*","brightness":60.85},
    {"x":6,"y":5,"r":36,"g":63,"b":115,"char":"*","brightness":60.85},
    {"x":7,"y":5,"r":36,"g":63,"b":115,"char":"*","brightness":60.85},
    {"x":8,"y":5,"r":36,"g":63,"b":115,"char":"*","brightness":60.85},
    {"x":9,"y":5,"r":36,"g":63,"b":115,"char":"*","brightness":60.85},
    {"x":10,"y":5,"r":36,"g":63,"b":115,"char":"*","brightness":60.85},
    {"x":11,"y":5,"r":36,"g":63,"b":115,"char":"*","brightness":60.85},
    {"x":12,"y":5,"r":36,"g":63,"b":115,"char":"*","brightness":60.85},
    {"x":13,"y":5,"r":36,"g":63,"b":115,"char":"*","brightness":60.85},
    {"x":14,"y":5,"r":36,"g":63,"b":115,"char":"*","brightness":60.85},
    {"x":15,"y":5,"r":36,"g":63,"b":115,"char":"*","brightness":60.85},
    {"x":16,"y":5,"r":36,"g":63,"b":115,"char":"*","brightness":60.85},
    {"x":17,"y":5,"r":38,"g":64,"b":116,"char":"*","brightness":62.15},
    {"x":18,"y":5,"r":131,"g":145,"b":176,"char":"$","brightness":144.35},
    {"x":19,"y":5,"r":242,"g":244,"b":247,"char":"$","brightness":243.74},
    {"x":20,"y":5,"r":255,"g":255,"b":255,"char":"$","brightness":255.00},
    {"x":21,"y":5,"r":255,"g":255,"b":255,"char":"$","brightness":255.00},
    {"x":22,"y":5,"r":255,"g":255,"b":255,"char":"$","brightness":255.00},
    {"x":23,"y":5,"r":237,"g":239,"b":244,"char":"$","brightness":238.97},
    {"x":24,"y":5,"r":183,"g":191,"b":209,"char":"$","brightness":190.66},
    {"x":25,"y":5,"r":136,"g":149,"b":179,"char":"$","brightness":148.53},
    {"x":26,"y":5,"r":110,"g":127,"b":162,"char":"*","brightness":125.91},
    {"x":27,"y":5,"r":106,"g":124,"b":160,"char":"*","brightness":122.72},
    {"x":28,"y":5,"r":116,"g":132,"b":166,"char":"$","brightness":131.09},
    {"x":29,"y":5,"r":118,"g":139,"b":178,"char":"$","brightness":137.17},
    {"x":30,"y":5,"r":89,"g":127,"b":183,"char":"*","brightness":122.02},
    {"x":31,"y":5,"r":59,"g":111,"b":182,"char":"*","brightness":103.55},
    {"x":32,"y":5,"r":57,"g":110,"b":181,"char":"*","brightness":102.25},
    {"x":33,"y":5,"r":57,"g":111,"b":182,"char":"*","brightness":102.95},
    {"x":34,"y":5,"r":57,"g":110,"b":180,"char":"*","brightness":102.13},
    {"x":35,"y":5,"r":50,"g":92,"b":156,"char":"*","brightness":86.74},
    {"x":36,"y":5,"r":38,"g":66,"b":120,"char":"*","brightness":63.78},
    {"x":37,"y":5,"r":36,"g":63,"b":115,"char":"*","brightness":60.85},
    {"x":38,"y":5,"r":33,"g":58,"b":110,"char":"*","brightness":56.45},
    {"x":39,"y":5,"r":33,"g":50,"b":91,"char":"*","brightness":49.59},
    {"x":40,"y":5,"r":30,"g":116,"b":140,"char":" ","brightness":93.02},
    {"x":41,"y":5,"r":6,"g":23,"b":59,"char":" ","brightness":22.02},
    {"x":0,"y":6,"r":45,"g":50,"b":111,"char":" ","brightness":55.46},
    {"x":1,"y":6,"r":25,"g":55,"b":91,"char":"*","brightness":50.13},
    {"x":2,"y":6,"r":36,"g":60,"b":111,"char":"*","brightness":58.64},
    {"x":3,"y":6,"r":36,"g":63,"b":115,"char":"*","brightness":60.85},
    {"x":4,"y":6,"r":36,"g":63,"b":115,"char":"*","brightness":60.85},
    {"x":5,"y":6,"r":36,"g":63,"b":115,"char":"*","brightness":60.85},
    {"x":6,"y":6,"r":36,"g":63,"b":115,"char":"*","brightness":60.85},
    {"x":7,"y":6,"r":36,"g":63,"b":115,"char":"*","brightness":60.85},
    {"x":8,"y":6,"r":36,"g":63,"b":115,"char":"*","brightness":60.85},
    {"x":9,"y":6,"r":36,"g":63,"b":115,"char":"*","brightness":60.85},
    {"x":10,"y":6,"r":36,"g":63,"b":115,"char":"*","brightness":60.85},
    {"x":11,"y":6,"r":36,"g":63,"b":115,"char":"*","brightness":60.85},
    {"x":12,"y":6,"r":36,"g":63,"b":115,"char":"*","brightness":60.85},
    {"x":13,"y":6,"r":36,"g":63,"b":115,"char":"*","brightness":60.85},
    {"x":14,"y":6,"r":36,"g":63,"b":115,"char":"*","brightness":60.85},
    {"x":15,"y":6,"r":36,"g":63,"b":115,"char":"*","brightness":60.85},
    {"x":16,"y":6,"r":33,"g":61,"b":113,"char":"*","brightness":58.56},
    {"x":17,"y":6,"r":94,"g":112,"b":152,"char":"*","brightness":111.18},
    {"x":18,"y":6,"r":241,"g":242,"b":246,"char":"$","brightness":242.16},
    {"x":19,"y":6,"r":255,"g":255,"b":255,"char":"$","brightness":255.00},
    {"x":20,"y":6,"r":255,"g":255,"b":255,"char":"$","brightness":255.00},
    {"x":21,"y":6,"r":255,"g":255,"b":255,"char":"$","brightness":255.00},
    {"x":22,"y":6,"r":202,"g":208,"b":221,"char":"$","brightness":207.69},
    {"x":23,"y":6,"r":85,"g":106,"b":147,"char":"*","brightness":104.39},
    {"x":24,"y":6,"r":40,"g":66,"b":117,"char":"*","brightness":64.04},
    {"x":25,"y":6,"r":33,"g":60,"b":113,"char":"*","brightness":57.97},
    {"x":26,"y":6,"r":32,"g":60,"b":113,"char":"*","brightness":57.67},
    {"x":27,"y":6,"r":32,"g":60,"b":113,"char":"*","brightness":57.67},
    {"x":28,"y":6,"r":32,"g":60,"b":113,"char":"*","brightness":57.67},
    {"x":29,"y":6,"r":33,"g":60,"b":113,"char":"*","brightness":57.97},
    {"x":30,"y":6,"r":37,"g":67,"b":122,"char":"*","brightness":64.30},
    {"x":31,"y":6,"r":48,"g":89,"b":152,"char":"*","brightness":83.92},
    {"x":32,"y":6,"r":57,"g":109,"b":179,"char":"*","brightness":101.43},
    {"x":33,"y":6,"r":57,"g":110,"b":181,"char":"*","brightness":102.25},
    {"x":34,"y":6,"r":57,"g":110,"b":181,"char":"*","brightness":102.25},
    {"x":35,"y":6,"r":57,"g":110,"b":181,"char":"*","brightness":102.25},
    {"x":36,"y":6,"r":47,"g":86,"b":147,"char":"*","brightness":81.29},
    {"x":37,"y":6,"r":36,"g":63,"b":115,"char":"*","brightness":60.85},
    {"x":38,"y":6,"r":36,"g":63,"b":115,"char":"*","brightness":60.85},
    {"x":39,"y":6,"r":36,"g":60,"b":111,"char":"*","brightness":58.64},
    {"x":40,"y":6,"r":25,"g":55,"b":90,"char":"*","brightness":50.02},
    {"x":41,"y":6,"r":45,"g":50,"b":111,"char":" ","brightness":55.46},
    {"x":0,"y":7,"r":19,"g":36,"b":54,"char":"*","brightness":32.97},
    {"x":1,"y":7,"r":31,"g":59,"b":102,"char":"*","brightness":55.53},
    {"x":2,"y":7,"r":36,"g":63,"b":115,"char":"*","brightness":60.85},
    {"x":3,"y":7,"r":36,"g":63,"b":115,"char":"*","brightness":60.85},
    {"x":4,"y":7,"r":36,"g":63,"b":115,"char":"*","brightness":60.85},
    {"x":5,"y":7,"r":36,"g":63,"b":115,"char":"*","brightness":60.85},
    {"x":6,"y":7,"r":36,"g":63,"b":115,"char":"*","brightness":60.85},
    {"x":7,"y":7,"r":36,"g":63,"b":115,"char":"*","brightness":60.85},
    {"x":8,"y":7,"r":36,"g":63,"b":115,"char":"*","brightness":60.85},
    {"x":9,"y":7,"r":36,"g":63,"b":115,"char":"*","brightness":60.85},
    {"x":10,"y":7,"r":36,"g":63,"b":115,"char":"*","brightness":60.85},
    {"x":11,"y":7,"r":36,"g":63,"b":115,"char":"*","brightness":60.85},
    {"x":12,"y":7,"r":36,"g":63,"b":115,"char":"*","brightness":60.85},
    {"x":13,"y":7,"r":36,"g":63,"b":115,"char":"*","brightness":60.85},
    {"x":14,"y":7,"r":36,"g":63,"b":115,"char":"*","brightness":60.85},
    {"x":15,"y":7,"r":36,"g":63,"b":115,"char":"*","brightness":60.85},
    {"x":16,"y":7,"r":35,"g":62,"b":115,"char":"*","brightness":59.97},
    {"x":17,"y":7,"r":163,"g":172,"b":196,"char":"$","brightness":172.04},
    {"x":18,"y":7,"r":255,"g":255,"b":255,"char":"$","brightness":255.00},
    {"x":19,"y":7,"r":255,"g":255,"b":255,"char":"$","brightness":255.00},
    {"x":20,"y":7,"r":255,"g":255,"b":255,"char":"$","brightness":255.00},
    {"x":21,"y":7,"r":239,"g":241,"b":246,"char":"$","brightness":240.97},
    {"x":22,"y":7,"r":85,"g":105,"b":146,"char":"*","brightness":103.69},
    {"x":23,"y":7,"r":31,"g":59,"b":112,"char":"*","brightness":56.67},
    {"x":24,"y":7,"r":36,"g":63,"b":115,"char":"*","brightness":60.85},
    {"x":25,"y":7,"r":36,"g":63,"b":115,"char":"*","brightness":60.85},
    {"x":26,"y":7,"r":36,"g":63,"b":115,"char":"*","brightness":60.85},
    {"x":27,"y":7,"r":36,"g":63,"b":115,"char":"*","brightness":60.85},
    {"x":28,"y":7,"r":36,"g":63,"b":115,"char":"*","brightness":60.85},
    {"x":29,"y":7,"r":36,"g":63,"b":115,"char":"*","brightness":60.85},
    {"x":30,"y":7,"r":36,"g":63,"b":114,"char":"*","brightness":60.74},
    {"x":31,"y":7,"r":37,"g":65,"b":118,"char":"*","brightness":62.67},
    {"x":32,"y":7,"r":52,"g":97,"b":163,"char":"*","brightness":91.07},
    {"x":33,"y":7,"r":57,"g":111,"b":182,"char":"*","brightness":102.95},
    {"x":34,"y":7,"r":57,"g":110,"b":181,"char":"*","brightness":102.25},
    {"x":35,"y":7,"r":57,"g":111,"b":182,"char":"*","brightness":102.95},
    {"x":36,"y":7,"r":54,"g":101,"b":169,"char":"*","brightness":94.70},
    {"x":37,"y":7,"r":38,"g":66,"b":120,"char":"*","brightness":63.78},
    {"x":38,"y":7,"r":36,"g":63,"b":115,"char":"*","brightness":60.85},
    {"x":39,"y":7,"r":36,"g":63,"b":115,"char":"*","brightness":60.85},
    {"x":40,"y":7,"r":31,"g":59,"b":102,"char":"*","brightness":55.53},
    {"x":41,"y":7,"r":19,"g":36,"b":54,"char":"*","brightness":32.97},
    {"x":0,"y":8,"r":31,"g":60,"b":96,"char":"*","brightness":55.43},
    {"x":1,"y":8,"r":35,"g":62,"b":112,"char":"*","brightness":59.63},
    {"x":2,"y":8,"r":36,"g":63,"b":115,"char":"*","brightness":60.85},
    {"x":3,"y":8,"r":36,"g":63,"b":115,"char":"*","brightness":60.85},
    {"x":4,"y":8,"r":36,"g":63,"b":115,"char":"*","brightness":60.85},
    {"x":5,"y":8,"r":36,"g":63,"b":115,"char":"*","brightness":60.85},
    {"x":6,"y":8,"r":36,"g":63,"b":115,"char":"*","brightness":60.85},
    {"x":7,"y":8,"r":36,"g":63,"b":115,"char":"*","brightness":60.85},
    {"x":8,"y":8,"r":36,"g":63,"b":115,"char":"*","brightness":60.85},
    {"x":9,"y":8,"r":36,"g":63,"b":115,"char":"*","brightness":60.85},
    {"x":10,"y":8,"r":36,"g":63,"b":115,"char":"*","brightness":60.85},
    {"x":11,"y":8,"r":36,"g":63,"b":115,"char":"*","brightness":60.85},
    {"x":12,"y":8,"r":36,"g":63,"b":115,"char":"*","brightness":60.85},
    {"x":13,"y":8,"r":36,"g":63,"b":115,"char":"*","brightness":60.85},
    {"x":14,"y":8,"r":36,"g":63,"b":115,"char":"*","brightness":60.85},
    {"x":15,"y":8,"r":36,"g":63,"b":115,"char":"*","brightness":60.85},
    {"x":16,"y":8,"r":38,"g":65,"b":117,"char":"*","brightness":62.86},
    {"x":17,"y":8,"r":180,"g":190,"b":209,"char":"$","brightness":189.18},
    {"x":18,"y":8,"r":255,"g":255,"b":255,"char":"$","brightness":255.00},
    {"x":19,"y":8,"r":255,"g":255,"b":255,"char":"$","brightness":255.00},
    {"x":20,"y":8,"r":255,"g":255,"b":255,"char":"$","brightness":255.00},
    {"x":21,"y":8,"r":223,"g":227,"b":236,"char":"$","brightness":226.83},
    {"x":22,"y":8,"r":58,"g":83,"b":131,"char":"*","brightness":81.00},
    {"x":23,"y":8,"r":35,"g":62,"b":114,"char":"*","brightness":59.85},
    {"x":24,"y":8,"r":36,"g":63,"b":115,"char":"*","brightness":60.85},
    {"x":25,"y":8,"r":36,"g":63,"b":115,"char":"*","brightness":60.85},
    {"x":26,"y":8,"r":36,"g":63,"b":115,"char":"*","brightness":60.85},
    {"x":27,"y":8,"r":36,"g":63,"b":115,"char":"*","brightness":60.85},
    {"x":28,"y":8,"r":36,"g":63,"b":115,"char":"*","brightness":60.85},
    {"x":29,"y":8,"r":36,"g":63,"b":115,"char":"*","brightness":60.85},
    {"x":30,"y":8,"r":36,"g":63,"b":115,"char":"*","brightness":60.85},
    {"x":31,"y":8,"r":36,"g":63,"b":116,"char":"*","brightness":60.97},
    {"x":32,"y":8,"r":51,"g":95,"b":160,"char":"*","brightness":89.25},
    {"x":33,"y":8,"r":57,"g":111,"b":182,"char":"*","brightness":102.95},
    {"x":34,"y":8,"r":57,"g":110,"b":181,"char":"*","brightness":102.25},
    {"x":35,"y":8,"r":57,"g":111,"b":182,"char":"*","brightness":102.95},
    {"x":36,"y":8,"r":54,"g":103,"b":171,"char":"*","brightness":96.10},
    {"x":37,"y":8,"r":38,"g":67,"b":121,"char":"*","brightness":64.48},
    {"x":38,"y":8,"r":36,"g":63,"b":115,"char":"*","brightness":60.85},
    {"x":39,"y":8,"r":36,"g":63,"b":115,"char":"*","brightness":60.85},
    {"x":40,"y":8,"r":35,"g":62,"b":112,"char":"*","brightness":59.63},
    {"x":41,"y":8,"r":31,"g":60,"b":96,"char":"*","brightness":55.43},
    {"x":0,"y":9,"r":36,"g":61,"b":107,"char":"*","brightness":58.77},
    {"x":1,"y":9,"r":36,"g":63,"b":115,"char":"*","brightness":60.85},
    {"x":2,"y":9,"r":36,"g":63,"b":115,"char":"*","brightness":60.85},
    {"x":3,"y":9,"r":36,"g":63,"b":115,"char":"*","brightness":60.85},
    {"x":4,"y":9,"r":36,"g":63,"b":115,"char":"*","brightness":60.85},
    {"x":5,"y":9,"r":36,"g":63,"b":115,"char":"*","brightness":60.85},
    {"x":6,"y":9,"r":36,"g":63,"b":115,"char":"*","brightness":60.85},
    {"x":7,"y":9,"r":36,"g":63,"b":115,"char":"*","brightness":60.85},
    {"x":8,"y":9,"r":36,"g":63,"b":115,"char":"*","brightness":60.85},
    {"x":9,"y":9,"r":36,"g":63,"b":115,"char":"*","brightness":60.85},
    {"x":10,"y":9,"r":36,"g":63,"b":115,"char":"*","brightness":60.85},
    {"x":11,"y":9,"r":36,"g":63,"b":114,"char":"*","brightness":60.74},
    {"x":12,"y":9,"r":35,"g":62,"b":114,"char":"*","brightness":59.85},
    {"x":13,"y":9,"r":34,"g":61,"b":114,"char":"*","brightness":58.97},
    {"x":14,"y":9,"r":34,"g":61,"b":114,"char":"*","brightness":58.97},
    {"x":15,"y":9,"r":34,"g":61,"b":114,"char":"*","brightness":58.97},
    {"x":16,"y":9,"r":37,"g":64,"b":116,"char":"*","brightness":61.86},
    {"x":17,"y":9,"r":179,"g":190,"b":209,"char":"$","brightness":188.88},
    {"x":18,"y":9,"r":255,"g":255,"b":255,"char":"$","brightness":255.00},
    {"x":19,"y":9,"r":255,"g":255,"b":255,"char":"$","brightness":255.00},
    {"x":20,"y":9,"r":255,"g":255,"b":255,"char":"$","brightness":255.00},
    {"x":21,"y":9,"r":221,"g":227,"b":235,"char":"$","brightness":226.12},
    {"x":22,"y":9,"r":57,"g":82,"b":130,"char":"*","brightness":80.00},
    {"x":23,"y":9,"r":33,"g":60,"b":113,"char":"*","brightness":57.97},
    {"x":24,"y":9,"r":34,"g":62,"b":114,"char":"*","brightness":59.56},
    {"x":25,"y":9,"r":34,"g":62,"b":114,"char":"*","brightness":59.56},
    {"x":26,"y":9,"r":35,"g":62,"b":114,"char":"*","brightness":59.85},
    {"x":27,"y":9,"r":35,"g":62,"b":114,"char":"*","brightness":59.85},
    {"x":28,"y":9,"r":36,"g":62,"b":114,"char":"*","brightness":60.15},
    {"x":29,"y":9,"r":36,"g":62,"b":114,"char":"*","brightness":60.15},
    {"x":30,"y":9,"r":37,"g":64,"b":116,"char":"*","brightness":61.86},
    {"x":31,"y":9,"r":45,"g":81,"b":140,"char":"*","brightness":76.96},
    {"x":32,"y":9,"r":56,"g":107,"b":177,"char":"*","brightness":99.73},
    {"x":33,"y":9,"r":57,"g":110,"b":181,"char":"*","brightness":102.25},
    {"x":34,"y":9,"r":57,"g":110,"b":181,"char":"*","brightness":102.25},
    {"x":35,"y":9,"r":57,"g":111,"b":182,"char":"*","brightness":102.95},
    {"x":36,"y":9,"r":49,"g":91,"b":155,"char":"*","brightness":85.74},
    {"x":37,"y":9,"r":36,"g":63,"b":116,"char":"*","brightness":60.97},
    {"x":38,"y":9,"r":36,"g":63,"b":115,"char":"*","brightness":60.85},
    {"x":39,"y":9,"r":36,"g":63,"b":115,"char":"*","brightness":60.85},
    {"x":40,"y":9,"r":36,"g":63,"b":115,"char":"*","brightness":60.85},
    {"x":41,"y":9,"r":36,"g":61,"b":106,"char":"*","brightness":58.66},
    {"x":0,"y":10,"r":36,"g":61,"b":112,"char":"*","brightness":59.34},
    {"x":1,"y":10,"r":36,"g":63,"b":115,"char":"*","brightness":60.85},
    {"x":2,"y":10,"r":36,"g":63,"b":115,"char":"*","brightness":60.85},
    {"x":3,"y":10,"r":36,"g":63,"b":115,"char":"*","brightness":60.85},
    {"x":4,"y":10,"r":36,"g":63,"b":115,"char":"*","brightness":60.85},
    {"x":5,"y":10,"r":36,"g":63,"b":115,"char":"*","brightness":60.85},
    {"x":6,"y":10,"r":36,"g":63,"b":114,"char":"*","brightness":60.74},
    {"x":7,"y":10,"r":36,"g":62,"b":114,"char":"*","brightness":60.15},
    {"x":8,"y":10,"r":36,"g":63,"b":115,"char":"*","brightness":60.85},
    {"x":9,"y":10,"r":37,"g":65,"b":118,"char":"*","brightness":62.67},
    {"x":10,"y":10,"r":37,"g":67,"b":121,"char":"*","brightness":64.19},
    {"x":11,"y":10,"r":41,"g":70,"b":124,"char":"*","brightness":67.48},
    {"x":12,"y":10,"r":57,"g":82,"b":130,"char":"*","brightness":80.00},
    {"x":13,"y":10,"r":64,"g":87,"b":133,"char":"*","brightness":85.37},
    {"x":14,"y":10,"r":64,"g":87,"b":133,"char":"*","brightness":85.37},
    {"x":15,"y":10,"r":64,"g":86,"b":133,"char":"*","brightness":84.78},
    {"x":16,"y":10,"r":67,"g":89,"b":135,"char":"*","brightness":87.67},
    {"x":17,"y":10,"r":189,"g":198,"b":215,"char":"$","brightness":197.25},
    {"x":18,"y":10,"r":255,"g":255,"b":255,"char":"$","brightness":255.00},
    {"x":19,"y":10,"r":255,"g":255,"b":255,"char":"$","brightness":255.00},
    {"x":20,"y":10,"r":255,"g":255,"b":255,"char":"$","brightness":255.00},
    {"x":21,"y":10,"r":230,"g":234,"b":240,"char":"$","brightness":233.49},
    {"x":22,"y":10,"r":89,"g":109,"b":149,"char":"*","brightness":107.58},
    {"x":23,"y":10,"r":61,"g":83,"b":130,"char":"*","brightness":81.78},
    {"x":24,"y":10,"r":62,"g":85,"b":131,"char":"*","brightness":83.37},
    {"x":25,"y":10,"r":62,"g":85,"b":131,"char":"*","brightness":83.37},
    {"x":26,"y":10,"r":59,"g":83,"b":131,"char":"*","brightness":81.30},
    {"x":27,"y":10,"r":44,"g":73,"b":126,"char":"*","brightness":70.37},
    {"x":28,"y":10,"r":39,"g":71,"b":127,"char":"*","brightness":67.82},
    {"x":29,"y":10,"r":44,"g":79,"b":138,"char":"*","brightness":75.26},
    {"x":30,"y":10,"r":50,"g":94,"b":159,"char":"*","brightness":88.25},
    {"x":31,"y":10,"r":56,"g":108,"b":178,"char":"*","brightness":100.43},
    {"x":32,"y":10,"r":57,"g":110,"b":181,"char":"*","brightness":102.25},
    {"x":33,"y":10,"r":57,"g":110,"b":181,"char":"*","brightness":102.25},
    {"x":34,"y":10,"r":57,"g":111,"b":182,"char":"*","brightness":102.95},
    {"x":35,"y":10,"r":53,"g":100,"b":167,"char":"*","brightness":93.58},
    {"x":36,"y":10,"r":40,"g":70,"b":125,"char":"*","brightness":67.30},
    {"x":37,"y":10,"r":36,"g":63,"b":114,"char":"*","brightness":60.74},
    {"x":38,"y":10,"r":36,"g":63,"b":115,"char":"*","brightness":60.85},
    {"x":39,"y":10,"r":36,"g":63,"b":115,"char":"*","brightness":60.85},
    {"x":40,"y":10,"r":36,"g":63,"b":115,"char":"*","brightness":60.85},
    {"x":41,"y":10,"r":36,"g":61,"b":112,"char":"*","brightness":59.34},
    {"x":0,"y":11,"r":36,"g":63,"b":115,"char":"*","brightness":60.85},
    {"x":1,"y":11,"r":36,"g":63,"b":115,"char":"*","brightness":60.85},
    {"x":2,"y":11,"r":36,"g":63,"b":115,"char":"*","brightness":60.85},
    {"x":3,"y":11,"r":36,"g":63,"b":115,"char":"*","brightness":60.85},
    {"x":4,"y":11,"r":36,"g":63,"b":114,"char":"*","brightness":60.74},
    {"x":5,"y":11,"r":36,"g":63,"b":115,"char":"*","brightness":60.85},
    {"x":6,"y":11,"r":40,"g":70,"b":125,"char":"*","brightness":67.30},
    {"x":7,"y":11,"r":45,"g":82,"b":141,"char":"*","brightness":77.66},
    {"x":8,"y":11,"r":49,"g":92,"b":155,"char":"*","brightness":86.33},
    {"x":9,"y":11,"r":51,"g":98,"b":165,"char":"*","brightness":91.58},
    {"x":10,"y":11,"r":65,"g":110,"b":174,"char":"*","brightness":103.84},
    {"x":11,"y":11,"r":163,"g":183,"b":213,"char":"$","brightness":180.44},
    {"x":12,"y":11,"r":222,"g":226,"b":236,"char":"$","brightness":225.94},
    {"x":13,"y":11,"r":230,"g":232,"b":239,"char":"$","brightness":232.20},
    {"x":14,"y":11,"r":230,"g":232,"b":239,"char":"$","brightness":232.20},
    {"x":15,"y":11,"r":230,"g":232,"b":239,"char":"$","brightness":232.20},
    {"x":16,"y":11,"r":230,"g":232,"b":239,"char":"$","brightness":232.20},
    {"x":17,"y":11,"r":246,"g":247,"b":250,"char":"$","brightness":247.04},
    {"x":18,"y":11,"r":255,"g":255,"b":255,"char":"$","brightness":255.00},
    {"x":19,"y":11,"r":255,"g":255,"b":255,"char":"$","brightness":255.00},
    {"x":20,"y":11,"r":255,"g":255,"b":255,"char":"$","brightness":255.00},
    {"x":21,"y":11,"r":254,"g":254,"b":254,"char":"$","brightness":254.00},
    {"x":22,"y":11,"r":235,"g":237,"b":242,"char":"$","brightness":236.97},
    {"x":23,"y":11,"r":228,"g":230,"b":237,"char":"$","brightness":230.20},
    {"x":24,"y":11,"r":228,"g":230,"b":237,"char":"$","brightness":230.20},
    {"x":25,"y":11,"r":228,"g":230,"b":237,"char":"$","brightness":230.20},
    {"x":26,"y":11,"r":225,"g":228,"b":237,"char":"$","brightness":228.13},
    {"x":27,"y":11,"r":187,"g":202,"b":224,"char":"$","brightness":200.02},
    {"x":28,"y":11,"r":84,"g":128,"b":187,"char":"*","brightness":121.57},
    {"x":29,"y":11,"r":55,"g":108,"b":180,"char":"*","brightness":100.36},
    {"x":30,"y":11,"r":57,"g":111,"b":182,"char":"*","brightness":102.95},
    {"x":31,"y":11,"r":57,"g":111,"b":182,"char":"*","brightness":102.95},
    {"x":32,"y":11,"r":57,"g":111,"b":182,"char":"*","brightness":102.95},
    {"x":33,"y":11,"r":56,"g":108,"b":178,"char":"*","brightness":100.43},
    {"x":34,"y":11,"r":50,"g":93,"b":157,"char":"*","brightness":87.44},
    {"x":35,"y":11,"r":39,"g":70,"b":124,"char":"*","brightness":66.89},
    {"x":36,"y":11,"r":36,"g":63,"b":114,"char":"*","brightness":60.74},
    {"x":37,"y":11,"r":36,"g":63,"b":115,"char":"*","brightness":60.85},
    {"x":38,"y":11,"r":36,"g":63,"b":115,"char":"*","brightness":60.85},
    {"x":39,"y":11,"r":36,"g":63,"b":115,"char":"*","brightness":60.85},
    {"x":40,"y":11,"r":36,"g":63,"b":115,"char":"*","brightness":60.85},
    {"x":41,"y":11,"r":36,"g":63,"b":115,"char":"*","brightness":60.85},
    {"x":0,"y":12,"r":36,"g":63,"b":115,"char":"*","brightness":60.85},
    {"x":1,"y":12,"r":36,"g":63,"b":115,"char":"*","brightness":60.85},
    {"x":2,"y":12,"r":36,"g":63,"b":115,"char":"*","brightness":60.85},
    {"x":3,"y":12,"r":36,"g":63,"b":114,"char":"*","brightness":60.74},
    {"x":4,"y":12,"r":39,"g":70,"b":125,"char":"*","brightness":67.00},
    {"x":5,"y":12,"r":48,"g":90,"b":153,"char":"*","brightness":84.62},
    {"x":6,"y":12,"r":55,"g":105,"b":174,"char":"*","brightness":97.92},
    {"x":7,"y":12,"r":57,"g":110,"b":181,"char":"*","brightness":102.25},
    {"x":8,"y":12,"r":57,"g":111,"b":182,"char":"*","brightness":102.95},
    {"x":9,"y":12,"r":56,"g":110,"b":182,"char":"*","brightness":102.06},
    {"x":10,"y":12,"r":81,"g":127,"b":191,"char":"*","brightness":120.54},
    {"x":11,"y":12,"r":222,"g":231,"b":243,"char":"$","brightness":229.68},
    {"x":12,"y":12,"r":255,"g":255,"b":255,"char":"$","brightness":255.00},
    {"x":13,"y":12,"r":255,"g":255,"b":255,"char":"$","brightness":255.00},
    {"x":14,"y":12,"r":255,"g":255,"b":255,"char":"$","brightness":255.00},
    {"x":15,"y":12,"r":255,"g":255,"b":255,"char":"$","brightness":255.00},
    {"x":16,"y":12,"r":255,"g":255,"b":255,"char":"$","brightness":255.00},
    {"x":17,"y":12,"r":255,"g":255,"b":255,"char":"$","brightness":255.00},
    {"x":18,"y":12,"r":255,"g":255,"b":255,"char":"$","brightness":255.00},
    {"x":19,"y":12,"r":255,"g":255,"b":255,"char":"$","brightness":255.00},
    {"x":20,"y":12,"r":255,"g":255,"b":255,"char":"$","brightness":255.00},
    {"x":21,"y":12,"r":255,"g":255,"b":255,"char":"$","brightness":255.00},
    {"x":22,"y":12,"r":255,"g":255,"b":255,"char":"$","brightness":255.00},
    {"x":23,"y":12,"r":255,"g":255,"b":255,"char":"$","brightness":255.00},
    {"x":24,"y":12,"r":255,"g":255,"b":255,"char":"$","brightness":255.00},
    {"x":25,"y":12,"r":255,"g":255,"b":255,"char":"$","brightness":255.00},
    {"x":26,"y":12,"r":255,"g":255,"b":255,"char":"$","brightness":255.00},
    {"x":27,"y":12,"r":246,"g":249,"b":253,"char":"$","brightness":248.56},
    {"x":28,"y":12,"r":113,"g":152,"b":203,"char":"$","brightness":146.15},
    {"x":29,"y":12,"r":54,"g":108,"b":180,"char":"*","brightness":100.06},
    {"x":30,"y":12,"r":56,"g":108,"b":178,"char":"*","brightness":100.43},
    {"x":31,"y":12,"r":54,"g":102,"b":171,"char":"*","brightness":95.51},
    {"x":32,"y":12,"r":50,"g":92,"b":156,"char":"*","brightness":86.74},
    {"x":33,"y":12,"r":42,"g":76,"b":133,"char":"*","brightness":72.33},
    {"x":34,"y":12,"r":37,"g":64,"b":117,"char":"*","brightness":61.97},
    {"x":35,"y":12,"r":36,"g":63,"b":114,"char":"*","brightness":60.74},
    {"x":36,"y":12,"r":36,"g":63,"b":115,"char":"*","brightness":60.85},
    {"x":37,"y":12,"r":36,"g":63,"b":115,"char":"*","brightness":60.85},
    {"x":38,"y":12,"r":36,"g":63,"b":115,"char":"*","brightness":60.85},
    {"x":39,"y":12,"r":36,"g":63,"b":115,"char":"*","brightness":60.85},
    {"x":40,"y":12,"r":36,"g":63,"b":115,"char":"*","brightness":60.85},
    {"x":41,"y":12,"r":36,"g":61,"b":112,"char":"*","brightness":59.34},
    {"x":0,"y":13,"r":36,"g":63,"b":115,"char":"*","brightness":60.85},
    {"x":1,"y":13,"r":36,"g":63,"b":115,"char":"*","brightness":60.85},
    {"x":2,"y":13,"r":36,"g":63,"b":115,"char":"*","brightness":60.85},
    {"x":3,"y":13,"r":42,"g":76,"b":134,"char":"*","brightness":72.45},
    {"x":4,"y":13,"r":54,"g":103,"b":171,"char":"*","brightness":96.10},
    {"x":5,"y":13,"r":57,"g":111,"b":182,"char":"*","brightness":102.95},
    {"x":6,"y":13,"r":57,"g":110,"b":181,"char":"*","brightness":102.25},
    {"x":7,"y":13,"r":57,"g":110,"b":182,"char":"*","brightness":102.36},
    {"x":8,"y":13,"r":57,"g":109,"b":179,"char":"*","brightness":101.43},
    {"x":9,"y":13,"r":53,"g":101,"b":168,"char":"*","brightness":94.29},
    {"x":10,"y":13,"r":50,"g":93,"b":157,"char":"*","brightness":87.44},
    {"x":11,"y":13,"r":84,"g":113,"b":163,"char":"*","brightness":110.03},
    {"x":12,"y":13,"r":131,"g":147,"b":179,"char":"$","brightness":145.86},
    {"x":13,"y":13,"r":144,"g":155,"b":183,"char":"$","brightness":154.90},
    {"x":14,"y":13,"r":144,"g":155,"b":183,"char":"$","brightness":154.90},
    {"x":15,"y":13,"r":144,"g":155,"b":182,"char":"$","brightness":154.79},
    {"x":16,"y":13,"r":150,"g":161,"b":187,"char":"$","brightness":160.68},
    {"x":17,"y":13,"r":225,"g":229,"b":237,"char":"$","brightness":228.72},
    {"x":18,"y":13,"r":255,"g":255,"b":255,"char":"$","brightness":255.00},
    {"x":19,"y":13,"r":255,"g":255,"b":255,"char":"$","brightness":255.00},
    {"x":20,"y":13,"r":255,"g":255,"b":255,"char":"$","brightness":255.00},
    {"x":21,"y":13,"r":239,"g":241,"b":246,"char":"$","brightness":240.97},
    {"x":22,"y":13,"r":158,"g":169,"b":194,"char":"$","brightness":168.56},
    {"x":23,"y":13,"r":146,"g":158,"b":185,"char":"$","brightness":157.49},
    {"x":24,"y":13,"r":147,"g":158,"b":186,"char":"$","brightness":157.90},
    {"x":25,"y":13,"r":147,"g":159,"b":186,"char":"$","brightness":158.49},
    {"x":26,"y":13,"r":140,"g":154,"b":183,"char":"$","brightness":153.12},
    {"x":27,"y":13,"r":100,"g":125,"b":167,"char":"*","brightness":122.31},
    {"x":28,"y":13,"r":51,"g":88,"b":147,"char":"*","brightness":83.66},
    {"x":29,"y":13,"r":44,"g":80,"b":139,"char":"*","brightness":75.96},
    {"x":30,"y":13,"r":41,"g":74,"b":130,"char":"*","brightness":70.52},
    {"x":31,"y":13,"r":38,"g":67,"b":121,"char":"*","brightness":64.48},
    {"x":32,"y":13,"r":36,"g":63,"b":115,"char":"*","brightness":60.85},
    {"x":33,"y":13,"r":36,"g":62,"b":114,"char":"*","brightness":60.15},
    {"x":34,"y":13,"r":36,"g":63,"b":115,"char":"*","brightness":60.85},
    {"x":35,"y":13,"r":36,"g":63,"b":115,"char":"*","brightness":60.85},
    {"x":36,"y":13,"r":36,"g":63,"b":115,"char":"*","brightness":60.85},
    {"x":37,"y":13,"r":36,"g":63,"b":115,"char":"*","brightness":60.85},
    {"x":38,"y":13,"r":36,"g":63,"b":115,"char":"*","brightness":60.85},
    {"x":39,"y":13,"r":36,"g":63,"b":115,"char":"*","brightness":60.85},
    {"x":40,"y":13,"r":36,"g":63,"b":115,"char":"*","brightness":60.85},
    {"x":41,"y":13,"r":36,"g":61,"b":106,"char":"*","brightness":58.66},
    {"x":0,"y":14,"r":36,"g":63,"b":115,"char":"*","brightness":60.85},
    {"x":1,"y":14,"r":36,"g":63,"b":114,"char":"*","brightness":60.74},
    {"x":2,"y":14,"r":40,"g":71,"b":127,"char":"*","brightness":68.11},
    {"x":3,"y":14,"r":55,"g":104,"b":172,"char":"*","brightness":97.10},
    {"x":4,"y":14,"r":57,"g":111,"b":182,"char":"*","brightness":102.95},
    {"x":5,"y":14,"r":57,"g":110,"b":181,"char":"*","brightness":102.25},
    {"x":6,"y":14,"r":57,"g":110,"b":181,"char":"*","brightness":102.25},
    {"x":7,"y":14,"r":54,"g":103,"b":171,"char":"*","brightness":96.10},
    {"x":8,"y":14,"r":44,"g":80,"b":139,"char":"*","brightness":75.96},
    {"x":9,"y":14,"r":38,"g":66,"b":120,"char":"*","brightness":63.78},
    {"x":10,"y":14,"r":36,"g":63,"b":115,"char":"*","brightness":60.85},
    {"x":11,"y":14,"r":34,"g":61,"b":114,"char":"*","brightness":58.97},
    {"x":12,"y":14,"r":32,"g":60,"b":113,"char":"*","brightness":57.67},
    {"x":13,"y":14,"r":33,"g":60,"b":113,"char":"*","brightness":57.97},
    {"x":14,"y":14,"r":33,"g":60,"b":113,"char":"*","brightness":57.97},
    {"x":15,"y":14,"r":33,"g":60,"b":113,"char":"*","brightness":57.97},
    {"x":16,"y":14,"r":36,"g":63,"b":115,"char":"*","brightness":60.85},
    {"x":17,"y":14,"r":180,"g":191,"b":209,"char":"$","brightness":189.76},
    {"x":18,"y":14,"r":255,"g":255,"b":255,"char":"$","brightness":255.00},
    {"x":19,"y":14,"r":255,"g":255,"b":255,"char":"$","brightness":255.00},
    {"x":20,"y":14,"r":255,"g":255,"b":255,"char":"$","brightness":255.00},
    {"x":21,"y":14,"r":222,"g":227,"b":235,"char":"$","brightness":226.42},
    {"x":22,"y":14,"r":56,"g":81,"b":129,"char":"*","brightness":79.00},
    {"x":23,"y":14,"r":32,"g":59,"b":112,"char":"*","brightness":56.97},
    {"x":24,"y":14,"r":33,"g":60,"b":113,"char":"*","brightness":57.97},
    {"x":25,"y":14,"r":33,"g":60,"b":113,"char":"*","brightness":57.97},
    {"x":26,"y":14,"r":33,"g":60,"b":113,"char":"*","brightness":57.97},
    {"x":27,"y":14,"r":33,"g":60,"b":113,"char":"*","brightness":57.97},
    {"x":28,"y":14,"r":35,"g":62,"b":114,"char":"*","brightness":59.85},
    {"x":29,"y":14,"r":36,"g":62,"b":114,"char":"*","brightness":60.15},
    {"x":30,"y":14,"r":36,"g":62,"b":114,"char":"*","brightness":60.15},
    {"x":31,"y":14,"r":36,"g":63,"b":115,"char":"*","brightness":60.85},
    {"x":32,"y":14,"r":36,"g":63,"b":115,"char":"*","brightness":60.85},
    {"x":33,"y":14,"r":36,"g":63,"b":115,"char":"*","brightness":60.85},
    {"x":34,"y":14,"r":36,"g":63,"b":115,"char":"*","brightness":60.85},
    {"x":35,"y":14,"r":36,"g":63,"b":115,"char":"*","brightness":60.85},
    {"x":36,"y":14,"r":36,"g":63,"b":115,"char":"*","brightness":60.85},
    {"x":37,"y":14,"r":36,"g":63,"b":115,"char":"*","brightness":60.85},
    {"x":38,"y":14,"r":36,"g":63,"b":115,"char":"*","brightness":60.85},
    {"x":39,"y":14,"r":36,"g":63,"b":115,"char":"*","brightness":60.85},
    {"x":40,"y":14,"r":35,"g":62,"b":112,"char":"*","brightness":59.63},
    {"x":41,"y":14,"r":31,"g":60,"b":96,"char":"*","brightness":55.43},
    {"x":0,"y":15,"r":36,"g":63,"b":115,"char":"*","brightness":60.85},
    {"x":1,"y":15,"r":36,"g":63,"b":115,"char":"*","brightness":60.85},
    {"x":2,"y":15,"r":48,"g":88,"b":151,"char":"*","brightness":83.22},
    {"x":3,"y":15,"r":57,"g":111,"b":182,"char":"*","brightness":102.95},
    {"x":4,"y":15,"r":57,"g":110,"b":181,"char":"*","brightness":102.25},
    {"x":5,"y":15,"r":57,"g":110,"b":181,"char":"*","brightness":102.25},
    {"x":6,"y":15,"r":56,"g":107,"b":177,"char":"*","brightness":99.73},
    {"x":7,"y":15,"r":42,"g":75,"b":133,"char":"*","brightness":71.75},
    {"x":8,"y":15,"r":36,"g":62,"b":114,"char":"*","brightness":60.15},
    {"x":9,"y":15,"r":36,"g":63,"b":115,"char":"*","brightness":60.85},
    {"x":10,"y":15,"r":36,"g":63,"b":115,"char":"*","brightness":60.85},
    {"x":11,"y":15,"r":36,"g":63,"b":115,"char":"*","brightness":60.85},
    {"x":12,"y":15,"r":36,"g":63,"b":115,"char":"*","brightness":60.85},
    {"x":13,"y":15,"r":36,"g":63,"b":115,"char":"*","brightness":60.85},
    {"x":14,"y":15,"r":36,"g":63,"b":115,"char":"*","brightness":60.85},
    {"x":15,"y":15,"r":36,"g":63,"b":115,"char":"*","brightness":60.85},
    {"x":16,"y":15,"r":38,"g":65,"b":117,"char":"*","brightness":62.86},
    {"x":17,"y":15,"r":179,"g":190,"b":209,"char":"$","brightness":188.88},
    {"x":18,"y":15,"r":255,"g":255,"b":255,"char":"$","brightness":255.00},
    {"x":19,"y":15,"r":255,"g":255,"b":255,"char":"$","brightness":255.00},
    {"x":20,"y":15,"r":255,"g":255,"b":255,"char":"$","brightness":255.00},
    {"x":21,"y":15,"r":222,"g":227,"b":236,"char":"$","brightness":226.53},
    {"x":22,"y":15,"r":59,"g":83,"b":131,"char":"*","brightness":81.30},
    {"x":23,"y":15,"r":35,"g":62,"b":114,"char":"*","brightness":59.85},
    {"x":24,"y":15,"r":36,"g":63,"b":115,"char":"*","brightness":60.85},
    {"x":25,"y":15,"r":36,"g":63,"b":115,"char":"*","brightness":60.85},
    {"x":26,"y":15,"r":36,"g":63,"b":115,"char":"*","brightness":60.85},
    {"x":27,"y":15,"r":36,"g":63,"b":115,"char":"*","brightness":60.85},
    {"x":28,"y":15,"r":36,"g":63,"b":115,"char":"*","brightness":60.85},
    {"x":29,"y":15,"r":36,"g":63,"b":115,"char":"*","brightness":60.85},
    {"x":30,"y":15,"r":36,"g":63,"b":115,"char":"*","brightness":60.85},
    {"x":31,"y":15,"r":36,"g":63,"b":115,"char":"*","brightness":60.85},
    {"x":32,"y":15,"r":36,"g":63,"b":115,"char":"*","brightness":60.85},
    {"x":33,"y":15,"r":36,"g":63,"b":115,"char":"*","brightness":60.85},
    {"x":34,"y":15,"r":36,"g":63,"b":115,"char":"*","brightness":60.85},
    {"x":35,"y":15,"r":36,"g":63,"b":115,"char":"*","brightness":60.85},
    {"x":36,"y":15,"r":36,"g":63,"b":115,"char":"*","brightness":60.85},
    {"x":37,"y":15,"r":36,"g":63,"b":115,"char":"*","brightness":60.85},
    {"x":38,"y":15,"r":36,"g":63,"b":115,"char":"*","brightness":60.85},
    {"x":39,"y":15,"r":36,"g":63,"b":115,"char":"*","brightness":60.85},
    {"x":40,"y":15,"r":31,"g":59,"b":102,"char":"*","brightness":55.53},
    {"x":41,"y":15,"r":19,"g":36,"b":54,"char":"*","brightness":32.97},
    {"x":0,"y":16,"r":36,"g":63,"b":115,"char":"*","brightness":60.85},
    {"x":1,"y":16,"r":36,"g":63,"b":115,"char":"*","brightness":60.85},
    {"x":2,"y":16,"r":50,"g":94,"b":158,"char":"*","brightness":88.14},
    {"x":3,"y":16,"r":57,"g":111,"b":182,"char":"*","brightness":102.95},
    {"x":4,"y":16,"r":57,"g":110,"b":181,"char":"*","brightness":102.25},
    {"x":5,"y":16,"r":57,"g":110,"b":182,"char":"*","brightness":102.36},
    {"x":6,"y":16,"r":54,"g":103,"b":171,"char":"*","brightness":96.10},
    {"x":7,"y":16,"r":38,"g":67,"b":121,"char":"*","brightness":64.48},
    {"x":8,"y":16,"r":36,"g":63,"b":114,"char":"*","brightness":60.74},
    {"x":9,"y":16,"r":36,"g":63,"b":115,"char":"*","brightness":60.85},
    {"x":10,"y":16,"r":36,"g":63,"b":115,"char":"*","brightness":60.85},
    {"x":11,"y":16,"r":36,"g":63,"b":115,"char":"*","brightness":60.85},
    {"x":12,"y":16,"r":36,"g":63,"b":115,"char":"*","brightness":60.85},
    {"x":13,"y":16,"r":36,"g":63,"b":115,"char":"*","brightness":60.85},
    {"x":14,"y":16,"r":36,"g":63,"b":115,"char":"*","brightness":60.85},
    {"x":15,"y":16,"r":36,"g":63,"b":115,"char":"*","brightness":60.85},
    {"x":16,"y":16,"r":39,"g":66,"b":117,"char":"*","brightness":63.74},
    {"x":17,"y":16,"r":188,"g":196,"b":214,"char":"$","brightness":195.66},
    {"x":18,"y":16,"r":255,"g":255,"b":255,"char":"$","brightness":255.00},
    {"x":19,"y":16,"r":255,"g":255,"b":255,"char":"$","brightness":255.00},
    {"x":20,"y":16,"r":255,"g":255,"b":255,"char":"$","brightness":255.00},
    {"x":21,"y":16,"r":220,"g":224,"b":233,"char":"$","brightness":223.83},
    {"x":22,"y":16,"r":56,"g":80,"b":129,"char":"*","brightness":78.41},
    {"x":23,"y":16,"r":35,"g":62,"b":114,"char":"*","brightness":59.85},
    {"x":24,"y":16,"r":36,"g":63,"b":115,"char":"*","brightness":60.85},
    {"x":25,"y":16,"r":36,"g":63,"b":115,"char":"*","brightness":60.85},
    {"x":26,"y":16,"r":36,"g":63,"b":115,"char":"*","brightness":60.85},
    {"x":27,"y":16,"r":36,"g":63,"b":115,"char":"*","brightness":60.85},
    {"x":28,"y":16,"r":36,"g":63,"b":115,"char":"*","brightness":60.85},
    {"x":29,"y":16,"r":36,"g":63,"b":115,"char":"*","brightness":60.85},
    {"x":30,"y":16,"r":36,"g":63,"b":115,"char":"*","brightness":60.85},
    {"x":31,"y":16,"r":36,"g":63,"b":115,"char":"*","brightness":60.85},
    {"x":32,"y":16,"r":36,"g":63,"b":115,"char":"*","brightness":60.85},
    {"x":33,"y":16,"r":36,"g":63,"b":115,"char":"*","brightness":60.85},
    {"x":34,"y":16,"r":36,"g":63,"b":115,"char":"*","brightness":60.85},
    {"x":35,"y":16,"r":36,"g":63,"b":115,"char":"*","brightness":60.85},
    {"x":36,"y":16,"r":36,"g":63,"b":115,"char":"*","brightness":60.85},
    {"x":37,"y":16,"r":36,"g":63,"b":115,"char":"*","brightness":60.85},
    {"x":38,"y":16,"r":36,"g":63,"b":115,"char":"*","brightness":60.85},
    {"x":39,"y":16,"r":36,"g":60,"b":111,"char":"*","brightness":58.64},
    {"x":40,"y":16,"r":25,"g":55,"b":91,"char":"*","brightness":50.13},
    {"x":41,"y":16,"r":45,"g":50,"b":111,"char":" ","brightness":55.46},
    {"x":0,"y":17,"r":36,"g":63,"b":115,"char":"*","brightness":60.85},
    {"x":1,"y":17,"r":36,"g":62,"b":114,"char":"*","brightness":60.15},
    {"x":2,"y":17,"r":46,"g":84,"b":145,"char":"*","brightness":79.59},
    {"x":3,"y":17,"r":57,"g":110,"b":181,"char":"*","brightness":102.25},
    {"x":4,"y":17,"r":57,"g":110,"b":181,"char":"*","brightness":102.25},
    {"x":5,"y":17,"r":57,"g":110,"b":181,"char":"*","brightness":102.25},
    {"x":6,"y":17,"r":57,"g":109,"b":179,"char":"*","brightness":101.43},
    {"x":7,"y":17,"r":45,"g":82,"b":142,"char":"*","brightness":77.78},
    {"x":8,"y":17,"r":36,"g":63,"b":115,"char":"*","brightness":60.85},
    {"x":9,"y":17,"r":35,"g":62,"b":114,"char":"*","brightness":59.85},
    {"x":10,"y":17,"r":35,"g":62,"b":114,"char":"*","brightness":59.85},
    {"x":11,"y":17,"r":35,"g":63,"b":115,"char":"*","brightness":60.56},
    {"x":12,"y":17,"r":35,"g":63,"b":115,"char":"*","brightness":60.56},
    {"x":13,"y":17,"r":35,"g":62,"b":114,"char":"*","brightness":59.85},
    {"x":14,"y":17,"r":33,"g":61,"b":113,"char":"*","brightness":58.56},
    {"x":15,"y":17,"r":34,"g":61,"b":113,"char":"*","brightness":58.85},
    {"x":16,"y":17,"r":96,"g":115,"b":154,"char":"*","brightness":113.77},
    {"x":17,"y":17,"r":235,"g":236,"b":242,"char":"$","brightness":236.38},
    {"x":18,"y":17,"r":255,"g":255,"b":255,"char":"$","brightness":255.00},
    {"x":19,"y":17,"r":255,"g":255,"b":255,"char":"$","brightness":255.00},
    {"x":20,"y":17,"r":255,"g":255,"b":255,"char":"$","brightness":255.00},
    {"x":21,"y":17,"r":184,"g":191,"b":210,"char":"$","brightness":191.07},
    {"x":22,"y":17,"r":41,"g":67,"b":119,"char":"*","brightness":65.15},
    {"x":23,"y":17,"r":36,"g":63,"b":115,"char":"*","brightness":60.85},
    {"x":24,"y":17,"r":36,"g":63,"b":115,"char":"*","brightness":60.85},
    {"x":25,"y":17,"r":36,"g":63,"b":115,"char":"*","brightness":60.85},
    {"x":26,"y":17,"r":36,"g":63,"b":115,"char":"*","brightness":60.85},
    {"x":27,"y":17,"r":36,"g":63,"b":115,"char":"*","brightness":60.85},
    {"x":28,"y":17,"r":36,"g":63,"b":115,"char":"*","brightness":60.85},
    {"x":29,"y":17,"r":36,"g":63,"b":115,"char":"*","brightness":60.85},
    {"x":30,"y":17,"r":36,"g":63,"b":115,"char":"*","brightness":60.85},
    {"x":31,"y":17,"r":36,"g":63,"b":115,"char":"*","brightness":60.85},
    {"x":32,"y":17,"r":36,"g":63,"b":115,"char":"*","brightness":60.85},
    {"x":33,"y":17,"r":36,"g":63,"b":115,"char":"*","brightness":60.85},
    {"x":34,"y":17,"r":36,"g":63,"b":115,"char":"*","brightness":60.85},
    {"x":35,"y":17,"r":36,"g":63,"b":115,"char":"*","brightness":60.85},
    {"x":36,"y":17,"r":36,"g":63,"b":115,"char":"*","brightness":60.85},
    {"x":37,"y":17,"r":36,"g":63,"b":115,"char":"*","brightness":60.85},
    {"x":38,"y":17,"r":33,"g":58,"b":110,"char":"*","brightness":56.45},
    {"x":39,"y":17,"r":33,"g":50,"b":90,"char":"*","brightness":49.48},
    {"x":40,"y":17,"r":30,"g":116,"b":139,"char":" ","brightness":92.91},
    {"x":41,"y":17,"r":6,"g":23,"b":59,"char":" ","brightness":22.02},
    {"x":0,"y":18,"r":36,"g":63,"b":115,"char":"*","brightness":60.85},
    {"x":1,"y":18,"r":36,"g":63,"b":115,"char":"*","brightness":60.85},
    {"x":2,"y":18,"r":39,"g":68,"b":122,"char":"*","brightness":65.48},
    {"x":3,"y":18,"r":52,"g":98,"b":165,"char":"*","brightness":91.88},
    {"x":4,"y":18,"r":57,"g":111,"b":182,"char":"*","brightness":102.95},
    {"x":5,"y":18,"r":57,"g":110,"b":181,"char":"*","brightness":102.25},
    {"x":6,"y":18,"r":57,"g":110,"b":181,"char":"*","brightness":102.25},
    {"x":7,"y":18,"r":56,"g":107,"b":177,"char":"*","brightness":99.73},
    {"x":8,"y":18,"r":48,"g":89,"b":153,"char":"*","brightness":84.04},
    {"x":9,"y":18,"r":49,"g":79,"b":133,"char":"*","brightness":76.19},
    {"x":10,"y":18,"r":50,"g":76,"b":125,"char":"*","brightness":73.81},
    {"x":11,"y":18,"r":45,"g":70,"b":120,"char":"*","brightness":68.22},
    {"x":12,"y":18,"r":45,"g":70,"b":120,"char":"*","brightness":68.22},
    {"x":13,"y":18,"r":53,"g":78,"b":126,"char":"*","brightness":76.00},
    {"x":14,"y":18,"r":80,"g":101,"b":143,"char":"*","brightness":99.51},
    {"x":15,"y":18,"r":146,"g":159,"b":185,"char":"$","brightness":158.08},
    {"x":16,"y":18,"r":232,"g":234,"b":240,"char":"$","brightness":234.09},
    {"x":17,"y":18,"r":255,"g":255,"b":255,"char":"$","brightness":255.00},
    {"x":18,"y":18,"r":255,"g":255,"b":255,"char":"$","brightness":255.00},
    {"x":19,"y":18,"r":255,"g":255,"b":255,"char":"$","brightness":255.00},
    {"x":20,"y":18,"r":230,"g":232,"b":239,"char":"$","brightness":232.20},
    {"x":21,"y":18,"r":88,"g":107,"b":148,"char":"*","brightness":105.99},
    {"x":22,"y":18,"r":34,"g":61,"b":114,"char":"*","brightness":58.97},
    {"x":23,"y":18,"r":36,"g":63,"b":115,"char":"*","brightness":60.85},
    {"x":24,"y":18,"r":36,"g":63,"b":115,"char":"*","brightness":60.85},
    {"x":25,"y":18,"r":36,"g":63,"b":115,"char":"*","brightness":60.85},
    {"x":26,"y":18,"r":36,"g":63,"b":115,"char":"*","brightness":60.85},
    {"x":27,"y":18,"r":36,"g":63,"b":115,"char":"*","brightness":60.85},
    {"x":28,"y":18,"r":36,"g":63,"b":115,"char":"*","brightness":60.85},
    {"x":29,"y":18,"r":36,"g":63,"b":115,"char":"*","brightness":60.85},
    {"x":30,"y":18,"r":36,"g":63,"b":115,"char":"*","brightness":60.85},
    {"x":31,"y":18,"r":36,"g":63,"b":115,"char":"*","brightness":60.85},
    {"x":32,"y":18,"r":36,"g":63,"b":115,"char":"*","brightness":60.85},
    {"x":33,"y":18,"r":36,"g":63,"b":115,"char":"*","brightness":60.85},
    {"x":34,"y":18,"r":36,"g":63,"b":115,"char":"*","brightness":60.85},
    {"x":35,"y":18,"r":36,"g":63,"b":115,"char":"*","brightness":60.85},
    {"x":36,"y":18,"r":35,"g":62,"b":113,"char":"*","brightness":59.74},
    {"x":37,"y":18,"r":33,"g":59,"b":105,"char":"*","brightness":56.47},
    {"x":38,"y":18,"r":24,"g":48,"b":93,"char":"*","brightness":45.95},
    {"x":39,"y":18,"r":56,"g":97,"b":135,"char":" ","brightness":89.07},
    {"x":40,"y":18,"r":17,"g":15,"b":55,"char":" ","brightness":20.16},
    {"x":41,"y":18,"r":14,"g":17,"b":80,"char":" ","brightness":23.29},
    {"x":0,"y":19,"r":36,"g":63,"b":115,"char":"*","brightness":60.85},
    {"x":1,"y":19,"r":36,"g":63,"b":115,"char":"*","brightness":60.85},
    {"x":2,"y":19,"r":36,"g":63,"b":114,"char":"*","brightness":60.74},
    {"x":3,"y":19,"r":40,"g":70,"b":125,"char":"*","brightness":67.30},
    {"x":4,"y":19,"r":51,"g":95,"b":160,"char":"*","brightness":89.25},
    {"x":5,"y":19,"r":57,"g":109,"b":180,"char":"*","brightness":101.55},
    {"x":6,"y":19,"r":57,"g":110,"b":182,"char":"*","brightness":102.36},
    {"x":7,"y":19,"r":63,"g":114,"b":184,"char":"*","brightness":106.73},
    {"x":8,"y":19,"r":143,"g":173,"b":214,"char":"$","brightness":168.70},
    {"x":9,"y":19,"r":205,"g":216,"b":233,"char":"$","brightness":214.65},
    {"x":10,"y":19,"r":213,"g":218,"b":229,"char":"$","brightness":217.76},
    {"x":11,"y":19,"r":202,"g":208,"b":221,"char":"$","brightness":207.69},
    {"x":12,"y":19,"r":202,"g":208,"b":221,"char":"$","brightness":207.69},
    {"x":13,"y":19,"r":217,"g":221,"b":230,"char":"$","brightness":220.83},
    {"x":14,"y":19,"r":240,"g":241,"b":245,"char":"$","brightness":241.16},
    {"x":15,"y":19,"r":255,"g":255,"b":255,"char":"$","brightness":255.00},
    {"x":16,"y":19,"r":255,"g":255,"b":255,"char":"$","brightness":255.00},
    {"x":17,"y":19,"r":255,"g":255,"b":255,"char":"$","brightness":255.00},
    {"x":18,"y":19,"r":255,"g":255,"b":255,"char":"$","brightness":255.00},
    {"x":19,"y":19,"r":211,"g":215,"b":227,"char":"$","brightness":215.17},
    {"x":20,"y":19,"r":94,"g":113,"b":152,"char":"*","brightness":111.77},
    {"x":21,"y":19,"r":35,"g":62,"b":114,"char":"*","brightness":59.85},
    {"x":22,"y":19,"r":36,"g":63,"b":115,"char":"*","brightness":60.85},
    {"x":23,"y":19,"r":36,"g":63,"b":115,"char":"*","brightness":60.85},
    {"x":24,"y":19,"r":36,"g":63,"b":115,"char":"*","brightness":60.85},
    {"x":25,"y":19,"r":36,"g":63,"b":115,"char":"*","brightness":60.85},
    {"x":26,"y":19,"r":36,"g":63,"b":115,"char":"*","brightness":60.85},
    {"x":27,"y":19,"r":36,"g":63,"b":115,"char":"*","brightness":60.85},
    {"x":28,"y":19,"r":36,"g":63,"b":115,"char":"*","brightness":60.85},
    {"x":29,"y":19,"r":36,"g":63,"b":115,"char":"*","brightness":60.85},
    {"x":30,"y":19,"r":36,"g":63,"b":115,"char":"*","brightness":60.85},
    {"x":31,"y":19,"r":36,"g":63,"b":115,"char":"*","brightness":60.85},
    {"x":32,"y":19,"r":36,"g":63,"b":115,"char":"*","brightness":60.85},
    {"x":33,"y":19,"r":36,"g":63,"b":115,"char":"*","brightness":60.85},
    {"x":34,"y":19,"r":35,"g":62,"b":114,"char":"*","brightness":59.85},
    {"x":35,"y":19,"r":39,"g":66,"b":112,"char":"*","brightness":63.17},
    {"x":36,"y":19,"r":38,"g":69,"b":111,"char":"*","brightness":64.52},
    {"x":37,"y":19,"r":31,"g":57,"b":119,"char":"*","brightness":56.29},
    {"x":38,"y":19,"r":44,"g":74,"b":237,"char":" ","brightness":83.61},
    {"x":39,"y":19,"r":35,"g":58,"b":255,"char":" ","brightness":73.58},
    {"x":40,"y":19,"r":1,"g":3,"b":255,"char":" ","brightness":31.13},
    {"x":41,"y":19,"r":0,"g":0,"b":0,"char":" ","brightness":0.00},
    {"x":0,"y":20,"r":35,"g":62,"b":113,"char":"*","brightness":59.74},
    {"x":1,"y":20,"r":36,"g":63,"b":115,"char":"*","brightness":60.85},
    {"x":2,"y":20,"r":36,"g":63,"b":115,"char":"*","brightness":60.85},
    {"x":3,"y":20,"r":36,"g":63,"b":114,"char":"*","brightness":60.74},
    {"x":4,"y":20,"r":37,"g":65,"b":118,"char":"*","brightness":62.67},
    {"x":5,"y":20,"r":44,"g":79,"b":138,"char":"*","brightness":75.26},
    {"x":6,"y":20,"r":50,"g":96,"b":162,"char":"*","brightness":89.77},
    {"x":7,"y":20,"r":73,"g":119,"b":183,"char":"*","brightness":112.54},
    {"x":8,"y":20,"r":216,"g":226,"b":240,"char":"$","brightness":224.61},
    {"x":9,"y":20,"r":255,"g":255,"b":255,"char":"$","brightness":255.00},
    {"x":10,"y":20,"r":255,"g":255,"b":255,"char":"$","brightness":255.00},
    {"x":11,"y":20,"r":255,"g":255,"b":255,"char":"$","brightness":255.00},
    {"x":12,"y":20,"r":255,"g":255,"b":255,"char":"$","brightness":255.00},
    {"x":13,"y":20,"r":255,"g":255,"b":255,"char":"$","brightness":255.00},
    {"x":14,"y":20,"r":255,"g":255,"b":255,"char":"$","brightness":255.00},
    {"x":15,"y":20,"r":255,"g":255,"b":255,"char":"$","brightness":255.00},
    {"x":16,"y":20,"r":244,"g":245,"b":248,"char":"$","brightness":245.04},
    {"x":17,"y":20,"r":208,"g":213,"b":225,"char":"$","brightness":212.87},
    {"x":18,"y":20,"r":136,"g":150,"b":179,"char":"$","brightness":149.12},
    {"x":19,"y":20,"r":59,"g":83,"b":130,"char":"*","brightness":81.18},
    {"x":20,"y":20,"r":34,"g":61,"b":113,"char":"*","brightness":58.85},
    {"x":21,"y":20,"r":36,"g":63,"b":115,"char":"*","brightness":60.85},
    {"x":22,"y":20,"r":36,"g":63,"b":115,"char":"*","brightness":60.85},
    {"x":23,"y":20,"r":36,"g":63,"b":115,"char":"*","brightness":60.85},
    {"x":24,"y":20,"r":36,"g":63,"b":115,"char":"*","brightness":60.85},
    {"x":25,"y":20,"r":36,"g":63,"b":115,"char":"*","brightness":60.85},
    {"x":26,"y":20,"r":36,"g":63,"b":115,"char":"*","brightness":60.85},
    {"x":27,"y":20,"r":36,"g":63,"b":115,"char":"*","brightness":60.85},
    {"x":28,"y":20,"r":36,"g":63,"b":115,"char":"*","brightness":60.85},
    {"x":29,"y":20,"r":36,"g":63,"b":115,"char":"*","brightness":60.85},
    {"x":30,"y":20,"r":36,"g":63,"b":115,"char":"*","brightness":60.85},
    {"x":31,"y":20,"r":36,"g":63,"b":115,"char":"*","brightness":60.85},
    {"x":32,"y":20,"r":35,"g":62,"b":114,"char":"*","brightness":59.85},
    {"x":33,"y":20,"r":37,"g":62,"b":110,"char":"*","brightness":60.00},
    {"x":34,"y":20,"r":33,"g":55,"b":97,"char":"*","brightness":53.21},
    {"x":35,"y":20,"r":28,"g":62,"b":126,"char":"*","brightness":59.13},
    {"x":36,"y":20,"r":41,"g":79,"b":200,"char":"*","brightness":81.43},
    {"x":37,"y":20,"r":47,"g":95,"b":191,"char":"*","brightness":91.59},
    {"x":38,"y":20,"r":41,"g":88,"b":201,"char":"*","brightness":86.83},
    {"x":39,"y":20,"r":4,"g":9,"b":252,"char":" ","brightness":35.21},
    {"x":40,"y":20,"r":2,"g":4,"b":253,"char":" ","brightness":31.79},
    {"x":41,"y":20,"r":0,"g":0,"b":0,"char":" ","brightness":0.00},
    {"x":0,"y":21,"r":33,"g":60,"b":101,"char":"*","brightness":56.60},
    {"x":1,"y":21,"r":36,"g":63,"b":113,"char":"*","brightness":60.63},
    {"x":2,"y":21,"r":36,"g":63,"b":115,"char":"*","brightness":60.85},
    {"x":3,"y":21,"r":36,"g":63,"b":115,"char":"*","brightness":60.85},
    {"x":4,"y":21,"r":36,"g":63,"b":115,"char":"*","brightness":60.85},
    {"x":5,"y":21,"r":36,"g":62,"b":114,"char":"*","brightness":60.15},
    {"x":6,"y":21,"r":37,"g":65,"b":117,"char":"*","brightness":62.56},
    {"x":7,"y":21,"r":41,"g":72,"b":128,"char":"*","brightness":69.11},
    {"x":8,"y":21,"r":79,"g":106,"b":153,"char":"*","brightness":103.28},
    {"x":9,"y":21,"r":141,"g":156,"b":185,"char":"$","brightness":154.82},
    {"x":10,"y":21,"r":173,"g":182,"b":203,"char":"$","brightness":181.70},
    {"x":11,"y":21,"r":187,"g":195,"b":212,"char":"$","brightness":194.55},
    {"x":12,"y":21,"r":188,"g":196,"b":213,"char":"$","brightness":195.55},
    {"x":13,"y":21,"r":180,"g":189,"b":207,"char":"$","brightness":188.36},
    {"x":14,"y":21,"r":160,"g":171,"b":194,"char":"$","brightness":170.33},
    {"x":15,"y":21,"r":128,"g":142,"b":174,"char":"$","brightness":141.46},
    {"x":16,"y":21,"r":87,"g":107,"b":148,"char":"*","brightness":105.69},
    {"x":17,"y":21,"r":50,"g":75,"b":124,"char":"*","brightness":73.11},
    {"x":18,"y":21,"r":34,"g":61,"b":114,"char":"*","brightness":58.97},
    {"x":19,"y":21,"r":34,"g":62,"b":114,"char":"*","brightness":59.56},
    {"x":20,"y":21,"r":36,"g":63,"b":115,"char":"*","brightness":60.85},
    {"x":21,"y":21,"r":36,"g":63,"b":115,"char":"*","brightness":60.85},
    {"x":22,"y":21,"r":36,"g":63,"b":115,"char":"*","brightness":60.85},
    {"x":23,"y":21,"r":36,"g":63,"b":115,"char":"*","brightness":60.85},
    {"x":24,"y":21,"r":36,"g":63,"b":115,"char":"*","brightness":60.85},
    {"x":25,"y":21,"r":36,"g":63,"b":115,"char":"*","brightness":60.85},
    {"x":26,"y":21,"r":36,"g":63,"b":115,"char":"*","brightness":60.85},
    {"x":27,"y":21,"r":36,"g":63,"b":114,"char":"*","brightness":60.74},
    {"x":28,"y":21,"r":35,"g":63,"b":114,"char":"*","brightness":60.44},
    {"x":29,"y":21,"r":35,"g":64,"b":114,"char":"*","brightness":61.03},
    {"x":30,"y":21,"r":35,"g":62,"b":110,"char":"*","brightness":59.40},
    {"x":31,"y":21,"r":35,"g":59,"b":104,"char":"*","brightness":56.95},
    {"x":32,"y":21,"r":29,"g":56,"b":103,"char":"*","brightness":53.28},
    {"x":33,"y":21,"r":33,"g":59,"b":91,"char":"*","brightness":54.87},
    {"x":34,"y":21,"r":26,"g":74,"b":174,"char":" ","brightness":71.05},
    {"x":35,"y":21,"r":0,"g":0,"b":255,"char":" ","brightness":29.07},
    {"x":36,"y":21,"r":28,"g":65,"b":205,"char":"*","brightness":69.90},
    {"x":37,"y":21,"r":40,"g":112,"b":190,"char":"*","brightness":99.36},
    {"x":38,"y":21,"r":32,"g":115,"b":213,"char":"*","brightness":101.35},
    {"x":39,"y":21,"r":1,"g":14,"b":253,"char":" ","brightness":37.36},
    {"x":40,"y":21,"r":1,"g":4,"b":254,"char":" ","brightness":31.60},
    {"x":41,"y":21,"r":0,"g":0,"b":0,"char":" ","brightness":0.00},
    {"x":0,"y":22,"r":30,"g":48,"b":67,"char":"*","brightness":44.78},
    {"x":1,"y":22,"r":30,"g":57,"b":93,"char":"*","brightness":53.03},
    {"x":2,"y":22,"r":35,"g":63,"b":110,"char":"*","brightness":59.99},
    {"x":3,"y":22,"r":34,"g":62,"b":112,"char":"*","brightness":59.33},
    {"x":4,"y":22,"r":36,"g":63,"b":114,"char":"*","brightness":60.74},
    {"x":5,"y":22,"r":36,"g":63,"b":115,"char":"*","brightness":60.85},
    {"x":6,"y":22,"r":36,"g":63,"b":115,"char":"*","brightness":60.85},
    {"x":7,"y":22,"r":36,"g":62,"b":114,"char":"*","brightness":60.15},
    {"x":8,"y":22,"r":33,"g":60,"b":113,"char":"*","brightness":57.97},
    {"x":9,"y":22,"r":33,"g":60,"b":113,"char":"*","brightness":57.97},
    {"x":10,"y":22,"r":37,"g":63,"b":115,"char":"*","brightness":61.15},
    {"x":11,"y":22,"r":40,"g":66,"b":118,"char":"*","brightness":64.15},
    {"x":12,"y":22,"r":40,"g":66,"b":118,"char":"*","brightness":64.15},
    {"x":13,"y":22,"r":38,"g":65,"b":116,"char":"*","brightness":62.74},
    {"x":14,"y":22,"r":34,"g":61,"b":114,"char":"*","brightness":58.97},
    {"x":15,"y":22,"r":32,"g":59,"b":112,"char":"*","brightness":56.97},
    {"x":16,"y":22,"r":33,"g":60,"b":113,"char":"*","brightness":57.97},
    {"x":17,"y":22,"r":35,"g":62,"b":114,"char":"*","brightness":59.85},
    {"x":18,"y":22,"r":36,"g":63,"b":115,"char":"*","brightness":60.85},
    {"x":19,"y":22,"r":36,"g":63,"b":115,"char":"*","brightness":60.85},
    {"x":20,"y":22,"r":36,"g":63,"b":115,"char":"*","brightness":60.85},
    {"x":21,"y":22,"r":36,"g":63,"b":115,"char":"*","brightness":60.85},
    {"x":22,"y":22,"r":36,"g":63,"b":115,"char":"*","brightness":60.85},
    {"x":23,"y":22,"r":35,"g":60,"b":110,"char":"*","brightness":58.23},
    {"x":24,"y":22,"r":37,"g":62,"b":112,"char":"*","brightness":60.22},
    {"x":25,"y":22,"r":35,"g":63,"b":111,"char":"*","brightness":60.10},
    {"x":26,"y":22,"r":33,"g":62,"b":108,"char":"*","brightness":58.57},
    {"x":27,"y":22,"r":32,"g":55,"b":98,"char":"*","brightness":53.02},
    {"x":28,"y":22,"r":29,"g":55,"b":95,"char":"*","brightness":51.79},
    {"x":29,"y":22,"r":27,"g":72,"b":108,"char":"*","brightness":62.65},
    {"x":30,"y":22,"r":30,"g":59,"b":88,"char":"*","brightness":53.63},
    {"x":31,"y":22,"r":0,"g":0,"b":0,"char":" ","brightness":0.00},
    {"x":32,"y":22,"r":33,"g":58,"b":109,"char":" ","brightness":56.34},
    {"x":33,"y":22,"r":33,"g":61,"b":95,"char":" ","brightness":56.50},
    {"x":34,"y":22,"r":79,"g":0,"b":0,"char":" ","brightness":23.62},
    {"x":35,"y":22,"r":11,"g":19,"b":244,"char":" ","brightness":42.26},
    {"x":36,"y":22,"r":30,"g":67,"b":204,"char":" ","brightness":71.56},
    {"x":37,"y":22,"r":40,"g":111,"b":190,"char":" ","brightness":98.78},
    {"x":38,"y":22,"r":33,"g":114,"b":213,"char":" ","brightness":101.07},
    {"x":39,"y":22,"r":2,"g":15,"b":252,"char":" ","brightness":38.13},
    {"x":40,"y":22,"r":1,"g":4,"b":254,"char":" ","brightness":31.60},
    {"x":41,"y":22,"r":0,"g":0,"b":0,"char":" ","brightness":0.00}
  ]
}
